Workbook
Name Tolerance: Settings!$B$2

Sheet README
A1: Audit ledger — example workbook
A2: Built from workbook.md on 2026-09-13 with generic names. Sample data only: Project Alpha, Vendor A, Vendor B.
A4: How to read the colours
A5: Blue text on a yellow fill = data you paste or type. Black text = formulas; do not edit.
A7: Sheets
A8: Lines Every row from every Stage 1 CSV, pasted under the last row. Columns A–V are the CSV; W onward are helper formulas that must be filled down to the last row.
A9: Mapping The label table. Paste this whole range into every Stage 1 chat. Add a row when Review shows 'no mapping rule'.
A10: Docs One row per document, derived from the coverage rows. Stated totals vs extracted totals, sum checks, page coverage.
A11: Tracker One row per project and vendor. Quoted vs invoiced by category, variance, discrepancy flag.
A12: Detail Every line that differs between a quote and its invoices: quote only, invoice only, or amount differs.
A13: Review Everything a human should look at. Empty means no PDF needs opening.
A14: Notes Where Stage 3 output is pasted. Tracker and Detail look notes up from here.
... A26: workbook.md sketches Docs, Tracker, Detail and Review with FILTER, UNIQUE and VSTACK. This file uses the equivalent INDEX/MATCH helper-column pattern so it works in every Excel version and could be verified outside Excel. Same results, longer formulas.

Sheet Settings
A1: Setting | B1: Value
A2: Tolerance (amounts within this are 'matched exactly') | B2: 0.01
A4: Billing standards (paste into the Stage 3 chat)
A5: 1. Labour is billed at the quoted fixed rate unless a signed change order authorises time and materials.
A6: 2. Installation cost is itemised as a distinct line from product cost.
A7: 3. Product cost is invoiced consistent with the manufacturer-confirmed quote.
A8: 4. Allowance items require documented approval before being invoiced.

Sheet Lines
A1: row_kind | B1: project | C1: vendor | D1: doc_type | E1: doc_id | F1: doc_date | G1: ref_quote_id | H1: page | I1: line_no | J1: label_as_printed | K1: description | L1: qty | M1: unit_amount | N1: amount | O1: category | P1: confidence | Q1: note | R1: pages_total | S1: pages_read | T1: native_or_scan | U1: mapping_provided | V1: source_file | W1: match_key | X1: labour_group | Y1: invoice_amount | Z1: invoice_hits | AA1: quote_hits | AB1: status | AC1: detail_seq | AD1: review_reason | AE1: review_seq | AF1: coverage_seq | AG1: pair_seq
A2: line | B2: Project Alpha | C2: Vendor A | D2: quote | E2: Q-1001 | F2: 2026-05-04 | H2: 1 | I2: 1 | J2: Task chair TC-200 | K2: Task chair, model TC-200 | L2: 40 | M2: 350 | N2: 14000 | O2: PRODUCT | P2: H | V2: Project Alpha__Vendor A__quote__Q-1001.pdf | W2: =IF(A2="line",IF(D2="quote",E2,G2)&"|"&LOWER(TRIM(K2)),"") | X2: =IF(OR(O2="LABOUR",O2="INSTALL"),"LABOUR_ALL",IF(O2="","",O2)) | Y2: =IF(AND(A2="line",D2="quote"),SUMIFS($N$2:$N$500,$W$2:$W$500,W2,$D$2:$D$500,"invoice",$A$2:$A$500,"line"),"") | Z2: =IF(AND(A2="line",D2="quote"),COUNTIFS($W$2:$W$500,W2,$D$2:$D$500,"invoice",$A$2:$A$500,"line"),"") | AA2: =IF(AND(A2="line",D2="invoice"),COUNTIFS($W$2:$W$500,W2,$D$2:$D$500,"quote",$A$2:$A$500,"line"),"") | AB2: =IF(A2<>"line","",IF(D2="quote",IF(Z2=0,"quote only",IF(ABS(Y2-N2)>Settings!$B$2,"amount differs","match")),IF(AA2=0,"invoice only","match"))) | AC2: =IF(AND(A2="line",AB2<>"match",COUNTIFS($A$2:$A$500,"coverage",$B$2:$B$500,B2,$C$2:$C$500,C2,$D$2:$D$500,"invoice")>0),MAX($AC$1:AC1)+1,"") | AD2: =IF(A2<>"line","",IF(O2="UNMAPPED","no mapping rule",IF(P2="L","low confidence",""))) | AE2: =IF(AD2<>"",MAX($AE$1:AE1)+1,"") | AF2: =IF(A2="coverage",MAX($AF$1:AF1)+1,"") | AG2: =IF(A2="line",IF(COUNTIFS($B$1:B1,B2,$C$1:C1,C2,$A$1:A1,"line")=0,MAX($AG$1:AG1)+1,""),"")
A3: line | B3: Project Alpha | C3: Vendor A | D3: quote | E3: Q-1001 | F3: 2026-05-04 | H3: 1 | I3: 2 | J3: Desk HA-1600 | K3: Height-adjustable desk 1600 | L3: 40 | M3: 620 | N3: 24800 | O3: PRODUCT | P3: H | V3: Project Alpha__Vendor A__quote__Q-1001.pdf | W3: =IF(A3="line",IF(D3="quote",E3,G3)&"|"&LOWER(TRIM(K3)),"") | X3: =IF(OR(O3="LABOUR",O3="INSTALL"),"LABOUR_ALL",IF(O3="","",O3)) | Y3: =IF(AND(A3="line",D3="quote"),SUMIFS($N$2:$N$500,$W$2:$W$500,W3,$D$2:$D$500,"invoice",$A$2:$A$500,"line"),"") | Z3: =IF(AND(A3="line",D3="quote"),COUNTIFS($W$2:$W$500,W3,$D$2:$D$500,"invoice",$A$2:$A$500,"line"),"") | AA3: =IF(AND(A3="line",D3="invoice"),COUNTIFS($W$2:$W$500,W3,$D$2:$D$500,"quote",$A$2:$A$500,"line"),"") | AB3: =IF(A3<>"line","",IF(D3="quote",IF(Z3=0,"quote only",IF(ABS(Y3-N3)>Settings!$B$2,"amount differs","match")),IF(AA3=0,"invoice only","match"))) | AC3: =IF(AND(A3="line",AB3<>"match",COUNTIFS($A$2:$A$500,"coverage",$B$2:$B$500,B3,$C$2:$C$500,C3,$D$2:$D$500,"invoice")>0),MAX($AC$1:AC2)+1,"") | AD3: =IF(A3<>"line","",IF(O3="UNMAPPED","no mapping rule",IF(P3="L","low confidence",""))) | AE3: =IF(AD3<>"",MAX($AE$1:AE2)+1,"") | AF3: =IF(A3="coverage",MAX($AF$1:AF2)+1,"") | AG3: =IF(A3="line",IF(COUNTIFS($B$1:B2,B3,$C$1:C2,C3,$A$1:A2,"line")=0,MAX($AG$1:AG2)+1,""),"")
A4: line | B4: Project Alpha | C4: Vendor A | D4: quote | E4: Q-1001 | F4: 2026-05-04 | H4: 2 | I4: 3 | J4: Pedestal | K4: Storage pedestal | L4: 40 | M4: 180 | N4: 7200 | O4: PRODUCT | P4: H | V4: Project Alpha__Vendor A__quote__Q-1001.pdf | W4: =IF(A4="line",IF(D4="quote",E4,G4)&"|"&LOWER(TRIM(K4)),"") | X4: =IF(OR(O4="LABOUR",O4="INSTALL"),"LABOUR_ALL",IF(O4="","",O4)) | Y4: =IF(AND(A4="line",D4="quote"),SUMIFS($N$2:$N$500,$W$2:$W$500,W4,$D$2:$D$500,"invoice",$A$2:$A$500,"line"),"") | Z4: =IF(AND(A4="line",D4="quote"),COUNTIFS($W$2:$W$500,W4,$D$2:$D$500,"invoice",$A$2:$A$500,"line"),"") | AA4: =IF(AND(A4="line",D4="invoice"),COUNTIFS($W$2:$W$500,W4,$D$2:$D$500,"quote",$A$2:$A$500,"line"),"") | AB4: =IF(A4<>"line","",IF(D4="quote",IF(Z4=0,"quote only",IF(ABS(Y4-N4)>Settings!$B$2,"amount differs","match")),IF(AA4=0,"invoice only","match"))) | AC4: =IF(AND(A4="line",AB4<>"match",COUNTIFS($A$2:$A$500,"coverage",$B$2:$B$500,B4,$C$2:$C$500,C4,$D$2:$D$500,"invoice")>0),MAX($AC$1:AC3)+1,"") | AD4: =IF(A4<>"line","",IF(O4="UNMAPPED","no mapping rule",IF(P4="L","low confidence",""))) | AE4: =IF(AD4<>"",MAX($AE$1:AE3)+1,"") | AF4: =IF(A4="coverage",MAX($AF$1:AF3)+1,"") | AG4: =IF(A4="line",IF(COUNTIFS($B$1:B3,B4,$C$1:C3,C4,$A$1:A3,"line")=0,MAX($AG$1:AG3)+1,""),"")
A5: line | B5: Project Alpha | C5: Vendor A | D5: quote | E5: Q-1001 | F5: 2026-05-04 | H5: 2 | I5: 4 | J5: Installation | K5: Installation, 40 workstations, fixed price | N5: 9600 | O5: INSTALL | P5: H | V5: Project Alpha__Vendor A__quote__Q-1001.pdf | W5: =IF(A5="line",IF(D5="quote",E5,G5)&"|"&LOWER(TRIM(K5)),"") | X5: =IF(OR(O5="LABOUR",O5="INSTALL"),"LABOUR_ALL",IF(O5="","",O5)) | Y5: =IF(AND(A5="line",D5="quote"),SUMIFS($N$2:$N$500,$W$2:$W$500,W5,$D$2:$D$500,"invoice",$A$2:$A$500,"line"),"") | Z5: =IF(AND(A5="line",D5="quote"),COUNTIFS($W$2:$W$500,W5,$D$2:$D$500,"invoice",$A$2:$A$500,"line"),"") | AA5: =IF(AND(A5="line",D5="invoice"),COUNTIFS($W$2:$W$500,W5,$D$2:$D$500,"quote",$A$2:$A$500,"line"),"") | AB5: =IF(A5<>"line","",IF(D5="quote",IF(Z5=0,"quote only",IF(ABS(Y5-N5)>Settings!$B$2,"amount differs","match")),IF(AA5=0,"invoice only","match"))) | AC5: =IF(AND(A5="line",AB5<>"match",COUNTIFS($A$2:$A$500,"coverage",$B$2:$B$500,B5,$C$2:$C$500,C5,$D$2:$D$500,"invoice")>0),MAX($AC$1:AC4)+1,"") | AD5: =IF(A5<>"line","",IF(O5="UNMAPPED","no mapping rule",IF(P5="L","low confidence",""))) | AE5: =IF(AD5<>"",MAX($AE$1:AE4)+1,"") | AF5: =IF(A5="coverage",MAX($AF$1:AF4)+1,"") | AG5: =IF(A5="line",IF(COUNTIFS($B$1:B4,B5,$C$1:C4,C5,$A$1:A4,"line")=0,MAX($AG$1:AG4)+1,""),"")
A6: line | B6: Project Alpha | C6: Vendor A | D6: quote | E6: Q-1001 | F6: 2026-05-04 | H6: 2 | I6: 5 | J6: Project management | K6: Project management fee | N6: 2400 | O6: LABOUR | P6: H | V6: Project Alpha__Vendor A__quote__Q-1001.pdf | W6: =IF(A6="line",IF(D6="quote",E6,G6)&"|"&LOWER(TRIM(K6)),"") | X6: =IF(OR(O6="LABOUR",O6="INSTALL"),"LABOUR_ALL",IF(O6="","",O6)) | Y6: =IF(AND(A6="line",D6="quote"),SUMIFS($N$2:$N$500,$W$2:$W$500,W6,$D$2:$D$500,"invoice",$A$2:$A$500,"line"),"") | Z6: =IF(AND(A6="line",D6="quote"),COUNTIFS($W$2:$W$500,W6,$D$2:$D$500,"invoice",$A$2:$A$500,"line"),"") | AA6: =IF(AND(A6="line",D6="invoice"),COUNTIFS($W$2:$W$500,W6,$D$2:$D$500,"quote",$A$2:$A$500,"line"),"") | AB6: =IF(A6<>"line","",IF(D6="quote",IF(Z6=0,"quote only",IF(ABS(Y6-N6)>Settings!$B$2,"amount differs","match")),IF(AA6=0,"invoice only","match"))) | AC6: =IF(AND(A6="line",AB6<>"match",COUNTIFS($A$2:$A$500,"coverage",$B$2:$B$500,B6,$C$2:$C$500,C6,$D$2:$D$500,"invoice")>0),MAX($AC$1:AC5)+1,"") | AD6: =IF(A6<>"line","",IF(O6="UNMAPPED","no mapping rule",IF(P6="L","low confidence",""))) | AE6: =IF(AD6<>"",MAX($AE$1:AE5)+1,"") | AF6: =IF(A6="coverage",MAX($AF$1:AF5)+1,"") | AG6: =IF(A6="line",IF(COUNTIFS($B$1:B5,B6,$C$1:C5,C6,$A$1:A5,"line")=0,MAX($AG$1:AG5)+1,""),"")
A7: line | B7: Project Alpha | C7: Vendor A | D7: quote | E7: Q-1001 | F7: 2026-05-04 | H7: 2 | I7: 6 | J7: Freight | K7: Freight to site | N7: 1800 | O7: LABOUR | P7: H | V7: Project Alpha__Vendor A__quote__Q-1001.pdf | W7: =IF(A7="line",IF(D7="quote",E7,G7)&"|"&LOWER(TRIM(K7)),"") | X7: =IF(OR(O7="LABOUR",O7="INSTALL"),"LABOUR_ALL",IF(O7="","",O7)) | Y7: =IF(AND(A7="line",D7="quote"),SUMIFS($N$2:$N$500,$W$2:$W$500,W7,$D$2:$D$500,"invoice",$A$2:$A$500,"line"),"") | Z7: =IF(AND(A7="line",D7="quote"),COUNTIFS($W$2:$W$500,W7,$D$2:$D$500,"invoice",$A$2:$A$500,"line"),"") | AA7: =IF(AND(A7="line",D7="invoice"),COUNTIFS($W$2:$W$500,W7,$D$2:$D$500,"quote",$A$2:$A$500,"line"),"") | AB7: =IF(A7<>"line","",IF(D7="quote",IF(Z7=0,"quote only",IF(ABS(Y7-N7)>Settings!$B$2,"amount differs","match")),IF(AA7=0,"invoice only","match"))) | AC7: =IF(AND(A7="line",AB7<>"match",COUNTIFS($A$2:$A$500,"coverage",$B$2:$B$500,B7,$C$2:$C$500,C7,$D$2:$D$500,"invoice")>0),MAX($AC$1:AC6)+1,"") | AD7: =IF(A7<>"line","",IF(O7="UNMAPPED","no mapping rule",IF(P7="L","low confidence",""))) | AE7: =IF(AD7<>"",MAX($AE$1:AE6)+1,"") | AF7: =IF(A7="coverage",MAX($AF$1:AF6)+1,"") | AG7: =IF(A7="line",IF(COUNTIFS($B$1:B6,B7,$C$1:C6,C7,$A$1:A6,"line")=0,MAX($AG$1:AG6)+1,""),"")
A8: line | B8: Project Alpha | C8: Vendor A | D8: quote | E8: Q-1001 | F8: 2026-05-04 | H8: 3 | I8: 7 | J8: Contingency | K8: Contingency allowance | N8: 2000 | O8: ALLOWANCE | P8: H | V8: Project Alpha__Vendor A__quote__Q-1001.pdf | W8: =IF(A8="line",IF(D8="quote",E8,G8)&"|"&LOWER(TRIM(K8)),"") | X8: =IF(OR(O8="LABOUR",O8="INSTALL"),"LABOUR_ALL",IF(O8="","",O8)) | Y8: =IF(AND(A8="line",D8="quote"),SUMIFS($N$2:$N$500,$W$2:$W$500,W8,$D$2:$D$500,"invoice",$A$2:$A$500,"line"),"") | Z8: =IF(AND(A8="line",D8="quote"),COUNTIFS($W$2:$W$500,W8,$D$2:$D$500,"invoice",$A$2:$A$500,"line"),"") | AA8: =IF(AND(A8="line",D8="invoice"),COUNTIFS($W$2:$W$500,W8,$D$2:$D$500,"quote",$A$2:$A$500,"line"),"") | AB8: =IF(A8<>"line","",IF(D8="quote",IF(Z8=0,"quote only",IF(ABS(Y8-N8)>Settings!$B$2,"amount differs","match")),IF(AA8=0,"invoice only","match"))) | AC8: =IF(AND(A8="line",AB8<>"match",COUNTIFS($A$2:$A$500,"coverage",$B$2:$B$500,B8,$C$2:$C$500,C8,$D$2:$D$500,"invoice")>0),MAX($AC$1:AC7)+1,"") | AD8: =IF(A8<>"line","",IF(O8="UNMAPPED","no mapping rule",IF(P8="L","low confidence",""))) | AE8: =IF(AD8<>"",MAX($AE$1:AE7)+1,"") | AF8: =IF(A8="coverage",MAX($AF$1:AF7)+1,"") | AG8: =IF(A8="line",IF(COUNTIFS($B$1:B7,B8,$C$1:C7,C8,$A$1:A7,"line")=0,MAX($AG$1:AG7)+1,""),"")
A9: line | B9: Project Alpha | C9: Vendor A | D9: quote | E9: Q-1001 | F9: 2026-05-04 | H9: 3 | I9: 8 | J9: Sales tax | K9: Sales tax 8% | N9: 3680 | O9: EXCLUDED | P9: H | V9: Project Alpha__Vendor A__quote__Q-1001.pdf | W9: =IF(A9="line",IF(D9="quote",E9,G9)&"|"&LOWER(TRIM(K9)),"") | X9: =IF(OR(O9="LABOUR",O9="INSTALL"),"LABOUR_ALL",IF(O9="","",O9)) | Y9: =IF(AND(A9="line",D9="quote"),SUMIFS($N$2:$N$500,$W$2:$W$500,W9,$D$2:$D$500,"invoice",$A$2:$A$500,"line"),"") | Z9: =IF(AND(A9="line",D9="quote"),COUNTIFS($W$2:$W$500,W9,$D$2:$D$500,"invoice",$A$2:$A$500,"line"),"") | AA9: =IF(AND(A9="line",D9="invoice"),COUNTIFS($W$2:$W$500,W9,$D$2:$D$500,"quote",$A$2:$A$500,"line"),"") | AB9: =IF(A9<>"line","",IF(D9="quote",IF(Z9=0,"quote only",IF(ABS(Y9-N9)>Settings!$B$2,"amount differs","match")),IF(AA9=0,"invoice only","match"))) | AC9: =IF(AND(A9="line",AB9<>"match",COUNTIFS($A$2:$A$500,"coverage",$B$2:$B$500,B9,$C$2:$C$500,C9,$D$2:$D$500,"invoice")>0),MAX($AC$1:AC8)+1,"") | AD9: =IF(A9<>"line","",IF(O9="UNMAPPED","no mapping rule",IF(P9="L","low confidence",""))) | AE9: =IF(AD9<>"",MAX($AE$1:AE8)+1,"") | AF9: =IF(A9="coverage",MAX($AF$1:AF8)+1,"") | AG9: =IF(A9="line",IF(COUNTIFS($B$1:B8,B9,$C$1:C8,C9,$A$1:A8,"line")=0,MAX($AG$1:AG8)+1,""),"")
A10: total | B10: Project Alpha | C10: Vendor A | D10: quote | E10: Q-1001 | F10: 2026-05-04 | H10: 3 | J10: Product subtotal | N10: 46000 | O10: PRODUCT | P10: H | V10: Project Alpha__Vendor A__quote__Q-1001.pdf | W10: =IF(A10="line",IF(D10="quote",E10,G10)&"|"&LOWER(TRIM(K10)),"") | X10: =IF(OR(O10="LABOUR",O10="INSTALL"),"LABOUR_ALL",IF(O10="","",O10)) | Y10: =IF(AND(A10="line",D10="quote"),SUMIFS($N$2:$N$500,$W$2:$W$500,W10,$D$2:$D$500,"invoice",$A$2:$A$500,"line"),"") | Z10: =IF(AND(A10="line",D10="quote"),COUNTIFS($W$2:$W$500,W10,$D$2:$D$500,"invoice",$A$2:$A$500,"line"),"") | AA10: =IF(AND(A10="line",D10="invoice"),COUNTIFS($W$2:$W$500,W10,$D$2:$D$500,"quote",$A$2:$A$500,"line"),"") | AB10: =IF(A10<>"line","",IF(D10="quote",IF(Z10=0,"quote only",IF(ABS(Y10-N10)>Settings!$B$2,"amount differs","match")),IF(AA10=0,"invoice only","match"))) | AC10: =IF(AND(A10="line",AB10<>"match",COUNTIFS($A$2:$A$500,"coverage",$B$2:$B$500,B10,$C$2:$C$500,C10,$D$2:$D$500,"invoice")>0),MAX($AC$1:AC9)+1,"") | AD10: =IF(A10<>"line","",IF(O10="UNMAPPED","no mapping rule",IF(P10="L","low confidence",""))) | AE10: =IF(AD10<>"",MAX($AE$1:AE9)+1,"") | AF10: =IF(A10="coverage",MAX($AF$1:AF9)+1,"") | AG10: =IF(A10="line",IF(COUNTIFS($B$1:B9,B10,$C$1:C9,C10,$A$1:A9,"line")=0,MAX($AG$1:AG9)+1,""),"")
A11: total | B11: Project Alpha | C11: Vendor A | D11: quote | E11: Q-1001 | F11: 2026-05-04 | H11: 3 | J11: Installation | N11: 9600 | O11: INSTALL | P11: H | V11: Project Alpha__Vendor A__quote__Q-1001.pdf | W11: =IF(A11="line",IF(D11="quote",E11,G11)&"|"&LOWER(TRIM(K11)),"") | X11: =IF(OR(O11="LABOUR",O11="INSTALL"),"LABOUR_ALL",IF(O11="","",O11)) | Y11: =IF(AND(A11="line",D11="quote"),SUMIFS($N$2:$N$500,$W$2:$W$500,W11,$D$2:$D$500,"invoice",$A$2:$A$500,"line"),"") | Z11: =IF(AND(A11="line",D11="quote"),COUNTIFS($W$2:$W$500,W11,$D$2:$D$500,"invoice",$A$2:$A$500,"line"),"") | AA11: =IF(AND(A11="line",D11="invoice"),COUNTIFS($W$2:$W$500,W11,$D$2:$D$500,"quote",$A$2:$A$500,"line"),"") | AB11: =IF(A11<>"line","",IF(D11="quote",IF(Z11=0,"quote only",IF(ABS(Y11-N11)>Settings!$B$2,"amount differs","match")),IF(AA11=0,"invoice only","match"))) | AC11: =IF(AND(A11="line",AB11<>"match",COUNTIFS($A$2:$A$500,"coverage",$B$2:$B$500,B11,$C$2:$C$500,C11,$D$2:$D$500,"invoice")>0),MAX($AC$1:AC10)+1,"") | AD11: =IF(A11<>"line","",IF(O11="UNMAPPED","no mapping rule",IF(P11="L","low confidence",""))) | AE11: =IF(AD11<>"",MAX($AE$1:AE10)+1,"") | AF11: =IF(A11="coverage",MAX($AF$1:AF10)+1,"") | AG11: =IF(A11="line",IF(COUNTIFS($B$1:B10,B11,$C$1:C10,C11,$A$1:A10,"line")=0,MAX($AG$1:AG10)+1,""),"")
A12: total | B12: Project Alpha | C12: Vendor A | D12: quote | E12: Q-1001 | F12: 2026-05-04 | H12: 3 | J12: Services subtotal | N12: 4200 | O12: LABOUR | P12: H | V12: Project Alpha__Vendor A__quote__Q-1001.pdf | W12: =IF(A12="line",IF(D12="quote",E12,G12)&"|"&LOWER(TRIM(K12)),"") | X12: =IF(OR(O12="LABOUR",O12="INSTALL"),"LABOUR_ALL",IF(O12="","",O12)) | Y12: =IF(AND(A12="line",D12="quote"),SUMIFS($N$2:$N$500,$W$2:$W$500,W12,$D$2:$D$500,"invoice",$A$2:$A$500,"line"),"") | Z12: =IF(AND(A12="line",D12="quote"),COUNTIFS($W$2:$W$500,W12,$D$2:$D$500,"invoice",$A$2:$A$500,"line"),"") | AA12: =IF(AND(A12="line",D12="invoice"),COUNTIFS($W$2:$W$500,W12,$D$2:$D$500,"quote",$A$2:$A$500,"line"),"") | AB12: =IF(A12<>"line","",IF(D12="quote",IF(Z12=0,"quote only",IF(ABS(Y12-N12)>Settings!$B$2,"amount differs","match")),IF(AA12=0,"invoice only","match"))) | AC12: =IF(AND(A12="line",AB12<>"match",COUNTIFS($A$2:$A$500,"coverage",$B$2:$B$500,B12,$C$2:$C$500,C12,$D$2:$D$500,"invoice")>0),MAX($AC$1:AC11)+1,"") | AD12: =IF(A12<>"line","",IF(O12="UNMAPPED","no mapping rule",IF(P12="L","low confidence",""))) | AE12: =IF(AD12<>"",MAX($AE$1:AE11)+1,"") | AF12: =IF(A12="coverage",MAX($AF$1:AF11)+1,"") | AG12: =IF(A12="line",IF(COUNTIFS($B$1:B11,B12,$C$1:C11,C12,$A$1:A11,"line")=0,MAX($AG$1:AG11)+1,""),"")
A13: total | B13: Project Alpha | C13: Vendor A | D13: quote | E13: Q-1001 | F13: 2026-05-04 | H13: 3 | J13: Grand total | N13: 65480 | O13: GRAND | P13: H | V13: Project Alpha__Vendor A__quote__Q-1001.pdf | W13: =IF(A13="line",IF(D13="quote",E13,G13)&"|"&LOWER(TRIM(K13)),"") | X13: =IF(OR(O13="LABOUR",O13="INSTALL"),"LABOUR_ALL",IF(O13="","",O13)) | Y13: =IF(AND(A13="line",D13="quote"),SUMIFS($N$2:$N$500,$W$2:$W$500,W13,$D$2:$D$500,"invoice",$A$2:$A$500,"line"),"") | Z13: =IF(AND(A13="line",D13="quote"),COUNTIFS($W$2:$W$500,W13,$D$2:$D$500,"invoice",$A$2:$A$500,"line"),"") | AA13: =IF(AND(A13="line",D13="invoice"),COUNTIFS($W$2:$W$500,W13,$D$2:$D$500,"quote",$A$2:$A$500,"line"),"") | AB13: =IF(A13<>"line","",IF(D13="quote",IF(Z13=0,"quote only",IF(ABS(Y13-N13)>Settings!$B$2,"amount differs","match")),IF(AA13=0,"invoice only","match"))) | AC13: =IF(AND(A13="line",AB13<>"match",COUNTIFS($A$2:$A$500,"coverage",$B$2:$B$500,B13,$C$2:$C$500,C13,$D$2:$D$500,"invoice")>0),MAX($AC$1:AC12)+1,"") | AD13: =IF(A13<>"line","",IF(O13="UNMAPPED","no mapping rule",IF(P13="L","low confidence",""))) | AE13: =IF(AD13<>"",MAX($AE$1:AE12)+1,"") | AF13: =IF(A13="coverage",MAX($AF$1:AF12)+1,"") | AG13: =IF(A13="line",IF(COUNTIFS($B$1:B12,B13,$C$1:C12,C13,$A$1:A12,"line")=0,MAX($AG$1:AG12)+1,""),"")
A14: coverage | B14: Project Alpha | C14: Vendor A | D14: quote | E14: Q-1001 | F14: 2026-05-04 | R14: 3 | S14: 1-3 | T14: native | U14: Y | V14: Project Alpha__Vendor A__quote__Q-1001.pdf | W14: =IF(A14="line",IF(D14="quote",E14,G14)&"|"&LOWER(TRIM(K14)),"") | X14: =IF(OR(O14="LABOUR",O14="INSTALL"),"LABOUR_ALL",IF(O14="","",O14)) | Y14: =IF(AND(A14="line",D14="quote"),SUMIFS($N$2:$N$500,$W$2:$W$500,W14,$D$2:$D$500,"invoice",$A$2:$A$500,"line"),"") | Z14: =IF(AND(A14="line",D14="quote"),COUNTIFS($W$2:$W$500,W14,$D$2:$D$500,"invoice",$A$2:$A$500,"line"),"") | AA14: =IF(AND(A14="line",D14="invoice"),COUNTIFS($W$2:$W$500,W14,$D$2:$D$500,"quote",$A$2:$A$500,"line"),"") | AB14: =IF(A14<>"line","",IF(D14="quote",IF(Z14=0,"quote only",IF(ABS(Y14-N14)>Settings!$B$2,"amount differs","match")),IF(AA14=0,"invoice only","match"))) | AC14: =IF(AND(A14="line",AB14<>"match",COUNTIFS($A$2:$A$500,"coverage",$B$2:$B$500,B14,$C$2:$C$500,C14,$D$2:$D$500,"invoice")>0),MAX($AC$1:AC13)+1,"") | AD14: =IF(A14<>"line","",IF(O14="UNMAPPED","no mapping rule",IF(P14="L","low confidence",""))) | AE14: =IF(AD14<>"",MAX($AE$1:AE13)+1,"") | AF14: =IF(A14="coverage",MAX($AF$1:AF13)+1,"") | AG14: =IF(A14="line",IF(COUNTIFS($B$1:B13,B14,$C$1:C13,C14,$A$1:A13,"line")=0,MAX($AG$1:AG13)+1,""),"")
A15: line | B15: Project Alpha | C15: Vendor A | D15: invoice | E15: INV-2001 | F15: 2026-07-15 | G15: Q-1001 | H15: 1 | I15: 1 | J15: Task chair TC-200 | K15: Task chair, model TC-200 | L15: 40 | M15: 350 | N15: 14000 | O15: PRODUCT | P15: H | V15: Project Alpha__Vendor A__invoice__INV-2001.pdf | W15: =IF(A15="line",IF(D15="quote",E15,G15)&"|"&LOWER(TRIM(K15)),"") | X15: =IF(OR(O15="LABOUR",O15="INSTALL"),"LABOUR_ALL",IF(O15="","",O15)) | Y15: =IF(AND(A15="line",D15="quote"),SUMIFS($N$2:$N$500,$W$2:$W$500,W15,$D$2:$D$500,"invoice",$A$2:$A$500,"line"),"") | Z15: =IF(AND(A15="line",D15="quote"),COUNTIFS($W$2:$W$500,W15,$D$2:$D$500,"invoice",$A$2:$A$500,"line"),"") | AA15: =IF(AND(A15="line",D15="invoice"),COUNTIFS($W$2:$W$500,W15,$D$2:$D$500,"quote",$A$2:$A$500,"line"),"") | AB15: =IF(A15<>"line","",IF(D15="quote",IF(Z15=0,"quote only",IF(ABS(Y15-N15)>Settings!$B$2,"amount differs","match")),IF(AA15=0,"invoice only","match"))) | AC15: =IF(AND(A15="line",AB15<>"match",COUNTIFS($A$2:$A$500,"coverage",$B$2:$B$500,B15,$C$2:$C$500,C15,$D$2:$D$500,"invoice")>0),MAX($AC$1:AC14)+1,"") | AD15: =IF(A15<>"line","",IF(O15="UNMAPPED","no mapping rule",IF(P15="L","low confidence",""))) | AE15: =IF(AD15<>"",MAX($AE$1:AE14)+1,"") | AF15: =IF(A15="coverage",MAX($AF$1:AF14)+1,"") | AG15: =IF(A15="line",IF(COUNTIFS($B$1:B14,B15,$C$1:C14,C15,$A$1:A14,"line")=0,MAX($AG$1:AG14)+1,""),"")
A16: line | B16: Project Alpha | C16: Vendor A | D16: invoice | E16: INV-2001 | F16: 2026-07-15 | G16: Q-1001 | H16: 1 | I16: 2 | J16: Desk HA-1600 | K16: Height-adjustable desk 1600 | L16: 40 | M16: 620 | N16: 24800 | O16: PRODUCT | P16: H | V16: Project Alpha__Vendor A__invoice__INV-2001.pdf | W16: =IF(A16="line",IF(D16="quote",E16,G16)&"|"&LOWER(TRIM(K16)),"") | X16: =IF(OR(O16="LABOUR",O16="INSTALL"),"LABOUR_ALL",IF(O16="","",O16)) | Y16: =IF(AND(A16="line",D16="quote"),SUMIFS($N$2:$N$500,$W$2:$W$500,W16,$D$2:$D$500,"invoice",$A$2:$A$500,"line"),"") | Z16: =IF(AND(A16="line",D16="quote"),COUNTIFS($W$2:$W$500,W16,$D$2:$D$500,"invoice",$A$2:$A$500,"line"),"") | AA16: =IF(AND(A16="line",D16="invoice"),COUNTIFS($W$2:$W$500,W16,$D$2:$D$500,"quote",$A$2:$A$500,"line"),"") | AB16: =IF(A16<>"line","",IF(D16="quote",IF(Z16=0,"quote only",IF(ABS(Y16-N16)>Settings!$B$2,"amount differs","match")),IF(AA16=0,"invoice only","match"))) | AC16: =IF(AND(A16="line",AB16<>"match",COUNTIFS($A$2:$A$500,"coverage",$B$2:$B$500,B16,$C$2:$C$500,C16,$D$2:$D$500,"invoice")>0),MAX($AC$1:AC15)+1,"") | AD16: =IF(A16<>"line","",IF(O16="UNMAPPED","no mapping rule",IF(P16="L","low confidence",""))) | AE16: =IF(AD16<>"",MAX($AE$1:AE15)+1,"") | AF16: =IF(A16="coverage",MAX($AF$1:AF15)+1,"") | AG16: =IF(A16="line",IF(COUNTIFS($B$1:B15,B16,$C$1:C15,C16,$A$1:A15,"line")=0,MAX($AG$1:AG15)+1,""),"")
A17: line | B17: Project Alpha | C17: Vendor A | D17: invoice | E17: INV-2001 | F17: 2026-07-15 | G17: Q-1001 | H17: 1 | I17: 3 | J17: Pedestal | K17: Storage pedestal | L17: 40 | M17: 180 | N17: 7200 | O17: PRODUCT | P17: H | V17: Project Alpha__Vendor A__invoice__INV-2001.pdf | W17: =IF(A17="line",IF(D17="quote",E17,G17)&"|"&LOWER(TRIM(K17)),"") | X17: =IF(OR(O17="LABOUR",O17="INSTALL"),"LABOUR_ALL",IF(O17="","",O17)) | Y17: =IF(AND(A17="line",D17="quote"),SUMIFS($N$2:$N$500,$W$2:$W$500,W17,$D$2:$D$500,"invoice",$A$2:$A$500,"line"),"") | Z17: =IF(AND(A17="line",D17="quote"),COUNTIFS($W$2:$W$500,W17,$D$2:$D$500,"invoice",$A$2:$A$500,"line"),"") | AA17: =IF(AND(A17="line",D17="invoice"),COUNTIFS($W$2:$W$500,W17,$D$2:$D$500,"quote",$A$2:$A$500,"line"),"") | AB17: =IF(A17<>"line","",IF(D17="quote",IF(Z17=0,"quote only",IF(ABS(Y17-N17)>Settings!$B$2,"amount differs","match")),IF(AA17=0,"invoice only","match"))) | AC17: =IF(AND(A17="line",AB17<>"match",COUNTIFS($A$2:$A$500,"coverage",$B$2:$B$500,B17,$C$2:$C$500,C17,$D$2:$D$500,"invoice")>0),MAX($AC$1:AC16)+1,"") | AD17: =IF(A17<>"line","",IF(O17="UNMAPPED","no mapping rule",IF(P17="L","low confidence",""))) | AE17: =IF(AD17<>"",MAX($AE$1:AE16)+1,"") | AF17: =IF(A17="coverage",MAX($AF$1:AF16)+1,"") | AG17: =IF(A17="line",IF(COUNTIFS($B$1:B16,B17,$C$1:C16,C17,$A$1:A16,"line")=0,MAX($AG$1:AG16)+1,""),"")
A18: line | B18: Project Alpha | C18: Vendor A | D18: invoice | E18: INV-2001 | F18: 2026-07-15 | G18: Q-1001 | H18: 2 | I18: 4 | J18: Installation | K18: Installation, 40 workstations, fixed price | N18: 9600 | O18: INSTALL | P18: H | V18: Project Alpha__Vendor A__invoice__INV-2001.pdf | W18: =IF(A18="line",IF(D18="quote",E18,G18)&"|"&LOWER(TRIM(K18)),"") | X18: =IF(OR(O18="LABOUR",O18="INSTALL"),"LABOUR_ALL",IF(O18="","",O18)) | Y18: =IF(AND(A18="line",D18="quote"),SUMIFS($N$2:$N$500,$W$2:$W$500,W18,$D$2:$D$500,"invoice",$A$2:$A$500,"line"),"") | Z18: =IF(AND(A18="line",D18="quote"),COUNTIFS($W$2:$W$500,W18,$D$2:$D$500,"invoice",$A$2:$A$500,"line"),"") | AA18: =IF(AND(A18="line",D18="invoice"),COUNTIFS($W$2:$W$500,W18,$D$2:$D$500,"quote",$A$2:$A$500,"line"),"") | AB18: =IF(A18<>"line","",IF(D18="quote",IF(Z18=0,"quote only",IF(ABS(Y18-N18)>Settings!$B$2,"amount differs","match")),IF(AA18=0,"invoice only","match"))) | AC18: =IF(AND(A18="line",AB18<>"match",COUNTIFS($A$2:$A$500,"coverage",$B$2:$B$500,B18,$C$2:$C$500,C18,$D$2:$D$500,"invoice")>0),MAX($AC$1:AC17)+1,"") | AD18: =IF(A18<>"line","",IF(O18="UNMAPPED","no mapping rule",IF(P18="L","low confidence",""))) | AE18: =IF(AD18<>"",MAX($AE$1:AE17)+1,"") | AF18: =IF(A18="coverage",MAX($AF$1:AF17)+1,"") | AG18: =IF(A18="line",IF(COUNTIFS($B$1:B17,B18,$C$1:C17,C18,$A$1:A17,"line")=0,MAX($AG$1:AG17)+1,""),"")
A19: line | B19: Project Alpha | C19: Vendor A | D19: invoice | E19: INV-2001 | F19: 2026-07-15 | G19: Q-1001 | H19: 2 | I19: 5 | J19: Install labour - additional hours | K19: Additional installation hours, 32 hrs at 95 | L19: 32 | M19: 95 | N19: 3040 | O19: INSTALL | P19: M | Q19: matched by principle | V19: Project Alpha__Vendor A__invoice__INV-2001.pdf | W19: =IF(A19="line",IF(D19="quote",E19,G19)&"|"&LOWER(TRIM(K19)),"") | X19: =IF(OR(O19="LABOUR",O19="INSTALL"),"LABOUR_ALL",IF(O19="","",O19)) | Y19: =IF(AND(A19="line",D19="quote"),SUMIFS($N$2:$N$500,$W$2:$W$500,W19,$D$2:$D$500,"invoice",$A$2:$A$500,"line"),"") | Z19: =IF(AND(A19="line",D19="quote"),COUNTIFS($W$2:$W$500,W19,$D$2:$D$500,"invoice",$A$2:$A$500,"line"),"") | AA19: =IF(AND(A19="line",D19="invoice"),COUNTIFS($W$2:$W$500,W19,$D$2:$D$500,"quote",$A$2:$A$500,"line"),"") | AB19: =IF(A19<>"line","",IF(D19="quote",IF(Z19=0,"quote only",IF(ABS(Y19-N19)>Settings!$B$2,"amount differs","match")),IF(AA19=0,"invoice only","match"))) | AC19: =IF(AND(A19="line",AB19<>"match",COUNTIFS($A$2:$A$500,"coverage",$B$2:$B$500,B19,$C$2:$C$500,C19,$D$2:$D$500,"invoice")>0),MAX($AC$1:AC18)+1,"") | AD19: =IF(A19<>"line","",IF(O19="UNMAPPED","no mapping rule",IF(P19="L","low confidence",""))) | AE19: =IF(AD19<>"",MAX($AE$1:AE18)+1,"") | AF19: =IF(A19="coverage",MAX($AF$1:AF18)+1,"") | AG19: =IF(A19="line",IF(COUNTIFS($B$1:B18,B19,$C$1:C18,C19,$A$1:A18,"line")=0,MAX($AG$1:AG18)+1,""),"")
A20: line | B20: Project Alpha | C20: Vendor A | D20: invoice | E20: INV-2001 | F20: 2026-07-15 | G20: Q-1001 | H20: 2 | I20: 6 | J20: Project management | K20: Project management fee | N20: 2400 | O20: LABOUR | P20: H | V20: Project Alpha__Vendor A__invoice__INV-2001.pdf | W20: =IF(A20="line",IF(D20="quote",E20,G20)&"|"&LOWER(TRIM(K20)),"") | X20: =IF(OR(O20="LABOUR",O20="INSTALL"),"LABOUR_ALL",IF(O20="","",O20)) | Y20: =IF(AND(A20="line",D20="quote"),SUMIFS($N$2:$N$500,$W$2:$W$500,W20,$D$2:$D$500,"invoice",$A$2:$A$500,"line"),"") | Z20: =IF(AND(A20="line",D20="quote"),COUNTIFS($W$2:$W$500,W20,$D$2:$D$500,"invoice",$A$2:$A$500,"line"),"") | AA20: =IF(AND(A20="line",D20="invoice"),COUNTIFS($W$2:$W$500,W20,$D$2:$D$500,"quote",$A$2:$A$500,"line"),"") | AB20: =IF(A20<>"line","",IF(D20="quote",IF(Z20=0,"quote only",IF(ABS(Y20-N20)>Settings!$B$2,"amount differs","match")),IF(AA20=0,"invoice only","match"))) | AC20: =IF(AND(A20="line",AB20<>"match",COUNTIFS($A$2:$A$500,"coverage",$B$2:$B$500,B20,$C$2:$C$500,C20,$D$2:$D$500,"invoice")>0),MAX($AC$1:AC19)+1,"") | AD20: =IF(A20<>"line","",IF(O20="UNMAPPED","no mapping rule",IF(P20="L","low confidence",""))) | AE20: =IF(AD20<>"",MAX($AE$1:AE19)+1,"") | AF20: =IF(A20="coverage",MAX($AF$1:AF19)+1,"") | AG20: =IF(A20="line",IF(COUNTIFS($B$1:B19,B20,$C$1:C19,C20,$A$1:A19,"line")=0,MAX($AG$1:AG19)+1,""),"")
A21: line | B21: Project Alpha | C21: Vendor A | D21: invoice | E21: INV-2001 | F21: 2026-07-15 | G21: Q-1001 | H21: 2 | I21: 7 | J21: Freight | K21: Freight to site | N21: 2100 | O21: LABOUR | P21: H | V21: Project Alpha__Vendor A__invoice__INV-2001.pdf | W21: =IF(A21="line",IF(D21="quote",E21,G21)&"|"&LOWER(TRIM(K21)),"") | X21: =IF(OR(O21="LABOUR",O21="INSTALL"),"LABOUR_ALL",IF(O21="","",O21)) | Y21: =IF(AND(A21="line",D21="quote"),SUMIFS($N$2:$N$500,$W$2:$W$500,W21,$D$2:$D$500,"invoice",$A$2:$A$500,"line"),"") | Z21: =IF(AND(A21="line",D21="quote"),COUNTIFS($W$2:$W$500,W21,$D$2:$D$500,"invoice",$A$2:$A$500,"line"),"") | AA21: =IF(AND(A21="line",D21="invoice"),COUNTIFS($W$2:$W$500,W21,$D$2:$D$500,"quote",$A$2:$A$500,"line"),"") | AB21: =IF(A21<>"line","",IF(D21="quote",IF(Z21=0,"quote only",IF(ABS(Y21-N21)>Settings!$B$2,"amount differs","match")),IF(AA21=0,"invoice only","match"))) | AC21: =IF(AND(A21="line",AB21<>"match",COUNTIFS($A$2:$A$500,"coverage",$B$2:$B$500,B21,$C$2:$C$500,C21,$D$2:$D$500,"invoice")>0),MAX($AC$1:AC20)+1,"") | AD21: =IF(A21<>"line","",IF(O21="UNMAPPED","no mapping rule",IF(P21="L","low confidence",""))) | AE21: =IF(AD21<>"",MAX($AE$1:AE20)+1,"") | AF21: =IF(A21="coverage",MAX($AF$1:AF20)+1,"") | AG21: =IF(A21="line",IF(COUNTIFS($B$1:B20,B21,$C$1:C20,C21,$A$1:A20,"line")=0,MAX($AG$1:AG20)+1,""),"")
A22: line | B22: Project Alpha | C22: Vendor A | D22: invoice | E22: INV-2001 | F22: 2026-07-15 | G22: Q-1001 | H22: 2 | I22: 8 | J22: Site services | K22: Site services | N22: 650 | O22: UNMAPPED | P22: L | Q22: no mapping rule | V22: Project Alpha__Vendor A__invoice__INV-2001.pdf | W22: =IF(A22="line",IF(D22="quote",E22,G22)&"|"&LOWER(TRIM(K22)),"") | X22: =IF(OR(O22="LABOUR",O22="INSTALL"),"LABOUR_ALL",IF(O22="","",O22)) | Y22: =IF(AND(A22="line",D22="quote"),SUMIFS($N$2:$N$500,$W$2:$W$500,W22,$D$2:$D$500,"invoice",$A$2:$A$500,"line"),"") | Z22: =IF(AND(A22="line",D22="quote"),COUNTIFS($W$2:$W$500,W22,$D$2:$D$500,"invoice",$A$2:$A$500,"line"),"") | AA22: =IF(AND(A22="line",D22="invoice"),COUNTIFS($W$2:$W$500,W22,$D$2:$D$500,"quote",$A$2:$A$500,"line"),"") | AB22: =IF(A22<>"line","",IF(D22="quote",IF(Z22=0,"quote only",IF(ABS(Y22-N22)>Settings!$B$2,"amount differs","match")),IF(AA22=0,"invoice only","match"))) | AC22: =IF(AND(A22="line",AB22<>"match",COUNTIFS($A$2:$A$500,"coverage",$B$2:$B$500,B22,$C$2:$C$500,C22,$D$2:$D$500,"invoice")>0),MAX($AC$1:AC21)+1,"") | AD22: =IF(A22<>"line","",IF(O22="UNMAPPED","no mapping rule",IF(P22="L","low confidence",""))) | AE22: =IF(AD22<>"",MAX($AE$1:AE21)+1,"") | AF22: =IF(A22="coverage",MAX($AF$1:AF21)+1,"") | AG22: =IF(A22="line",IF(COUNTIFS($B$1:B21,B22,$C$1:C21,C22,$A$1:A21,"line")=0,MAX($AG$1:AG21)+1,""),"")
A23: line | B23: Project Alpha | C23: Vendor A | D23: invoice | E23: INV-2001 | F23: 2026-07-15 | G23: Q-1001 | H23: 2 | I23: 9 | J23: Sales tax | K23: Sales tax 8% | N23: 3680 | O23: EXCLUDED | P23: H | V23: Project Alpha__Vendor A__invoice__INV-2001.pdf | W23: =IF(A23="line",IF(D23="quote",E23,G23)&"|"&LOWER(TRIM(K23)),"") | X23: =IF(OR(O23="LABOUR",O23="INSTALL"),"LABOUR_ALL",IF(O23="","",O23)) | Y23: =IF(AND(A23="line",D23="quote"),SUMIFS($N$2:$N$500,$W$2:$W$500,W23,$D$2:$D$500,"invoice",$A$2:$A$500,"line"),"") | Z23: =IF(AND(A23="line",D23="quote"),COUNTIFS($W$2:$W$500,W23,$D$2:$D$500,"invoice",$A$2:$A$500,"line"),"") | AA23: =IF(AND(A23="line",D23="invoice"),COUNTIFS($W$2:$W$500,W23,$D$2:$D$500,"quote",$A$2:$A$500,"line"),"") | AB23: =IF(A23<>"line","",IF(D23="quote",IF(Z23=0,"quote only",IF(ABS(Y23-N23)>Settings!$B$2,"amount differs","match")),IF(AA23=0,"invoice only","match"))) | AC23: =IF(AND(A23="line",AB23<>"match",COUNTIFS($A$2:$A$500,"coverage",$B$2:$B$500,B23,$C$2:$C$500,C23,$D$2:$D$500,"invoice")>0),MAX($AC$1:AC22)+1,"") | AD23: =IF(A23<>"line","",IF(O23="UNMAPPED","no mapping rule",IF(P23="L","low confidence",""))) | AE23: =IF(AD23<>"",MAX($AE$1:AE22)+1,"") | AF23: =IF(A23="coverage",MAX($AF$1:AF22)+1,"") | AG23: =IF(A23="line",IF(COUNTIFS($B$1:B22,B23,$C$1:C22,C23,$A$1:A22,"line")=0,MAX($AG$1:AG22)+1,""),"")
A24: total | B24: Project Alpha | C24: Vendor A | D24: invoice | E24: INV-2001 | F24: 2026-07-15 | G24: Q-1001 | H24: 2 | J24: Product subtotal | N24: 46000 | O24: PRODUCT | P24: H | V24: Project Alpha__Vendor A__invoice__INV-2001.pdf | W24: =IF(A24="line",IF(D24="quote",E24,G24)&"|"&LOWER(TRIM(K24)),"") | X24: =IF(OR(O24="LABOUR",O24="INSTALL"),"LABOUR_ALL",IF(O24="","",O24)) | Y24: =IF(AND(A24="line",D24="quote"),SUMIFS($N$2:$N$500,$W$2:$W$500,W24,$D$2:$D$500,"invoice",$A$2:$A$500,"line"),"") | Z24: =IF(AND(A24="line",D24="quote"),COUNTIFS($W$2:$W$500,W24,$D$2:$D$500,"invoice",$A$2:$A$500,"line"),"") | AA24: =IF(AND(A24="line",D24="invoice"),COUNTIFS($W$2:$W$500,W24,$D$2:$D$500,"quote",$A$2:$A$500,"line"),"") | AB24: =IF(A24<>"line","",IF(D24="quote",IF(Z24=0,"quote only",IF(ABS(Y24-N24)>Settings!$B$2,"amount differs","match")),IF(AA24=0,"invoice only","match"))) | AC24: =IF(AND(A24="line",AB24<>"match",COUNTIFS($A$2:$A$500,"coverage",$B$2:$B$500,B24,$C$2:$C$500,C24,$D$2:$D$500,"invoice")>0),MAX($AC$1:AC23)+1,"") | AD24: =IF(A24<>"line","",IF(O24="UNMAPPED","no mapping rule",IF(P24="L","low confidence",""))) | AE24: =IF(AD24<>"",MAX($AE$1:AE23)+1,"") | AF24: =IF(A24="coverage",MAX($AF$1:AF23)+1,"") | AG24: =IF(A24="line",IF(COUNTIFS($B$1:B23,B24,$C$1:C23,C24,$A$1:A23,"line")=0,MAX($AG$1:AG23)+1,""),"")
A25: total | B25: Project Alpha | C25: Vendor A | D25: invoice | E25: INV-2001 | F25: 2026-07-15 | G25: Q-1001 | H25: 2 | J25: Installation | N25: 12640 | O25: INSTALL | P25: H | V25: Project Alpha__Vendor A__invoice__INV-2001.pdf | W25: =IF(A25="line",IF(D25="quote",E25,G25)&"|"&LOWER(TRIM(K25)),"") | X25: =IF(OR(O25="LABOUR",O25="INSTALL"),"LABOUR_ALL",IF(O25="","",O25)) | Y25: =IF(AND(A25="line",D25="quote"),SUMIFS($N$2:$N$500,$W$2:$W$500,W25,$D$2:$D$500,"invoice",$A$2:$A$500,"line"),"") | Z25: =IF(AND(A25="line",D25="quote"),COUNTIFS($W$2:$W$500,W25,$D$2:$D$500,"invoice",$A$2:$A$500,"line"),"") | AA25: =IF(AND(A25="line",D25="invoice"),COUNTIFS($W$2:$W$500,W25,$D$2:$D$500,"quote",$A$2:$A$500,"line"),"") | AB25: =IF(A25<>"line","",IF(D25="quote",IF(Z25=0,"quote only",IF(ABS(Y25-N25)>Settings!$B$2,"amount differs","match")),IF(AA25=0,"invoice only","match"))) | AC25: =IF(AND(A25="line",AB25<>"match",COUNTIFS($A$2:$A$500,"coverage",$B$2:$B$500,B25,$C$2:$C$500,C25,$D$2:$D$500,"invoice")>0),MAX($AC$1:AC24)+1,"") | AD25: =IF(A25<>"line","",IF(O25="UNMAPPED","no mapping rule",IF(P25="L","low confidence",""))) | AE25: =IF(AD25<>"",MAX($AE$1:AE24)+1,"") | AF25: =IF(A25="coverage",MAX($AF$1:AF24)+1,"") | AG25: =IF(A25="line",IF(COUNTIFS($B$1:B24,B25,$C$1:C24,C25,$A$1:A24,"line")=0,MAX($AG$1:AG24)+1,""),"")
A26: total | B26: Project Alpha | C26: Vendor A | D26: invoice | E26: INV-2001 | F26: 2026-07-15 | G26: Q-1001 | H26: 2 | J26: Services subtotal | N26: 4500 | O26: LABOUR | P26: H | V26: Project Alpha__Vendor A__invoice__INV-2001.pdf | W26: =IF(A26="line",IF(D26="quote",E26,G26)&"|"&LOWER(TRIM(K26)),"") | X26: =IF(OR(O26="LABOUR",O26="INSTALL"),"LABOUR_ALL",IF(O26="","",O26)) | Y26: =IF(AND(A26="line",D26="quote"),SUMIFS($N$2:$N$500,$W$2:$W$500,W26,$D$2:$D$500,"invoice",$A$2:$A$500,"line"),"") | Z26: =IF(AND(A26="line",D26="quote"),COUNTIFS($W$2:$W$500,W26,$D$2:$D$500,"invoice",$A$2:$A$500,"line"),"") | AA26: =IF(AND(A26="line",D26="invoice"),COUNTIFS($W$2:$W$500,W26,$D$2:$D$500,"quote",$A$2:$A$500,"line"),"") | AB26: =IF(A26<>"line","",IF(D26="quote",IF(Z26=0,"quote only",IF(ABS(Y26-N26)>Settings!$B$2,"amount differs","match")),IF(AA26=0,"invoice only","match"))) | AC26: =IF(AND(A26="line",AB26<>"match",COUNTIFS($A$2:$A$500,"coverage",$B$2:$B$500,B26,$C$2:$C$500,C26,$D$2:$D$500,"invoice")>0),MAX($AC$1:AC25)+1,"") | AD26: =IF(A26<>"line","",IF(O26="UNMAPPED","no mapping rule",IF(P26="L","low confidence",""))) | AE26: =IF(AD26<>"",MAX($AE$1:AE25)+1,"") | AF26: =IF(A26="coverage",MAX($AF$1:AF25)+1,"") | AG26: =IF(A26="line",IF(COUNTIFS($B$1:B25,B26,$C$1:C25,C26,$A$1:A25,"line")=0,MAX($AG$1:AG25)+1,""),"")
A27: total | B27: Project Alpha | C27: Vendor A | D27: invoice | E27: INV-2001 | F27: 2026-07-15 | G27: Q-1001 | H27: 2 | J27: Grand total | N27: 67470 | O27: GRAND | P27: H | V27: Project Alpha__Vendor A__invoice__INV-2001.pdf | W27: =IF(A27="line",IF(D27="quote",E27,G27)&"|"&LOWER(TRIM(K27)),"") | X27: =IF(OR(O27="LABOUR",O27="INSTALL"),"LABOUR_ALL",IF(O27="","",O27)) | Y27: =IF(AND(A27="line",D27="quote"),SUMIFS($N$2:$N$500,$W$2:$W$500,W27,$D$2:$D$500,"invoice",$A$2:$A$500,"line"),"") | Z27: =IF(AND(A27="line",D27="quote"),COUNTIFS($W$2:$W$500,W27,$D$2:$D$500,"invoice",$A$2:$A$500,"line"),"") | AA27: =IF(AND(A27="line",D27="invoice"),COUNTIFS($W$2:$W$500,W27,$D$2:$D$500,"quote",$A$2:$A$500,"line"),"") | AB27: =IF(A27<>"line","",IF(D27="quote",IF(Z27=0,"quote only",IF(ABS(Y27-N27)>Settings!$B$2,"amount differs","match")),IF(AA27=0,"invoice only","match"))) | AC27: =IF(AND(A27="line",AB27<>"match",COUNTIFS($A$2:$A$500,"coverage",$B$2:$B$500,B27,$C$2:$C$500,C27,$D$2:$D$500,"invoice")>0),MAX($AC$1:AC26)+1,"") | AD27: =IF(A27<>"line","",IF(O27="UNMAPPED","no mapping rule",IF(P27="L","low confidence",""))) | AE27: =IF(AD27<>"",MAX($AE$1:AE26)+1,"") | AF27: =IF(A27="coverage",MAX($AF$1:AF26)+1,"") | AG27: =IF(A27="line",IF(COUNTIFS($B$1:B26,B27,$C$1:C26,C27,$A$1:A26,"line")=0,MAX($AG$1:AG26)+1,""),"")
A28: coverage | B28: Project Alpha | C28: Vendor A | D28: invoice | E28: INV-2001 | F28: 2026-07-15 | G28: Q-1001 | R28: 2 | S28: 1-2 | T28: native | U28: Y | V28: Project Alpha__Vendor A__invoice__INV-2001.pdf | W28: =IF(A28="line",IF(D28="quote",E28,G28)&"|"&LOWER(TRIM(K28)),"") | X28: =IF(OR(O28="LABOUR",O28="INSTALL"),"LABOUR_ALL",IF(O28="","",O28)) | Y28: =IF(AND(A28="line",D28="quote"),SUMIFS($N$2:$N$500,$W$2:$W$500,W28,$D$2:$D$500,"invoice",$A$2:$A$500,"line"),"") | Z28: =IF(AND(A28="line",D28="quote"),COUNTIFS($W$2:$W$500,W28,$D$2:$D$500,"invoice",$A$2:$A$500,"line"),"") | AA28: =IF(AND(A28="line",D28="invoice"),COUNTIFS($W$2:$W$500,W28,$D$2:$D$500,"quote",$A$2:$A$500,"line"),"") | AB28: =IF(A28<>"line","",IF(D28="quote",IF(Z28=0,"quote only",IF(ABS(Y28-N28)>Settings!$B$2,"amount differs","match")),IF(AA28=0,"invoice only","match"))) | AC28: =IF(AND(A28="line",AB28<>"match",COUNTIFS($A$2:$A$500,"coverage",$B$2:$B$500,B28,$C$2:$C$500,C28,$D$2:$D$500,"invoice")>0),MAX($AC$1:AC27)+1,"") | AD28: =IF(A28<>"line","",IF(O28="UNMAPPED","no mapping rule",IF(P28="L","low confidence",""))) | AE28: =IF(AD28<>"",MAX($AE$1:AE27)+1,"") | AF28: =IF(A28="coverage",MAX($AF$1:AF27)+1,"") | AG28: =IF(A28="line",IF(COUNTIFS($B$1:B27,B28,$C$1:C27,C28,$A$1:A27,"line")=0,MAX($AG$1:AG27)+1,""),"")
A29: line | B29: Project Alpha | C29: Vendor B | D29: quote | E29: Q-1002 | F29: 2026-05-10 | H29: 1 | I29: 1 | J29: Meeting table MT-3200 | K29: Meeting table 3200 | L29: 4 | M29: 2900 | N29: 11600 | O29: PRODUCT | P29: H | V29: Project Alpha__Vendor B__quote__Q-1002.pdf | W29: =IF(A29="line",IF(D29="quote",E29,G29)&"|"&LOWER(TRIM(K29)),"") | X29: =IF(OR(O29="LABOUR",O29="INSTALL"),"LABOUR_ALL",IF(O29="","",O29)) | Y29: =IF(AND(A29="line",D29="quote"),SUMIFS($N$2:$N$500,$W$2:$W$500,W29,$D$2:$D$500,"invoice",$A$2:$A$500,"line"),"") | Z29: =IF(AND(A29="line",D29="quote"),COUNTIFS($W$2:$W$500,W29,$D$2:$D$500,"invoice",$A$2:$A$500,"line"),"") | AA29: =IF(AND(A29="line",D29="invoice"),COUNTIFS($W$2:$W$500,W29,$D$2:$D$500,"quote",$A$2:$A$500,"line"),"") | AB29: =IF(A29<>"line","",IF(D29="quote",IF(Z29=0,"quote only",IF(ABS(Y29-N29)>Settings!$B$2,"amount differs","match")),IF(AA29=0,"invoice only","match"))) | AC29: =IF(AND(A29="line",AB29<>"match",COUNTIFS($A$2:$A$500,"coverage",$B$2:$B$500,B29,$C$2:$C$500,C29,$D$2:$D$500,"invoice")>0),MAX($AC$1:AC28)+1,"") | AD29: =IF(A29<>"line","",IF(O29="UNMAPPED","no mapping rule",IF(P29="L","low confidence",""))) | AE29: =IF(AD29<>"",MAX($AE$1:AE28)+1,"") | AF29: =IF(A29="coverage",MAX($AF$1:AF28)+1,"") | AG29: =IF(A29="line",IF(COUNTIFS($B$1:B28,B29,$C$1:C28,C29,$A$1:A28,"line")=0,MAX($AG$1:AG28)+1,""),"")
A30: line | B30: Project Alpha | C30: Vendor B | D30: quote | E30: Q-1002 | F30: 2026-05-10 | H30: 2 | I30: 2 | J30: Conference chair | K30: Conference chair | L30: 32 | M30: 410 | N30: 13120 | O30: PRODUCT | P30: M | Q30: scan, figure clear | V30: Project Alpha__Vendor B__quote__Q-1002.pdf | W30: =IF(A30="line",IF(D30="quote",E30,G30)&"|"&LOWER(TRIM(K30)),"") | X30: =IF(OR(O30="LABOUR",O30="INSTALL"),"LABOUR_ALL",IF(O30="","",O30)) | Y30: =IF(AND(A30="line",D30="quote"),SUMIFS($N$2:$N$500,$W$2:$W$500,W30,$D$2:$D$500,"invoice",$A$2:$A$500,"line"),"") | Z30: =IF(AND(A30="line",D30="quote"),COUNTIFS($W$2:$W$500,W30,$D$2:$D$500,"invoice",$A$2:$A$500,"line"),"") | AA30: =IF(AND(A30="line",D30="invoice"),COUNTIFS($W$2:$W$500,W30,$D$2:$D$500,"quote",$A$2:$A$500,"line"),"") | AB30: =IF(A30<>"line","",IF(D30="quote",IF(Z30=0,"quote only",IF(ABS(Y30-N30)>Settings!$B$2,"amount differs","match")),IF(AA30=0,"invoice only","match"))) | AC30: =IF(AND(A30="line",AB30<>"match",COUNTIFS($A$2:$A$500,"coverage",$B$2:$B$500,B30,$C$2:$C$500,C30,$D$2:$D$500,"invoice")>0),MAX($AC$1:AC29)+1,"") | AD30: =IF(A30<>"line","",IF(O30="UNMAPPED","no mapping rule",IF(P30="L","low confidence",""))) | AE30: =IF(AD30<>"",MAX($AE$1:AE29)+1,"") | AF30: =IF(A30="coverage",MAX($AF$1:AF29)+1,"") | AG30: =IF(A30="line",IF(COUNTIFS($B$1:B29,B30,$C$1:C29,C30,$A$1:A29,"line")=0,MAX($AG$1:AG29)+1,""),"")
A31: line | B31: Project Alpha | C31: Vendor B | D31: quote | E31: Q-1002 | F31: 2026-05-10 | H31: 2 | I31: 3 | J31: Credenza | K31: Credenza | L31: 4 | M31: 1450 | N31: 5800 | O31: PRODUCT | P31: L | Q31: figure partly legible | V31: Project Alpha__Vendor B__quote__Q-1002.pdf | W31: =IF(A31="line",IF(D31="quote",E31,G31)&"|"&LOWER(TRIM(K31)),"") | X31: =IF(OR(O31="LABOUR",O31="INSTALL"),"LABOUR_ALL",IF(O31="","",O31)) | Y31: =IF(AND(A31="line",D31="quote"),SUMIFS($N$2:$N$500,$W$2:$W$500,W31,$D$2:$D$500,"invoice",$A$2:$A$500,"line"),"") | Z31: =IF(AND(A31="line",D31="quote"),COUNTIFS($W$2:$W$500,W31,$D$2:$D$500,"invoice",$A$2:$A$500,"line"),"") | AA31: =IF(AND(A31="line",D31="invoice"),COUNTIFS($W$2:$W$500,W31,$D$2:$D$500,"quote",$A$2:$A$500,"line"),"") | AB31: =IF(A31<>"line","",IF(D31="quote",IF(Z31=0,"quote only",IF(ABS(Y31-N31)>Settings!$B$2,"amount differs","match")),IF(AA31=0,"invoice only","match"))) | AC31: =IF(AND(A31="line",AB31<>"match",COUNTIFS($A$2:$A$500,"coverage",$B$2:$B$500,B31,$C$2:$C$500,C31,$D$2:$D$500,"invoice")>0),MAX($AC$1:AC30)+1,"") | AD31: =IF(A31<>"line","",IF(O31="UNMAPPED","no mapping rule",IF(P31="L","low confidence",""))) | AE31: =IF(AD31<>"",MAX($AE$1:AE30)+1,"") | AF31: =IF(A31="coverage",MAX($AF$1:AF30)+1,"") | AG31: =IF(A31="line",IF(COUNTIFS($B$1:B30,B31,$C$1:C30,C31,$A$1:A30,"line")=0,MAX($AG$1:AG30)+1,""),"")
A32: line | B32: Project Alpha | C32: Vendor B | D32: quote | E32: Q-1002 | F32: 2026-05-10 | H32: 3 | I32: 4 | J32: Labour | K32: Delivery and installation | N32: 4200 | O32: INSTALL | P32: M | Q32: matched by principle | V32: Project Alpha__Vendor B__quote__Q-1002.pdf | W32: =IF(A32="line",IF(D32="quote",E32,G32)&"|"&LOWER(TRIM(K32)),"") | X32: =IF(OR(O32="LABOUR",O32="INSTALL"),"LABOUR_ALL",IF(O32="","",O32)) | Y32: =IF(AND(A32="line",D32="quote"),SUMIFS($N$2:$N$500,$W$2:$W$500,W32,$D$2:$D$500,"invoice",$A$2:$A$500,"line"),"") | Z32: =IF(AND(A32="line",D32="quote"),COUNTIFS($W$2:$W$500,W32,$D$2:$D$500,"invoice",$A$2:$A$500,"line"),"") | AA32: =IF(AND(A32="line",D32="invoice"),COUNTIFS($W$2:$W$500,W32,$D$2:$D$500,"quote",$A$2:$A$500,"line"),"") | AB32: =IF(A32<>"line","",IF(D32="quote",IF(Z32=0,"quote only",IF(ABS(Y32-N32)>Settings!$B$2,"amount differs","match")),IF(AA32=0,"invoice only","match"))) | AC32: =IF(AND(A32="line",AB32<>"match",COUNTIFS($A$2:$A$500,"coverage",$B$2:$B$500,B32,$C$2:$C$500,C32,$D$2:$D$500,"invoice")>0),MAX($AC$1:AC31)+1,"") | AD32: =IF(A32<>"line","",IF(O32="UNMAPPED","no mapping rule",IF(P32="L","low confidence",""))) | AE32: =IF(AD32<>"",MAX($AE$1:AE31)+1,"") | AF32: =IF(A32="coverage",MAX($AF$1:AF31)+1,"") | AG32: =IF(A32="line",IF(COUNTIFS($B$1:B31,B32,$C$1:C31,C32,$A$1:A31,"line")=0,MAX($AG$1:AG31)+1,""),"")
A33: total | B33: Project Alpha | C33: Vendor B | D33: quote | E33: Q-1002 | F33: 2026-05-10 | H33: 4 | J33: Product subtotal | N33: 30620 | O33: PRODUCT | P33: H | V33: Project Alpha__Vendor B__quote__Q-1002.pdf | W33: =IF(A33="line",IF(D33="quote",E33,G33)&"|"&LOWER(TRIM(K33)),"") | X33: =IF(OR(O33="LABOUR",O33="INSTALL"),"LABOUR_ALL",IF(O33="","",O33)) | Y33: =IF(AND(A33="line",D33="quote"),SUMIFS($N$2:$N$500,$W$2:$W$500,W33,$D$2:$D$500,"invoice",$A$2:$A$500,"line"),"") | Z33: =IF(AND(A33="line",D33="quote"),COUNTIFS($W$2:$W$500,W33,$D$2:$D$500,"invoice",$A$2:$A$500,"line"),"") | AA33: =IF(AND(A33="line",D33="invoice"),COUNTIFS($W$2:$W$500,W33,$D$2:$D$500,"quote",$A$2:$A$500,"line"),"") | AB33: =IF(A33<>"line","",IF(D33="quote",IF(Z33=0,"quote only",IF(ABS(Y33-N33)>Settings!$B$2,"amount differs","match")),IF(AA33=0,"invoice only","match"))) | AC33: =IF(AND(A33="line",AB33<>"match",COUNTIFS($A$2:$A$500,"coverage",$B$2:$B$500,B33,$C$2:$C$500,C33,$D$2:$D$500,"invoice")>0),MAX($AC$1:AC32)+1,"") | AD33: =IF(A33<>"line","",IF(O33="UNMAPPED","no mapping rule",IF(P33="L","low confidence",""))) | AE33: =IF(AD33<>"",MAX($AE$1:AE32)+1,"") | AF33: =IF(A33="coverage",MAX($AF$1:AF32)+1,"") | AG33: =IF(A33="line",IF(COUNTIFS($B$1:B32,B33,$C$1:C32,C33,$A$1:A32,"line")=0,MAX($AG$1:AG32)+1,""),"")
A34: total | B34: Project Alpha | C34: Vendor B | D34: quote | E34: Q-1002 | F34: 2026-05-10 | H34: 4 | J34: Grand total | N34: 34820 | O34: GRAND | P34: H | V34: Project Alpha__Vendor B__quote__Q-1002.pdf | W34: =IF(A34="line",IF(D34="quote",E34,G34)&"|"&LOWER(TRIM(K34)),"") | X34: =IF(OR(O34="LABOUR",O34="INSTALL"),"LABOUR_ALL",IF(O34="","",O34)) | Y34: =IF(AND(A34="line",D34="quote"),SUMIFS($N$2:$N$500,$W$2:$W$500,W34,$D$2:$D$500,"invoice",$A$2:$A$500,"line"),"") | Z34: =IF(AND(A34="line",D34="quote"),COUNTIFS($W$2:$W$500,W34,$D$2:$D$500,"invoice",$A$2:$A$500,"line"),"") | AA34: =IF(AND(A34="line",D34="invoice"),COUNTIFS($W$2:$W$500,W34,$D$2:$D$500,"quote",$A$2:$A$500,"line"),"") | AB34: =IF(A34<>"line","",IF(D34="quote",IF(Z34=0,"quote only",IF(ABS(Y34-N34)>Settings!$B$2,"amount differs","match")),IF(AA34=0,"invoice only","match"))) | AC34: =IF(AND(A34="line",AB34<>"match",COUNTIFS($A$2:$A$500,"coverage",$B$2:$B$500,B34,$C$2:$C$500,C34,$D$2:$D$500,"invoice")>0),MAX($AC$1:AC33)+1,"") | AD34: =IF(A34<>"line","",IF(O34="UNMAPPED","no mapping rule",IF(P34="L","low confidence",""))) | AE34: =IF(AD34<>"",MAX($AE$1:AE33)+1,"") | AF34: =IF(A34="coverage",MAX($AF$1:AF33)+1,"") | AG34: =IF(A34="line",IF(COUNTIFS($B$1:B33,B34,$C$1:C33,C34,$A$1:A33,"line")=0,MAX($AG$1:AG33)+1,""),"")
A35: coverage | B35: Project Alpha | C35: Vendor B | D35: quote | E35: Q-1002 | F35: 2026-05-10 | Q35: page 5 illegible | R35: 5 | S35: 1-4 | T35: scan | U35: Y | V35: Project Alpha__Vendor B__quote__Q-1002.pdf | W35: =IF(A35="line",IF(D35="quote",E35,G35)&"|"&LOWER(TRIM(K35)),"") | X35: =IF(OR(O35="LABOUR",O35="INSTALL"),"LABOUR_ALL",IF(O35="","",O35)) | Y35: =IF(AND(A35="line",D35="quote"),SUMIFS($N$2:$N$500,$W$2:$W$500,W35,$D$2:$D$500,"invoice",$A$2:$A$500,"line"),"") | Z35: =IF(AND(A35="line",D35="quote"),COUNTIFS($W$2:$W$500,W35,$D$2:$D$500,"invoice",$A$2:$A$500,"line"),"") | AA35: =IF(AND(A35="line",D35="invoice"),COUNTIFS($W$2:$W$500,W35,$D$2:$D$500,"quote",$A$2:$A$500,"line"),"") | AB35: =IF(A35<>"line","",IF(D35="quote",IF(Z35=0,"quote only",IF(ABS(Y35-N35)>Settings!$B$2,"amount differs","match")),IF(AA35=0,"invoice only","match"))) | AC35: =IF(AND(A35="line",AB35<>"match",COUNTIFS($A$2:$A$500,"coverage",$B$2:$B$500,B35,$C$2:$C$500,C35,$D$2:$D$500,"invoice")>0),MAX($AC$1:AC34)+1,"") | AD35: =IF(A35<>"line","",IF(O35="UNMAPPED","no mapping rule",IF(P35="L","low confidence",""))) | AE35: =IF(AD35<>"",MAX($AE$1:AE34)+1,"") | AF35: =IF(A35="coverage",MAX($AF$1:AF34)+1,"") | AG35: =IF(A35="line",IF(COUNTIFS($B$1:B34,B35,$C$1:C34,C35,$A$1:A34,"line")=0,MAX($AG$1:AG34)+1,""),"")
W36: =IF(A36="line",IF(D36="quote",E36,G36)&"|"&LOWER(TRIM(K36)),"") | X36: =IF(OR(O36="LABOUR",O36="INSTALL"),"LABOUR_ALL",IF(O36="","",O36)) | Y36: =IF(AND(A36="line",D36="quote"),SUMIFS($N$2:$N$500,$W$2:$W$500,W36,$D$2:$D$500,"invoice",$A$2:$A$500,"line"),"") | Z36: =IF(AND(A36="line",D36="quote"),COUNTIFS($W$2:$W$500,W36,$D$2:$D$500,"invoice",$A$2:$A$500,"line"),"") | AA36: =IF(AND(A36="line",D36="invoice"),COUNTIFS($W$2:$W$500,W36,$D$2:$D$500,"quote",$A$2:$A$500,"line"),"") | AB36: =IF(A36<>"line","",IF(D36="quote",IF(Z36=0,"quote only",IF(ABS(Y36-N36)>Settings!$B$2,"amount differs","match")),IF(AA36=0,"invoice only","match"))) | AC36: =IF(AND(A36="line",AB36<>"match",COUNTIFS($A$2:$A$500,"coverage",$B$2:$B$500,B36,$C$2:$C$500,C36,$D$2:$D$500,"invoice")>0),MAX($AC$1:AC35)+1,"") | AD36: =IF(A36<>"line","",IF(O36="UNMAPPED","no mapping rule",IF(P36="L","low confidence",""))) | AE36: =IF(AD36<>"",MAX($AE$1:AE35)+1,"") | AF36: =IF(A36="coverage",MAX($AF$1:AF35)+1,"") | AG36: =IF(A36="line",IF(COUNTIFS($B$1:B35,B36,$C$1:C35,C36,$A$1:A35,"line")=0,MAX($AG$1:AG35)+1,""),"")
W37: =IF(A37="line",IF(D37="quote",E37,G37)&"|"&LOWER(TRIM(K37)),"") | X37: =IF(OR(O37="LABOUR",O37="INSTALL"),"LABOUR_ALL",IF(O37="","",O37)) | Y37: =IF(AND(A37="line",D37="quote"),SUMIFS($N$2:$N$500,$W$2:$W$500,W37,$D$2:$D$500,"invoice",$A$2:$A$500,"line"),"") | Z37: =IF(AND(A37="line",D37="quote"),COUNTIFS($W$2:$W$500,W37,$D$2:$D$500,"invoice",$A$2:$A$500,"line"),"") | AA37: =IF(AND(A37="line",D37="invoice"),COUNTIFS($W$2:$W$500,W37,$D$2:$D$500,"quote",$A$2:$A$500,"line"),"") | AB37: =IF(A37<>"line","",IF(D37="quote",IF(Z37=0,"quote only",IF(ABS(Y37-N37)>Settings!$B$2,"amount differs","match")),IF(AA37=0,"invoice only","match"))) | AC37: =IF(AND(A37="line",AB37<>"match",COUNTIFS($A$2:$A$500,"coverage",$B$2:$B$500,B37,$C$2:$C$500,C37,$D$2:$D$500,"invoice")>0),MAX($AC$1:AC36)+1,"") | AD37: =IF(A37<>"line","",IF(O37="UNMAPPED","no mapping rule",IF(P37="L","low confidence",""))) | AE37: =IF(AD37<>"",MAX($AE$1:AE36)+1,"") | AF37: =IF(A37="coverage",MAX($AF$1:AF36)+1,"") | AG37: =IF(A37="line",IF(COUNTIFS($B$1:B36,B37,$C$1:C36,C37,$A$1:A36,"line")=0,MAX($AG$1:AG36)+1,""),"")
W38: =IF(A38="line",IF(D38="quote",E38,G38)&"|"&LOWER(TRIM(K38)),"") | X38: =IF(OR(O38="LABOUR",O38="INSTALL"),"LABOUR_ALL",IF(O38="","",O38)) | Y38: =IF(AND(A38="line",D38="quote"),SUMIFS($N$2:$N$500,$W$2:$W$500,W38,$D$2:$D$500,"invoice",$A$2:$A$500,"line"),"") | Z38: =IF(AND(A38="line",D38="quote"),COUNTIFS($W$2:$W$500,W38,$D$2:$D$500,"invoice",$A$2:$A$500,"line"),"") | AA38: =IF(AND(A38="line",D38="invoice"),COUNTIFS($W$2:$W$500,W38,$D$2:$D$500,"quote",$A$2:$A$500,"line"),"") | AB38: =IF(A38<>"line","",IF(D38="quote",IF(Z38=0,"quote only",IF(ABS(Y38-N38)>Settings!$B$2,"amount differs","match")),IF(AA38=0,"invoice only","match"))) | AC38: =IF(AND(A38="line",AB38<>"match",COUNTIFS($A$2:$A$500,"coverage",$B$2:$B$500,B38,$C$2:$C$500,C38,$D$2:$D$500,"invoice")>0),MAX($AC$1:AC37)+1,"") | AD38: =IF(A38<>"line","",IF(O38="UNMAPPED","no mapping rule",IF(P38="L","low confidence",""))) | AE38: =IF(AD38<>"",MAX($AE$1:AE37)+1,"") | AF38: =IF(A38="coverage",MAX($AF$1:AF37)+1,"") | AG38: =IF(A38="line",IF(COUNTIFS($B$1:B37,B38,$C$1:C37,C38,$A$1:A37,"line")=0,MAX($AG$1:AG37)+1,""),"")
W39: =IF(A39="line",IF(D39="quote",E39,G39)&"|"&LOWER(TRIM(K39)),"") | X39: =IF(OR(O39="LABOUR",O39="INSTALL"),"LABOUR_ALL",IF(O39="","",O39)) | Y39: =IF(AND(A39="line",D39="quote"),SUMIFS($N$2:$N$500,$W$2:$W$500,W39,$D$2:$D$500,"invoice",$A$2:$A$500,"line"),"") | Z39: =IF(AND(A39="line",D39="quote"),COUNTIFS($W$2:$W$500,W39,$D$2:$D$500,"invoice",$A$2:$A$500,"line"),"") | AA39: =IF(AND(A39="line",D39="invoice"),COUNTIFS($W$2:$W$500,W39,$D$2:$D$500,"quote",$A$2:$A$500,"line"),"") | AB39: =IF(A39<>"line","",IF(D39="quote",IF(Z39=0,"quote only",IF(ABS(Y39-N39)>Settings!$B$2,"amount differs","match")),IF(AA39=0,"invoice only","match"))) | AC39: =IF(AND(A39="line",AB39<>"match",COUNTIFS($A$2:$A$500,"coverage",$B$2:$B$500,B39,$C$2:$C$500,C39,$D$2:$D$500,"invoice")>0),MAX($AC$1:AC38)+1,"") | AD39: =IF(A39<>"line","",IF(O39="UNMAPPED","no mapping rule",IF(P39="L","low confidence",""))) | AE39: =IF(AD39<>"",MAX($AE$1:AE38)+1,"") | AF39: =IF(A39="coverage",MAX($AF$1:AF38)+1,"") | AG39: =IF(A39="line",IF(COUNTIFS($B$1:B38,B39,$C$1:C38,C39,$A$1:A38,"line")=0,MAX($AG$1:AG38)+1,""),"")
W40: =IF(A40="line",IF(D40="quote",E40,G40)&"|"&LOWER(TRIM(K40)),"") | X40: =IF(OR(O40="LABOUR",O40="INSTALL"),"LABOUR_ALL",IF(O40="","",O40)) | Y40: =IF(AND(A40="line",D40="quote"),SUMIFS($N$2:$N$500,$W$2:$W$500,W40,$D$2:$D$500,"invoice",$A$2:$A$500,"line"),"") | Z40: =IF(AND(A40="line",D40="quote"),COUNTIFS($W$2:$W$500,W40,$D$2:$D$500,"invoice",$A$2:$A$500,"line"),"") | AA40: =IF(AND(A40="line",D40="invoice"),COUNTIFS($W$2:$W$500,W40,$D$2:$D$500,"quote",$A$2:$A$500,"line"),"") | AB40: =IF(A40<>"line","",IF(D40="quote",IF(Z40=0,"quote only",IF(ABS(Y40-N40)>Settings!$B$2,"amount differs","match")),IF(AA40=0,"invoice only","match"))) | AC40: =IF(AND(A40="line",AB40<>"match",COUNTIFS($A$2:$A$500,"coverage",$B$2:$B$500,B40,$C$2:$C$500,C40,$D$2:$D$500,"invoice")>0),MAX($AC$1:AC39)+1,"") | AD40: =IF(A40<>"line","",IF(O40="UNMAPPED","no mapping rule",IF(P40="L","low confidence",""))) | AE40: =IF(AD40<>"",MAX($AE$1:AE39)+1,"") | AF40: =IF(A40="coverage",MAX($AF$1:AF39)+1,"") | AG40: =IF(A40="line",IF(COUNTIFS($B$1:B39,B40,$C$1:C39,C40,$A$1:A39,"line")=0,MAX($AG$1:AG39)+1,""),"")
W41: =IF(A41="line",IF(D41="quote",E41,G41)&"|"&LOWER(TRIM(K41)),"") | X41: =IF(OR(O41="LABOUR",O41="INSTALL"),"LABOUR_ALL",IF(O41="","",O41)) | Y41: =IF(AND(A41="line",D41="quote"),SUMIFS($N$2:$N$500,$W$2:$W$500,W41,$D$2:$D$500,"invoice",$A$2:$A$500,"line"),"") | Z41: =IF(AND(A41="line",D41="quote"),COUNTIFS($W$2:$W$500,W41,$D$2:$D$500,"invoice",$A$2:$A$500,"line"),"") | AA41: =IF(AND(A41="line",D41="invoice"),COUNTIFS($W$2:$W$500,W41,$D$2:$D$500,"quote",$A$2:$A$500,"line"),"") | AB41: =IF(A41<>"line","",IF(D41="quote",IF(Z41=0,"quote only",IF(ABS(Y41-N41)>Settings!$B$2,"amount differs","match")),IF(AA41=0,"invoice only","match"))) | AC41: =IF(AND(A41="line",AB41<>"match",COUNTIFS($A$2:$A$500,"coverage",$B$2:$B$500,B41,$C$2:$C$500,C41,$D$2:$D$500,"invoice")>0),MAX($AC$1:AC40)+1,"") | AD41: =IF(A41<>"line","",IF(O41="UNMAPPED","no mapping rule",IF(P41="L","low confidence",""))) | AE41: =IF(AD41<>"",MAX($AE$1:AE40)+1,"") | AF41: =IF(A41="coverage",MAX($AF$1:AF40)+1,"") | AG41: =IF(A41="line",IF(COUNTIFS($B$1:B40,B41,$C$1:C40,C41,$A$1:A40,"line")=0,MAX($AG$1:AG40)+1,""),"")
W42: =IF(A42="line",IF(D42="quote",E42,G42)&"|"&LOWER(TRIM(K42)),"") | X42: =IF(OR(O42="LABOUR",O42="INSTALL"),"LABOUR_ALL",IF(O42="","",O42)) | Y42: =IF(AND(A42="line",D42="quote"),SUMIFS($N$2:$N$500,$W$2:$W$500,W42,$D$2:$D$500,"invoice",$A$2:$A$500,"line"),"") | Z42: =IF(AND(A42="line",D42="quote"),COUNTIFS($W$2:$W$500,W42,$D$2:$D$500,"invoice",$A$2:$A$500,"line"),"") | AA42: =IF(AND(A42="line",D42="invoice"),COUNTIFS($W$2:$W$500,W42,$D$2:$D$500,"quote",$A$2:$A$500,"line"),"") | AB42: =IF(A42<>"line","",IF(D42="quote",IF(Z42=0,"quote only",IF(ABS(Y42-N42)>Settings!$B$2,"amount differs","match")),IF(AA42=0,"invoice only","match"))) | AC42: =IF(AND(A42="line",AB42<>"match",COUNTIFS($A$2:$A$500,"coverage",$B$2:$B$500,B42,$C$2:$C$500,C42,$D$2:$D$500,"invoice")>0),MAX($AC$1:AC41)+1,"") | AD42: =IF(A42<>"line","",IF(O42="UNMAPPED","no mapping rule",IF(P42="L","low confidence",""))) | AE42: =IF(AD42<>"",MAX($AE$1:AE41)+1,"") | AF42: =IF(A42="coverage",MAX($AF$1:AF41)+1,"") | AG42: =IF(A42="line",IF(COUNTIFS($B$1:B41,B42,$C$1:C41,C42,$A$1:A41,"line")=0,MAX($AG$1:AG41)+1,""),"")
W43: =IF(A43="line",IF(D43="quote",E43,G43)&"|"&LOWER(TRIM(K43)),"") | X43: =IF(OR(O43="LABOUR",O43="INSTALL"),"LABOUR_ALL",IF(O43="","",O43)) | Y43: =IF(AND(A43="line",D43="quote"),SUMIFS($N$2:$N$500,$W$2:$W$500,W43,$D$2:$D$500,"invoice",$A$2:$A$500,"line"),"") | Z43: =IF(AND(A43="line",D43="quote"),COUNTIFS($W$2:$W$500,W43,$D$2:$D$500,"invoice",$A$2:$A$500,"line"),"") | AA43: =IF(AND(A43="line",D43="invoice"),COUNTIFS($W$2:$W$500,W43,$D$2:$D$500,"quote",$A$2:$A$500,"line"),"") | AB43: =IF(A43<>"line","",IF(D43="quote",IF(Z43=0,"quote only",IF(ABS(Y43-N43)>Settings!$B$2,"amount differs","match")),IF(AA43=0,"invoice only","match"))) | AC43: =IF(AND(A43="line",AB43<>"match",COUNTIFS($A$2:$A$500,"coverage",$B$2:$B$500,B43,$C$2:$C$500,C43,$D$2:$D$500,"invoice")>0),MAX($AC$1:AC42)+1,"") | AD43: =IF(A43<>"line","",IF(O43="UNMAPPED","no mapping rule",IF(P43="L","low confidence",""))) | AE43: =IF(AD43<>"",MAX($AE$1:AE42)+1,"") | AF43: =IF(A43="coverage",MAX($AF$1:AF42)+1,"") | AG43: =IF(A43="line",IF(COUNTIFS($B$1:B42,B43,$C$1:C42,C43,$A$1:A42,"line")=0,MAX($AG$1:AG42)+1,""),"")
W44: =IF(A44="line",IF(D44="quote",E44,G44)&"|"&LOWER(TRIM(K44)),"") | X44: =IF(OR(O44="LABOUR",O44="INSTALL"),"LABOUR_ALL",IF(O44="","",O44)) | Y44: =IF(AND(A44="line",D44="quote"),SUMIFS($N$2:$N$500,$W$2:$W$500,W44,$D$2:$D$500,"invoice",$A$2:$A$500,"line"),"") | Z44: =IF(AND(A44="line",D44="quote"),COUNTIFS($W$2:$W$500,W44,$D$2:$D$500,"invoice",$A$2:$A$500,"line"),"") | AA44: =IF(AND(A44="line",D44="invoice"),COUNTIFS($W$2:$W$500,W44,$D$2:$D$500,"quote",$A$2:$A$500,"line"),"") | AB44: =IF(A44<>"line","",IF(D44="quote",IF(Z44=0,"quote only",IF(ABS(Y44-N44)>Settings!$B$2,"amount differs","match")),IF(AA44=0,"invoice only","match"))) | AC44: =IF(AND(A44="line",AB44<>"match",COUNTIFS($A$2:$A$500,"coverage",$B$2:$B$500,B44,$C$2:$C$500,C44,$D$2:$D$500,"invoice")>0),MAX($AC$1:AC43)+1,"") | AD44: =IF(A44<>"line","",IF(O44="UNMAPPED","no mapping rule",IF(P44="L","low confidence",""))) | AE44: =IF(AD44<>"",MAX($AE$1:AE43)+1,"") | AF44: =IF(A44="coverage",MAX($AF$1:AF43)+1,"") | AG44: =IF(A44="line",IF(COUNTIFS($B$1:B43,B44,$C$1:C43,C44,$A$1:A43,"line")=0,MAX($AG$1:AG43)+1,""),"")
W45: =IF(A45="line",IF(D45="quote",E45,G45)&"|"&LOWER(TRIM(K45)),"") | X45: =IF(OR(O45="LABOUR",O45="INSTALL"),"LABOUR_ALL",IF(O45="","",O45)) | Y45: =IF(AND(A45="line",D45="quote"),SUMIFS($N$2:$N$500,$W$2:$W$500,W45,$D$2:$D$500,"invoice",$A$2:$A$500,"line"),"") | Z45: =IF(AND(A45="line",D45="quote"),COUNTIFS($W$2:$W$500,W45,$D$2:$D$500,"invoice",$A$2:$A$500,"line"),"") | AA45: =IF(AND(A45="line",D45="invoice"),COUNTIFS($W$2:$W$500,W45,$D$2:$D$500,"quote",$A$2:$A$500,"line"),"") | AB45: =IF(A45<>"line","",IF(D45="quote",IF(Z45=0,"quote only",IF(ABS(Y45-N45)>Settings!$B$2,"amount differs","match")),IF(AA45=0,"invoice only","match"))) | AC45: =IF(AND(A45="line",AB45<>"match",COUNTIFS($A$2:$A$500,"coverage",$B$2:$B$500,B45,$C$2:$C$500,C45,$D$2:$D$500,"invoice")>0),MAX($AC$1:AC44)+1,"") | AD45: =IF(A45<>"line","",IF(O45="UNMAPPED","no mapping rule",IF(P45="L","low confidence",""))) | AE45: =IF(AD45<>"",MAX($AE$1:AE44)+1,"") | AF45: =IF(A45="coverage",MAX($AF$1:AF44)+1,"") | AG45: =IF(A45="line",IF(COUNTIFS($B$1:B44,B45,$C$1:C44,C45,$A$1:A44,"line")=0,MAX($AG$1:AG44)+1,""),"")
W46: =IF(A46="line",IF(D46="quote",E46,G46)&"|"&LOWER(TRIM(K46)),"") | X46: =IF(OR(O46="LABOUR",O46="INSTALL"),"LABOUR_ALL",IF(O46="","",O46)) | Y46: =IF(AND(A46="line",D46="quote"),SUMIFS($N$2:$N$500,$W$2:$W$500,W46,$D$2:$D$500,"invoice",$A$2:$A$500,"line"),"") | Z46: =IF(AND(A46="line",D46="quote"),COUNTIFS($W$2:$W$500,W46,$D$2:$D$500,"invoice",$A$2:$A$500,"line"),"") | AA46: =IF(AND(A46="line",D46="invoice"),COUNTIFS($W$2:$W$500,W46,$D$2:$D$500,"quote",$A$2:$A$500,"line"),"") | AB46: =IF(A46<>"line","",IF(D46="quote",IF(Z46=0,"quote only",IF(ABS(Y46-N46)>Settings!$B$2,"amount differs","match")),IF(AA46=0,"invoice only","match"))) | AC46: =IF(AND(A46="line",AB46<>"match",COUNTIFS($A$2:$A$500,"coverage",$B$2:$B$500,B46,$C$2:$C$500,C46,$D$2:$D$500,"invoice")>0),MAX($AC$1:AC45)+1,"") | AD46: =IF(A46<>"line","",IF(O46="UNMAPPED","no mapping rule",IF(P46="L","low confidence",""))) | AE46: =IF(AD46<>"",MAX($AE$1:AE45)+1,"") | AF46: =IF(A46="coverage",MAX($AF$1:AF45)+1,"") | AG46: =IF(A46="line",IF(COUNTIFS($B$1:B45,B46,$C$1:C45,C46,$A$1:A45,"line")=0,MAX($AG$1:AG45)+1,""),"")
W47: =IF(A47="line",IF(D47="quote",E47,G47)&"|"&LOWER(TRIM(K47)),"") | X47: =IF(OR(O47="LABOUR",O47="INSTALL"),"LABOUR_ALL",IF(O47="","",O47)) | Y47: =IF(AND(A47="line",D47="quote"),SUMIFS($N$2:$N$500,$W$2:$W$500,W47,$D$2:$D$500,"invoice",$A$2:$A$500,"line"),"") | Z47: =IF(AND(A47="line",D47="quote"),COUNTIFS($W$2:$W$500,W47,$D$2:$D$500,"invoice",$A$2:$A$500,"line"),"") | AA47: =IF(AND(A47="line",D47="invoice"),COUNTIFS($W$2:$W$500,W47,$D$2:$D$500,"quote",$A$2:$A$500,"line"),"") | AB47: =IF(A47<>"line","",IF(D47="quote",IF(Z47=0,"quote only",IF(ABS(Y47-N47)>Settings!$B$2,"amount differs","match")),IF(AA47=0,"invoice only","match"))) | AC47: =IF(AND(A47="line",AB47<>"match",COUNTIFS($A$2:$A$500,"coverage",$B$2:$B$500,B47,$C$2:$C$500,C47,$D$2:$D$500,"invoice")>0),MAX($AC$1:AC46)+1,"") | AD47: =IF(A47<>"line","",IF(O47="UNMAPPED","no mapping rule",IF(P47="L","low confidence",""))) | AE47: =IF(AD47<>"",MAX($AE$1:AE46)+1,"") | AF47: =IF(A47="coverage",MAX($AF$1:AF46)+1,"") | AG47: =IF(A47="line",IF(COUNTIFS($B$1:B46,B47,$C$1:C46,C47,$A$1:A46,"line")=0,MAX($AG$1:AG46)+1,""),"")
... W500: =IF(A500="line",IF(D500="quote",E500,G500)&"|"&LOWER(TRIM(K500)),"") | X500: =IF(OR(O500="LABOUR",O500="INSTALL"),"LABOUR_ALL",IF(O500="","",O500)) | Y500: =IF(AND(A500="line",D500="quote"),SUMIFS($N$2:$N$500,$W$2:$W$500,W500,$D$2:$D$500,"invoice",$A$2:$A$500,"line"),"") | Z500: =IF(AND(A500="line",D500="quote"),COUNTIFS($W$2:$W$500,W500,$D$2:$D$500,"invoice",$A$2:$A$500,"line"),"") | AA500: =IF(AND(A500="line",D500="invoice"),COUNTIFS($W$2:$W$500,W500,$D$2:$D$500,"quote",$A$2:$A$500,"line"),"") | AB500: =IF(A500<>"line","",IF(D500="quote",IF(Z500=0,"quote only",IF(ABS(Y500-N500)>Settings!$B$2,"amount differs","match")),IF(AA500=0,"invoice only","match"))) | AC500: =IF(AND(A500="line",AB500<>"match",COUNTIFS($A$2:$A$500,"coverage",$B$2:$B$500,B500,$C$2:$C$500,C500,$D$2:$D$500,"invoice")>0),MAX($AC$1:AC499)+1,"") | AD500: =IF(A500<>"line","",IF(O500="UNMAPPED","no mapping rule",IF(P500="L","low confidence",""))) | AE500: =IF(AD500<>"",MAX($AE$1:AE499)+1,"") | AF500: =IF(A500="coverage",MAX($AF$1:AF499)+1,"") | AG500: =IF(A500="line",IF(COUNTIFS($B$1:B499,B500,$C$1:C499,C500,$A$1:A499,"line")=0,MAX($AG$1:AG499)+1,""),"")

Sheet Mapping
A1: label_as_printed | B1: category | C1: vendor | D1: note
A2: Installation | B2: INSTALL | C2: any
A3: Install labour | B3: INSTALL | C3: any
A4: Delivery & install | B4: INSTALL | C4: any
A5: Labour | B5: INSTALL | C5: any | D5: Confirm per vendor; some print labour for design time
A6: Design fee | B6: LABOUR | C6: any
A7: Project management | B7: LABOUR | C7: any
A8: Freight | B8: LABOUR | C8: any
A9: Allowance | B9: ALLOWANCE | C9: any
A10: Contingency | B10: ALLOWANCE | C10: any
A11: Sales tax | B11: EXCLUDED | C11: any
A12: Surcharge | B12: EXCLUDED | C12: any

Sheet Notes
A1: tracker_notes (paste Stage 3 output here; column E is a formula)
A2: project | B2: vendor | C2: category | D2: note | E2: key
A3: Project Alpha | B3: Vendor A | C3: LABOUR_ALL | D3: Invoiced above quoted. See Detail: 2 lines, additional installation hours and a higher freight charge. | E3: =IF(A3="","",A3&"|"&B3&"|"&C3)
A4: Project Alpha | B4: Vendor A | C4: INSTALL | D4: Invoiced above quoted. See Detail: 1 invoice-only line, installation hours billed by the hour. | E4: =IF(A4="","",A4&"|"&B4&"|"&C4)
A5: Project Alpha | B5: Vendor A | C5: PRODUCT | D5: matched exactly | E5: =IF(A5="","",A5&"|"&B5&"|"&C5)
A6: Project Alpha | B6: Vendor A | C6: ALLOWANCE | D6: Invoiced below quoted. See Detail: 1 quote-only line, contingency not drawn. | E6: =IF(A6="","",A6&"|"&B6&"|"&C6)
E7: =IF(A7="","",A7&"|"&B7&"|"&C7)
E8: =IF(A8="","",A8&"|"&B8&"|"&C8)
E9: =IF(A9="","",A9&"|"&B9&"|"&C9)
E10: =IF(A10="","",A10&"|"&B10&"|"&C10)
E11: =IF(A11="","",A11&"|"&B11&"|"&C11)
E12: =IF(A12="","",A12&"|"&B12&"|"&C12)
E13: =IF(A13="","",A13&"|"&B13&"|"&C13)
E14: =IF(A14="","",A14&"|"&B14&"|"&C14)
E15: =IF(A15="","",A15&"|"&B15&"|"&C15)
E16: =IF(A16="","",A16&"|"&B16&"|"&C16)
E17: =IF(A17="","",A17&"|"&B17&"|"&C17)
E18: =IF(A18="","",A18&"|"&B18&"|"&C18)
... E52: =IF(A52="","",A52&"|"&B52&"|"&C52)
A60: detail_notes (paste Stage 3 output here; column G is a formula)
A61: project | B61: vendor | C61: doc_id | D61: line_no | E61: standard_ref | F61: note | G61: key
A62: Project Alpha | B62: Vendor A | C62: INV-2001 | D62: 5 | E62: 1 | F62: Hourly installation labour billed on top of the fixed-price installation line. | G62: =IF(C62="","",C62&"|"&D62)
A63: Project Alpha | B63: Vendor A | C63: Q-1001 | D63: 6 | E63: NONE | F63: Freight invoiced above the quoted amount. | G63: =IF(C63="","",C63&"|"&D63)
G64: =IF(C64="","",C64&"|"&D64)
G65: =IF(C65="","",C65&"|"&D65)
G66: =IF(C66="","",C66&"|"&D66)
G67: =IF(C67="","",C67&"|"&D67)
G68: =IF(C68="","",C68&"|"&D68)
G69: =IF(C69="","",C69&"|"&D69)
G70: =IF(C70="","",C70&"|"&D70)
G71: =IF(C71="","",C71&"|"&D71)
G72: =IF(C72="","",C72&"|"&D72)
G73: =IF(C73="","",C73&"|"&D73)
G74: =IF(C74="","",C74&"|"&D74)
G75: =IF(C75="","",C75&"|"&D75)
... G111: =IF(C111="","",C111&"|"&D111)

Sheet Docs
A1: seq | B1: row | C1: doc_id | D1: project | E1: vendor | F1: doc_type | G1: doc_date | H1: pages_total | I1: pages_read | J1: native_or_scan | K1: mapping_provided | L1: source_file | M1: stated_LABOUR_ALL | N1: extracted_LABOUR_ALL | O1: check_LABOUR_ALL | P1: stated_INSTALL | Q1: extracted_INSTALL | R1: check_INSTALL | S1: stated_PRODUCT | T1: extracted_PRODUCT | U1: check_PRODUCT | V1: stated_ALLOWANCE | W1: extracted_ALLOWANCE | X1: check_ALLOWANCE | Y1: stated_GRAND | Z1: extracted_ALL | AA1: check_GRAND | AB1: dup_count | AC1: review_reason | AD1: review_seq
A2: 1 | B2: =IFERROR(MATCH(A2,Lines!$AF$2:$AF$500,0),"") | C2: =IF(B2="","",INDEX(Lines!$E$2:$E$500,B2)&"") | D2: =IF(B2="","",INDEX(Lines!$B$2:$B$500,B2)&"") | E2: =IF(B2="","",INDEX(Lines!$C$2:$C$500,B2)&"") | F2: =IF(B2="","",INDEX(Lines!$D$2:$D$500,B2)&"") | G2: =IF(B2="","",INDEX(Lines!$F$2:$F$500,B2)&"") | H2: =IF(B2="","",INDEX(Lines!$R$2:$R$500,B2)) | I2: =IF(B2="","",INDEX(Lines!$S$2:$S$500,B2)&"") | J2: =IF(B2="","",INDEX(Lines!$T$2:$T$500,B2)&"") | K2: =IF(B2="","",INDEX(Lines!$U$2:$U$500,B2)&"") | L2: =IF(B2="","",INDEX(Lines!$V$2:$V$500,B2)&"") | M2: =IF(C2="","",SUMIFS(Lines!$N$2:$N$500,Lines!$E$2:$E$500,C2,Lines!$A$2:$A$500,"total",Lines!$X$2:$X$500,"LABOUR_ALL")) | N2: =IF(C2="","",SUMIFS(Lines!$N$2:$N$500,Lines!$E$2:$E$500,C2,Lines!$A$2:$A$500,"line",Lines!$X$2:$X$500,"LABOUR_ALL")) | O2: =IF(C2="","",IF(M2=0,"no stated total",IF(ABS(M2-N2)>Settings!$B$2,"MISMATCH","ok"))) | P2: =IF(C2="","",SUMIFS(Lines!$N$2:$N$500,Lines!$E$2:$E$500,C2,Lines!$A$2:$A$500,"total",Lines!$O$2:$O$500,"INSTALL")) | Q2: =IF(C2="","",SUMIFS(Lines!$N$2:$N$500,Lines!$E$2:$E$500,C2,Lines!$A$2:$A$500,"line",Lines!$O$2:$O$500,"INSTALL")) | R2: =IF(C2="","",IF(P2=0,"no stated total",IF(ABS(P2-Q2)>Settings!$B$2,"MISMATCH","ok"))) | S2: =IF(C2="","",SUMIFS(Lines!$N$2:$N$500,Lines!$E$2:$E$500,C2,Lines!$A$2:$A$500,"total",Lines!$O$2:$O$500,"PRODUCT")) | T2: =IF(C2="","",SUMIFS(Lines!$N$2:$N$500,Lines!$E$2:$E$500,C2,Lines!$A$2:$A$500,"line",Lines!$O$2:$O$500,"PRODUCT")) | U2: =IF(C2="","",IF(S2=0,"no stated total",IF(ABS(S2-T2)>Settings!$B$2,"MISMATCH","ok"))) | V2: =IF(C2="","",SUMIFS(Lines!$N$2:$N$500,Lines!$E$2:$E$500,C2,Lines!$A$2:$A$500,"total",Lines!$O$2:$O$500,"ALLOWANCE")) | W2: =IF(C2="","",SUMIFS(Lines!$N$2:$N$500,Lines!$E$2:$E$500,C2,Lines!$A$2:$A$500,"line",Lines!$O$2:$O$500,"ALLOWANCE")) | X2: =IF(C2="","",IF(V2=0,"no stated total",IF(ABS(V2-W2)>Settings!$B$2,"MISMATCH","ok"))) | Y2: =IF(C2="","",SUMIFS(Lines!$N$2:$N$500,Lines!$E$2:$E$500,C2,Lines!$A$2:$A$500,"total",Lines!$O$2:$O$500,"GRAND")) | Z2: =IF(C2="","",SUMIFS(Lines!$N$2:$N$500,Lines!$E$2:$E$500,C2,Lines!$A$2:$A$500,"line")) | AA2: =IF(C2="","",IF(Y2=0,"no stated total",IF(ABS(Y2-Z2)>Settings!$B$2,"MISMATCH","ok"))) | AB2: =IF(C2="","",COUNTIFS(Lines!$E$2:$E$500,C2,Lines!$A$2:$A$500,"coverage")) | AC2: =IF(C2="","",IF(LEN(IF(O2="MISMATCH","lines do not sum to stated total (LABOUR_ALL); ","")&IF(R2="MISMATCH","lines do not sum to stated total (INSTALL); ","")&IF(U2="MISMATCH","lines do not sum to stated total (PRODUCT); ","")&IF(X2="MISMATCH","lines do not sum to stated total (ALLOWANCE); ","")&IF(AA2="MISMATCH","lines do not sum to grand total; ","")&IF(OR(I2="1-"&H2,AND(H2=1,I2="1")),"","pages not read; ")&IF(K2="N","extracted without mapping table; ","")&IF(AB2>1,"document extracted twice; ",""))>2,LEFT(IF(O2="MISMATCH","lines do not sum to stated total (LABOUR_ALL); ","")&IF(R2="MISMATCH","lines do not sum to stated total (INSTALL); ","")&IF(U2="MISMATCH","lines do not sum to stated total (PRODUCT); ","")&IF(X2="MISMATCH","lines do not sum to stated total (ALLOWANCE); ","")&IF(AA2="MISMATCH","lines do not sum to grand total; ","")&IF(OR(I2="1-"&H2,AND(H2=1,I2="1")),"","pages not read; ")&IF(K2="N","extracted without mapping table; ","")&IF(AB2>1,"document extracted twice; ",""),LEN(IF(O2="MISMATCH","lines do not sum to stated total (LABOUR_ALL); ","")&IF(R2="MISMATCH","lines do not sum to stated total (INSTALL); ","")&IF(U2="MISMATCH","lines do not sum to stated total (PRODUCT); ","")&IF(X2="MISMATCH","lines do not sum to stated total (ALLOWANCE); ","")&IF(AA2="MISMATCH","lines do not sum to grand total; ","")&IF(OR(I2="1-"&H2,AND(H2=1,I2="1")),"","pages not read; ")&IF(K2="N","extracted without mapping table; ","")&IF(AB2>1,"document extracted twice; ",""))-2),"")) | AD2: =IF(AC2<>"",MAX($AD$1:AD1)+1,"")
A3: 2 | B3: =IFERROR(MATCH(A3,Lines!$AF$2:$AF$500,0),"") | C3: =IF(B3="","",INDEX(Lines!$E$2:$E$500,B3)&"") | D3: =IF(B3="","",INDEX(Lines!$B$2:$B$500,B3)&"") | E3: =IF(B3="","",INDEX(Lines!$C$2:$C$500,B3)&"") | F3: =IF(B3="","",INDEX(Lines!$D$2:$D$500,B3)&"") | G3: =IF(B3="","",INDEX(Lines!$F$2:$F$500,B3)&"") | H3: =IF(B3="","",INDEX(Lines!$R$2:$R$500,B3)) | I3: =IF(B3="","",INDEX(Lines!$S$2:$S$500,B3)&"") | J3: =IF(B3="","",INDEX(Lines!$T$2:$T$500,B3)&"") | K3: =IF(B3="","",INDEX(Lines!$U$2:$U$500,B3)&"") | L3: =IF(B3="","",INDEX(Lines!$V$2:$V$500,B3)&"") | M3: =IF(C3="","",SUMIFS(Lines!$N$2:$N$500,Lines!$E$2:$E$500,C3,Lines!$A$2:$A$500,"total",Lines!$X$2:$X$500,"LABOUR_ALL")) | N3: =IF(C3="","",SUMIFS(Lines!$N$2:$N$500,Lines!$E$2:$E$500,C3,Lines!$A$2:$A$500,"line",Lines!$X$2:$X$500,"LABOUR_ALL")) | O3: =IF(C3="","",IF(M3=0,"no stated total",IF(ABS(M3-N3)>Settings!$B$2,"MISMATCH","ok"))) | P3: =IF(C3="","",SUMIFS(Lines!$N$2:$N$500,Lines!$E$2:$E$500,C3,Lines!$A$2:$A$500,"total",Lines!$O$2:$O$500,"INSTALL")) | Q3: =IF(C3="","",SUMIFS(Lines!$N$2:$N$500,Lines!$E$2:$E$500,C3,Lines!$A$2:$A$500,"line",Lines!$O$2:$O$500,"INSTALL")) | R3: =IF(C3="","",IF(P3=0,"no stated total",IF(ABS(P3-Q3)>Settings!$B$2,"MISMATCH","ok"))) | S3: =IF(C3="","",SUMIFS(Lines!$N$2:$N$500,Lines!$E$2:$E$500,C3,Lines!$A$2:$A$500,"total",Lines!$O$2:$O$500,"PRODUCT")) | T3: =IF(C3="","",SUMIFS(Lines!$N$2:$N$500,Lines!$E$2:$E$500,C3,Lines!$A$2:$A$500,"line",Lines!$O$2:$O$500,"PRODUCT")) | U3: =IF(C3="","",IF(S3=0,"no stated total",IF(ABS(S3-T3)>Settings!$B$2,"MISMATCH","ok"))) | V3: =IF(C3="","",SUMIFS(Lines!$N$2:$N$500,Lines!$E$2:$E$500,C3,Lines!$A$2:$A$500,"total",Lines!$O$2:$O$500,"ALLOWANCE")) | W3: =IF(C3="","",SUMIFS(Lines!$N$2:$N$500,Lines!$E$2:$E$500,C3,Lines!$A$2:$A$500,"line",Lines!$O$2:$O$500,"ALLOWANCE")) | X3: =IF(C3="","",IF(V3=0,"no stated total",IF(ABS(V3-W3)>Settings!$B$2,"MISMATCH","ok"))) | Y3: =IF(C3="","",SUMIFS(Lines!$N$2:$N$500,Lines!$E$2:$E$500,C3,Lines!$A$2:$A$500,"total",Lines!$O$2:$O$500,"GRAND")) | Z3: =IF(C3="","",SUMIFS(Lines!$N$2:$N$500,Lines!$E$2:$E$500,C3,Lines!$A$2:$A$500,"line")) | AA3: =IF(C3="","",IF(Y3=0,"no stated total",IF(ABS(Y3-Z3)>Settings!$B$2,"MISMATCH","ok"))) | AB3: =IF(C3="","",COUNTIFS(Lines!$E$2:$E$500,C3,Lines!$A$2:$A$500,"coverage")) | AC3: =IF(C3="","",IF(LEN(IF(O3="MISMATCH","lines do not sum to stated total (LABOUR_ALL); ","")&IF(R3="MISMATCH","lines do not sum to stated total (INSTALL); ","")&IF(U3="MISMATCH","lines do not sum to stated total (PRODUCT); ","")&IF(X3="MISMATCH","lines do not sum to stated total (ALLOWANCE); ","")&IF(AA3="MISMATCH","lines do not sum to grand total; ","")&IF(OR(I3="1-"&H3,AND(H3=1,I3="1")),"","pages not read; ")&IF(K3="N","extracted without mapping table; ","")&IF(AB3>1,"document extracted twice; ",""))>2,LEFT(IF(O3="MISMATCH","lines do not sum to stated total (LABOUR_ALL); ","")&IF(R3="MISMATCH","lines do not sum to stated total (INSTALL); ","")&IF(U3="MISMATCH","lines do not sum to stated total (PRODUCT); ","")&IF(X3="MISMATCH","lines do not sum to stated total (ALLOWANCE); ","")&IF(AA3="MISMATCH","lines do not sum to grand total; ","")&IF(OR(I3="1-"&H3,AND(H3=1,I3="1")),"","pages not read; ")&IF(K3="N","extracted without mapping table; ","")&IF(AB3>1,"document extracted twice; ",""),LEN(IF(O3="MISMATCH","lines do not sum to stated total (LABOUR_ALL); ","")&IF(R3="MISMATCH","lines do not sum to stated total (INSTALL); ","")&IF(U3="MISMATCH","lines do not sum to stated total (PRODUCT); ","")&IF(X3="MISMATCH","lines do not sum to stated total (ALLOWANCE); ","")&IF(AA3="MISMATCH","lines do not sum to grand total; ","")&IF(OR(I3="1-"&H3,AND(H3=1,I3="1")),"","pages not read; ")&IF(K3="N","extracted without mapping table; ","")&IF(AB3>1,"document extracted twice; ",""))-2),"")) | AD3: =IF(AC3<>"",MAX($AD$1:AD2)+1,"")
A4: 3 | B4: =IFERROR(MATCH(A4,Lines!$AF$2:$AF$500,0),"") | C4: =IF(B4="","",INDEX(Lines!$E$2:$E$500,B4)&"") | D4: =IF(B4="","",INDEX(Lines!$B$2:$B$500,B4)&"") | E4: =IF(B4="","",INDEX(Lines!$C$2:$C$500,B4)&"") | F4: =IF(B4="","",INDEX(Lines!$D$2:$D$500,B4)&"") | G4: =IF(B4="","",INDEX(Lines!$F$2:$F$500,B4)&"") | H4: =IF(B4="","",INDEX(Lines!$R$2:$R$500,B4)) | I4: =IF(B4="","",INDEX(Lines!$S$2:$S$500,B4)&"") | J4: =IF(B4="","",INDEX(Lines!$T$2:$T$500,B4)&"") | K4: =IF(B4="","",INDEX(Lines!$U$2:$U$500,B4)&"") | L4: =IF(B4="","",INDEX(Lines!$V$2:$V$500,B4)&"") | M4: =IF(C4="","",SUMIFS(Lines!$N$2:$N$500,Lines!$E$2:$E$500,C4,Lines!$A$2:$A$500,"total",Lines!$X$2:$X$500,"LABOUR_ALL")) | N4: =IF(C4="","",SUMIFS(Lines!$N$2:$N$500,Lines!$E$2:$E$500,C4,Lines!$A$2:$A$500,"line",Lines!$X$2:$X$500,"LABOUR_ALL")) | O4: =IF(C4="","",IF(M4=0,"no stated total",IF(ABS(M4-N4)>Settings!$B$2,"MISMATCH","ok"))) | P4: =IF(C4="","",SUMIFS(Lines!$N$2:$N$500,Lines!$E$2:$E$500,C4,Lines!$A$2:$A$500,"total",Lines!$O$2:$O$500,"INSTALL")) | Q4: =IF(C4="","",SUMIFS(Lines!$N$2:$N$500,Lines!$E$2:$E$500,C4,Lines!$A$2:$A$500,"line",Lines!$O$2:$O$500,"INSTALL")) | R4: =IF(C4="","",IF(P4=0,"no stated total",IF(ABS(P4-Q4)>Settings!$B$2,"MISMATCH","ok"))) | S4: =IF(C4="","",SUMIFS(Lines!$N$2:$N$500,Lines!$E$2:$E$500,C4,Lines!$A$2:$A$500,"total",Lines!$O$2:$O$500,"PRODUCT")) | T4: =IF(C4="","",SUMIFS(Lines!$N$2:$N$500,Lines!$E$2:$E$500,C4,Lines!$A$2:$A$500,"line",Lines!$O$2:$O$500,"PRODUCT")) | U4: =IF(C4="","",IF(S4=0,"no stated total",IF(ABS(S4-T4)>Settings!$B$2,"MISMATCH","ok"))) | V4: =IF(C4="","",SUMIFS(Lines!$N$2:$N$500,Lines!$E$2:$E$500,C4,Lines!$A$2:$A$500,"total",Lines!$O$2:$O$500,"ALLOWANCE")) | W4: =IF(C4="","",SUMIFS(Lines!$N$2:$N$500,Lines!$E$2:$E$500,C4,Lines!$A$2:$A$500,"line",Lines!$O$2:$O$500,"ALLOWANCE")) | X4: =IF(C4="","",IF(V4=0,"no stated total",IF(ABS(V4-W4)>Settings!$B$2,"MISMATCH","ok"))) | Y4: =IF(C4="","",SUMIFS(Lines!$N$2:$N$500,Lines!$E$2:$E$500,C4,Lines!$A$2:$A$500,"total",Lines!$O$2:$O$500,"GRAND")) | Z4: =IF(C4="","",SUMIFS(Lines!$N$2:$N$500,Lines!$E$2:$E$500,C4,Lines!$A$2:$A$500,"line")) | AA4: =IF(C4="","",IF(Y4=0,"no stated total",IF(ABS(Y4-Z4)>Settings!$B$2,"MISMATCH","ok"))) | AB4: =IF(C4="","",COUNTIFS(Lines!$E$2:$E$500,C4,Lines!$A$2:$A$500,"coverage")) | AC4: =IF(C4="","",IF(LEN(IF(O4="MISMATCH","lines do not sum to stated total (LABOUR_ALL); ","")&IF(R4="MISMATCH","lines do not sum to stated total (INSTALL); ","")&IF(U4="MISMATCH","lines do not sum to stated total (PRODUCT); ","")&IF(X4="MISMATCH","lines do not sum to stated total (ALLOWANCE); ","")&IF(AA4="MISMATCH","lines do not sum to grand total; ","")&IF(OR(I4="1-"&H4,AND(H4=1,I4="1")),"","pages not read; ")&IF(K4="N","extracted without mapping table; ","")&IF(AB4>1,"document extracted twice; ",""))>2,LEFT(IF(O4="MISMATCH","lines do not sum to stated total (LABOUR_ALL); ","")&IF(R4="MISMATCH","lines do not sum to stated total (INSTALL); ","")&IF(U4="MISMATCH","lines do not sum to stated total (PRODUCT); ","")&IF(X4="MISMATCH","lines do not sum to stated total (ALLOWANCE); ","")&IF(AA4="MISMATCH","lines do not sum to grand total; ","")&IF(OR(I4="1-"&H4,AND(H4=1,I4="1")),"","pages not read; ")&IF(K4="N","extracted without mapping table; ","")&IF(AB4>1,"document extracted twice; ",""),LEN(IF(O4="MISMATCH","lines do not sum to stated total (LABOUR_ALL); ","")&IF(R4="MISMATCH","lines do not sum to stated total (INSTALL); ","")&IF(U4="MISMATCH","lines do not sum to stated total (PRODUCT); ","")&IF(X4="MISMATCH","lines do not sum to stated total (ALLOWANCE); ","")&IF(AA4="MISMATCH","lines do not sum to grand total; ","")&IF(OR(I4="1-"&H4,AND(H4=1,I4="1")),"","pages not read; ")&IF(K4="N","extracted without mapping table; ","")&IF(AB4>1,"document extracted twice; ",""))-2),"")) | AD4: =IF(AC4<>"",MAX($AD$1:AD3)+1,"")
A5: 4 | B5: =IFERROR(MATCH(A5,Lines!$AF$2:$AF$500,0),"") | C5: =IF(B5="","",INDEX(Lines!$E$2:$E$500,B5)&"") | D5: =IF(B5="","",INDEX(Lines!$B$2:$B$500,B5)&"") | E5: =IF(B5="","",INDEX(Lines!$C$2:$C$500,B5)&"") | F5: =IF(B5="","",INDEX(Lines!$D$2:$D$500,B5)&"") | G5: =IF(B5="","",INDEX(Lines!$F$2:$F$500,B5)&"") | H5: =IF(B5="","",INDEX(Lines!$R$2:$R$500,B5)) | I5: =IF(B5="","",INDEX(Lines!$S$2:$S$500,B5)&"") | J5: =IF(B5="","",INDEX(Lines!$T$2:$T$500,B5)&"") | K5: =IF(B5="","",INDEX(Lines!$U$2:$U$500,B5)&"") | L5: =IF(B5="","",INDEX(Lines!$V$2:$V$500,B5)&"") | M5: =IF(C5="","",SUMIFS(Lines!$N$2:$N$500,Lines!$E$2:$E$500,C5,Lines!$A$2:$A$500,"total",Lines!$X$2:$X$500,"LABOUR_ALL")) | N5: =IF(C5="","",SUMIFS(Lines!$N$2:$N$500,Lines!$E$2:$E$500,C5,Lines!$A$2:$A$500,"line",Lines!$X$2:$X$500,"LABOUR_ALL")) | O5: =IF(C5="","",IF(M5=0,"no stated total",IF(ABS(M5-N5)>Settings!$B$2,"MISMATCH","ok"))) | P5: =IF(C5="","",SUMIFS(Lines!$N$2:$N$500,Lines!$E$2:$E$500,C5,Lines!$A$2:$A$500,"total",Lines!$O$2:$O$500,"INSTALL")) | Q5: =IF(C5="","",SUMIFS(Lines!$N$2:$N$500,Lines!$E$2:$E$500,C5,Lines!$A$2:$A$500,"line",Lines!$O$2:$O$500,"INSTALL")) | R5: =IF(C5="","",IF(P5=0,"no stated total",IF(ABS(P5-Q5)>Settings!$B$2,"MISMATCH","ok"))) | S5: =IF(C5="","",SUMIFS(Lines!$N$2:$N$500,Lines!$E$2:$E$500,C5,Lines!$A$2:$A$500,"total",Lines!$O$2:$O$500,"PRODUCT")) | T5: =IF(C5="","",SUMIFS(Lines!$N$2:$N$500,Lines!$E$2:$E$500,C5,Lines!$A$2:$A$500,"line",Lines!$O$2:$O$500,"PRODUCT")) | U5: =IF(C5="","",IF(S5=0,"no stated total",IF(ABS(S5-T5)>Settings!$B$2,"MISMATCH","ok"))) | V5: =IF(C5="","",SUMIFS(Lines!$N$2:$N$500,Lines!$E$2:$E$500,C5,Lines!$A$2:$A$500,"total",Lines!$O$2:$O$500,"ALLOWANCE")) | W5: =IF(C5="","",SUMIFS(Lines!$N$2:$N$500,Lines!$E$2:$E$500,C5,Lines!$A$2:$A$500,"line",Lines!$O$2:$O$500,"ALLOWANCE")) | X5: =IF(C5="","",IF(V5=0,"no stated total",IF(ABS(V5-W5)>Settings!$B$2,"MISMATCH","ok"))) | Y5: =IF(C5="","",SUMIFS(Lines!$N$2:$N$500,Lines!$E$2:$E$500,C5,Lines!$A$2:$A$500,"total",Lines!$O$2:$O$500,"GRAND")) | Z5: =IF(C5="","",SUMIFS(Lines!$N$2:$N$500,Lines!$E$2:$E$500,C5,Lines!$A$2:$A$500,"line")) | AA5: =IF(C5="","",IF(Y5=0,"no stated total",IF(ABS(Y5-Z5)>Settings!$B$2,"MISMATCH","ok"))) | AB5: =IF(C5="","",COUNTIFS(Lines!$E$2:$E$500,C5,Lines!$A$2:$A$500,"coverage")) | AC5: =IF(C5="","",IF(LEN(IF(O5="MISMATCH","lines do not sum to stated total (LABOUR_ALL); ","")&IF(R5="MISMATCH","lines do not sum to stated total (INSTALL); ","")&IF(U5="MISMATCH","lines do not sum to stated total (PRODUCT); ","")&IF(X5="MISMATCH","lines do not sum to stated total (ALLOWANCE); ","")&IF(AA5="MISMATCH","lines do not sum to grand total; ","")&IF(OR(I5="1-"&H5,AND(H5=1,I5="1")),"","pages not read; ")&IF(K5="N","extracted without mapping table; ","")&IF(AB5>1,"document extracted twice; ",""))>2,LEFT(IF(O5="MISMATCH","lines do not sum to stated total (LABOUR_ALL); ","")&IF(R5="MISMATCH","lines do not sum to stated total (INSTALL); ","")&IF(U5="MISMATCH","lines do not sum to stated total (PRODUCT); ","")&IF(X5="MISMATCH","lines do not sum to stated total (ALLOWANCE); ","")&IF(AA5="MISMATCH","lines do not sum to grand total; ","")&IF(OR(I5="1-"&H5,AND(H5=1,I5="1")),"","pages not read; ")&IF(K5="N","extracted without mapping table; ","")&IF(AB5>1,"document extracted twice; ",""),LEN(IF(O5="MISMATCH","lines do not sum to stated total (LABOUR_ALL); ","")&IF(R5="MISMATCH","lines do not sum to stated total (INSTALL); ","")&IF(U5="MISMATCH","lines do not sum to stated total (PRODUCT); ","")&IF(X5="MISMATCH","lines do not sum to stated total (ALLOWANCE); ","")&IF(AA5="MISMATCH","lines do not sum to grand total; ","")&IF(OR(I5="1-"&H5,AND(H5=1,I5="1")),"","pages not read; ")&IF(K5="N","extracted without mapping table; ","")&IF(AB5>1,"document extracted twice; ",""))-2),"")) | AD5: =IF(AC5<>"",MAX($AD$1:AD4)+1,"")
A6: 5 | B6: =IFERROR(MATCH(A6,Lines!$AF$2:$AF$500,0),"") | C6: =IF(B6="","",INDEX(Lines!$E$2:$E$500,B6)&"") | D6: =IF(B6="","",INDEX(Lines!$B$2:$B$500,B6)&"") | E6: =IF(B6="","",INDEX(Lines!$C$2:$C$500,B6)&"") | F6: =IF(B6="","",INDEX(Lines!$D$2:$D$500,B6)&"") | G6: =IF(B6="","",INDEX(Lines!$F$2:$F$500,B6)&"") | H6: =IF(B6="","",INDEX(Lines!$R$2:$R$500,B6)) | I6: =IF(B6="","",INDEX(Lines!$S$2:$S$500,B6)&"") | J6: =IF(B6="","",INDEX(Lines!$T$2:$T$500,B6)&"") | K6: =IF(B6="","",INDEX(Lines!$U$2:$U$500,B6)&"") | L6: =IF(B6="","",INDEX(Lines!$V$2:$V$500,B6)&"") | M6: =IF(C6="","",SUMIFS(Lines!$N$2:$N$500,Lines!$E$2:$E$500,C6,Lines!$A$2:$A$500,"total",Lines!$X$2:$X$500,"LABOUR_ALL")) | N6: =IF(C6="","",SUMIFS(Lines!$N$2:$N$500,Lines!$E$2:$E$500,C6,Lines!$A$2:$A$500,"line",Lines!$X$2:$X$500,"LABOUR_ALL")) | O6: =IF(C6="","",IF(M6=0,"no stated total",IF(ABS(M6-N6)>Settings!$B$2,"MISMATCH","ok"))) | P6: =IF(C6="","",SUMIFS(Lines!$N$2:$N$500,Lines!$E$2:$E$500,C6,Lines!$A$2:$A$500,"total",Lines!$O$2:$O$500,"INSTALL")) | Q6: =IF(C6="","",SUMIFS(Lines!$N$2:$N$500,Lines!$E$2:$E$500,C6,Lines!$A$2:$A$500,"line",Lines!$O$2:$O$500,"INSTALL")) | R6: =IF(C6="","",IF(P6=0,"no stated total",IF(ABS(P6-Q6)>Settings!$B$2,"MISMATCH","ok"))) | S6: =IF(C6="","",SUMIFS(Lines!$N$2:$N$500,Lines!$E$2:$E$500,C6,Lines!$A$2:$A$500,"total",Lines!$O$2:$O$500,"PRODUCT")) | T6: =IF(C6="","",SUMIFS(Lines!$N$2:$N$500,Lines!$E$2:$E$500,C6,Lines!$A$2:$A$500,"line",Lines!$O$2:$O$500,"PRODUCT")) | U6: =IF(C6="","",IF(S6=0,"no stated total",IF(ABS(S6-T6)>Settings!$B$2,"MISMATCH","ok"))) | V6: =IF(C6="","",SUMIFS(Lines!$N$2:$N$500,Lines!$E$2:$E$500,C6,Lines!$A$2:$A$500,"total",Lines!$O$2:$O$500,"ALLOWANCE")) | W6: =IF(C6="","",SUMIFS(Lines!$N$2:$N$500,Lines!$E$2:$E$500,C6,Lines!$A$2:$A$500,"line",Lines!$O$2:$O$500,"ALLOWANCE")) | X6: =IF(C6="","",IF(V6=0,"no stated total",IF(ABS(V6-W6)>Settings!$B$2,"MISMATCH","ok"))) | Y6: =IF(C6="","",SUMIFS(Lines!$N$2:$N$500,Lines!$E$2:$E$500,C6,Lines!$A$2:$A$500,"total",Lines!$O$2:$O$500,"GRAND")) | Z6: =IF(C6="","",SUMIFS(Lines!$N$2:$N$500,Lines!$E$2:$E$500,C6,Lines!$A$2:$A$500,"line")) | AA6: =IF(C6="","",IF(Y6=0,"no stated total",IF(ABS(Y6-Z6)>Settings!$B$2,"MISMATCH","ok"))) | AB6: =IF(C6="","",COUNTIFS(Lines!$E$2:$E$500,C6,Lines!$A$2:$A$500,"coverage")) | AC6: =IF(C6="","",IF(LEN(IF(O6="MISMATCH","lines do not sum to stated total (LABOUR_ALL); ","")&IF(R6="MISMATCH","lines do not sum to stated total (INSTALL); ","")&IF(U6="MISMATCH","lines do not sum to stated total (PRODUCT); ","")&IF(X6="MISMATCH","lines do not sum to stated total (ALLOWANCE); ","")&IF(AA6="MISMATCH","lines do not sum to grand total; ","")&IF(OR(I6="1-"&H6,AND(H6=1,I6="1")),"","pages not read; ")&IF(K6="N","extracted without mapping table; ","")&IF(AB6>1,"document extracted twice; ",""))>2,LEFT(IF(O6="MISMATCH","lines do not sum to stated total (LABOUR_ALL); ","")&IF(R6="MISMATCH","lines do not sum to stated total (INSTALL); ","")&IF(U6="MISMATCH","lines do not sum to stated total (PRODUCT); ","")&IF(X6="MISMATCH","lines do not sum to stated total (ALLOWANCE); ","")&IF(AA6="MISMATCH","lines do not sum to grand total; ","")&IF(OR(I6="1-"&H6,AND(H6=1,I6="1")),"","pages not read; ")&IF(K6="N","extracted without mapping table; ","")&IF(AB6>1,"document extracted twice; ",""),LEN(IF(O6="MISMATCH","lines do not sum to stated total (LABOUR_ALL); ","")&IF(R6="MISMATCH","lines do not sum to stated total (INSTALL); ","")&IF(U6="MISMATCH","lines do not sum to stated total (PRODUCT); ","")&IF(X6="MISMATCH","lines do not sum to stated total (ALLOWANCE); ","")&IF(AA6="MISMATCH","lines do not sum to grand total; ","")&IF(OR(I6="1-"&H6,AND(H6=1,I6="1")),"","pages not read; ")&IF(K6="N","extracted without mapping table; ","")&IF(AB6>1,"document extracted twice; ",""))-2),"")) | AD6: =IF(AC6<>"",MAX($AD$1:AD5)+1,"")
A7: 6 | B7: =IFERROR(MATCH(A7,Lines!$AF$2:$AF$500,0),"") | C7: =IF(B7="","",INDEX(Lines!$E$2:$E$500,B7)&"") | D7: =IF(B7="","",INDEX(Lines!$B$2:$B$500,B7)&"") | E7: =IF(B7="","",INDEX(Lines!$C$2:$C$500,B7)&"") | F7: =IF(B7="","",INDEX(Lines!$D$2:$D$500,B7)&"") | G7: =IF(B7="","",INDEX(Lines!$F$2:$F$500,B7)&"") | H7: =IF(B7="","",INDEX(Lines!$R$2:$R$500,B7)) | I7: =IF(B7="","",INDEX(Lines!$S$2:$S$500,B7)&"") | J7: =IF(B7="","",INDEX(Lines!$T$2:$T$500,B7)&"") | K7: =IF(B7="","",INDEX(Lines!$U$2:$U$500,B7)&"") | L7: =IF(B7="","",INDEX(Lines!$V$2:$V$500,B7)&"") | M7: =IF(C7="","",SUMIFS(Lines!$N$2:$N$500,Lines!$E$2:$E$500,C7,Lines!$A$2:$A$500,"total",Lines!$X$2:$X$500,"LABOUR_ALL")) | N7: =IF(C7="","",SUMIFS(Lines!$N$2:$N$500,Lines!$E$2:$E$500,C7,Lines!$A$2:$A$500,"line",Lines!$X$2:$X$500,"LABOUR_ALL")) | O7: =IF(C7="","",IF(M7=0,"no stated total",IF(ABS(M7-N7)>Settings!$B$2,"MISMATCH","ok"))) | P7: =IF(C7="","",SUMIFS(Lines!$N$2:$N$500,Lines!$E$2:$E$500,C7,Lines!$A$2:$A$500,"total",Lines!$O$2:$O$500,"INSTALL")) | Q7: =IF(C7="","",SUMIFS(Lines!$N$2:$N$500,Lines!$E$2:$E$500,C7,Lines!$A$2:$A$500,"line",Lines!$O$2:$O$500,"INSTALL")) | R7: =IF(C7="","",IF(P7=0,"no stated total",IF(ABS(P7-Q7)>Settings!$B$2,"MISMATCH","ok"))) | S7: =IF(C7="","",SUMIFS(Lines!$N$2:$N$500,Lines!$E$2:$E$500,C7,Lines!$A$2:$A$500,"total",Lines!$O$2:$O$500,"PRODUCT")) | T7: =IF(C7="","",SUMIFS(Lines!$N$2:$N$500,Lines!$E$2:$E$500,C7,Lines!$A$2:$A$500,"line",Lines!$O$2:$O$500,"PRODUCT")) | U7: =IF(C7="","",IF(S7=0,"no stated total",IF(ABS(S7-T7)>Settings!$B$2,"MISMATCH","ok"))) | V7: =IF(C7="","",SUMIFS(Lines!$N$2:$N$500,Lines!$E$2:$E$500,C7,Lines!$A$2:$A$500,"total",Lines!$O$2:$O$500,"ALLOWANCE")) | W7: =IF(C7="","",SUMIFS(Lines!$N$2:$N$500,Lines!$E$2:$E$500,C7,Lines!$A$2:$A$500,"line",Lines!$O$2:$O$500,"ALLOWANCE")) | X7: =IF(C7="","",IF(V7=0,"no stated total",IF(ABS(V7-W7)>Settings!$B$2,"MISMATCH","ok"))) | Y7: =IF(C7="","",SUMIFS(Lines!$N$2:$N$500,Lines!$E$2:$E$500,C7,Lines!$A$2:$A$500,"total",Lines!$O$2:$O$500,"GRAND")) | Z7: =IF(C7="","",SUMIFS(Lines!$N$2:$N$500,Lines!$E$2:$E$500,C7,Lines!$A$2:$A$500,"line")) | AA7: =IF(C7="","",IF(Y7=0,"no stated total",IF(ABS(Y7-Z7)>Settings!$B$2,"MISMATCH","ok"))) | AB7: =IF(C7="","",COUNTIFS(Lines!$E$2:$E$500,C7,Lines!$A$2:$A$500,"coverage")) | AC7: =IF(C7="","",IF(LEN(IF(O7="MISMATCH","lines do not sum to stated total (LABOUR_ALL); ","")&IF(R7="MISMATCH","lines do not sum to stated total (INSTALL); ","")&IF(U7="MISMATCH","lines do not sum to stated total (PRODUCT); ","")&IF(X7="MISMATCH","lines do not sum to stated total (ALLOWANCE); ","")&IF(AA7="MISMATCH","lines do not sum to grand total; ","")&IF(OR(I7="1-"&H7,AND(H7=1,I7="1")),"","pages not read; ")&IF(K7="N","extracted without mapping table; ","")&IF(AB7>1,"document extracted twice; ",""))>2,LEFT(IF(O7="MISMATCH","lines do not sum to stated total (LABOUR_ALL); ","")&IF(R7="MISMATCH","lines do not sum to stated total (INSTALL); ","")&IF(U7="MISMATCH","lines do not sum to stated total (PRODUCT); ","")&IF(X7="MISMATCH","lines do not sum to stated total (ALLOWANCE); ","")&IF(AA7="MISMATCH","lines do not sum to grand total; ","")&IF(OR(I7="1-"&H7,AND(H7=1,I7="1")),"","pages not read; ")&IF(K7="N","extracted without mapping table; ","")&IF(AB7>1,"document extracted twice; ",""),LEN(IF(O7="MISMATCH","lines do not sum to stated total (LABOUR_ALL); ","")&IF(R7="MISMATCH","lines do not sum to stated total (INSTALL); ","")&IF(U7="MISMATCH","lines do not sum to stated total (PRODUCT); ","")&IF(X7="MISMATCH","lines do not sum to stated total (ALLOWANCE); ","")&IF(AA7="MISMATCH","lines do not sum to grand total; ","")&IF(OR(I7="1-"&H7,AND(H7=1,I7="1")),"","pages not read; ")&IF(K7="N","extracted without mapping table; ","")&IF(AB7>1,"document extracted twice; ",""))-2),"")) | AD7: =IF(AC7<>"",MAX($AD$1:AD6)+1,"")
A8: 7 | B8: =IFERROR(MATCH(A8,Lines!$AF$2:$AF$500,0),"") | C8: =IF(B8="","",INDEX(Lines!$E$2:$E$500,B8)&"") | D8: =IF(B8="","",INDEX(Lines!$B$2:$B$500,B8)&"") | E8: =IF(B8="","",INDEX(Lines!$C$2:$C$500,B8)&"") | F8: =IF(B8="","",INDEX(Lines!$D$2:$D$500,B8)&"") | G8: =IF(B8="","",INDEX(Lines!$F$2:$F$500,B8)&"") | H8: =IF(B8="","",INDEX(Lines!$R$2:$R$500,B8)) | I8: =IF(B8="","",INDEX(Lines!$S$2:$S$500,B8)&"") | J8: =IF(B8="","",INDEX(Lines!$T$2:$T$500,B8)&"") | K8: =IF(B8="","",INDEX(Lines!$U$2:$U$500,B8)&"") | L8: =IF(B8="","",INDEX(Lines!$V$2:$V$500,B8)&"") | M8: =IF(C8="","",SUMIFS(Lines!$N$2:$N$500,Lines!$E$2:$E$500,C8,Lines!$A$2:$A$500,"total",Lines!$X$2:$X$500,"LABOUR_ALL")) | N8: =IF(C8="","",SUMIFS(Lines!$N$2:$N$500,Lines!$E$2:$E$500,C8,Lines!$A$2:$A$500,"line",Lines!$X$2:$X$500,"LABOUR_ALL")) | O8: =IF(C8="","",IF(M8=0,"no stated total",IF(ABS(M8-N8)>Settings!$B$2,"MISMATCH","ok"))) | P8: =IF(C8="","",SUMIFS(Lines!$N$2:$N$500,Lines!$E$2:$E$500,C8,Lines!$A$2:$A$500,"total",Lines!$O$2:$O$500,"INSTALL")) | Q8: =IF(C8="","",SUMIFS(Lines!$N$2:$N$500,Lines!$E$2:$E$500,C8,Lines!$A$2:$A$500,"line",Lines!$O$2:$O$500,"INSTALL")) | R8: =IF(C8="","",IF(P8=0,"no stated total",IF(ABS(P8-Q8)>Settings!$B$2,"MISMATCH","ok"))) | S8: =IF(C8="","",SUMIFS(Lines!$N$2:$N$500,Lines!$E$2:$E$500,C8,Lines!$A$2:$A$500,"total",Lines!$O$2:$O$500,"PRODUCT")) | T8: =IF(C8="","",SUMIFS(Lines!$N$2:$N$500,Lines!$E$2:$E$500,C8,Lines!$A$2:$A$500,"line",Lines!$O$2:$O$500,"PRODUCT")) | U8: =IF(C8="","",IF(S8=0,"no stated total",IF(ABS(S8-T8)>Settings!$B$2,"MISMATCH","ok"))) | V8: =IF(C8="","",SUMIFS(Lines!$N$2:$N$500,Lines!$E$2:$E$500,C8,Lines!$A$2:$A$500,"total",Lines!$O$2:$O$500,"ALLOWANCE")) | W8: =IF(C8="","",SUMIFS(Lines!$N$2:$N$500,Lines!$E$2:$E$500,C8,Lines!$A$2:$A$500,"line",Lines!$O$2:$O$500,"ALLOWANCE")) | X8: =IF(C8="","",IF(V8=0,"no stated total",IF(ABS(V8-W8)>Settings!$B$2,"MISMATCH","ok"))) | Y8: =IF(C8="","",SUMIFS(Lines!$N$2:$N$500,Lines!$E$2:$E$500,C8,Lines!$A$2:$A$500,"total",Lines!$O$2:$O$500,"GRAND")) | Z8: =IF(C8="","",SUMIFS(Lines!$N$2:$N$500,Lines!$E$2:$E$500,C8,Lines!$A$2:$A$500,"line")) | AA8: =IF(C8="","",IF(Y8=0,"no stated total",IF(ABS(Y8-Z8)>Settings!$B$2,"MISMATCH","ok"))) | AB8: =IF(C8="","",COUNTIFS(Lines!$E$2:$E$500,C8,Lines!$A$2:$A$500,"coverage")) | AC8: =IF(C8="","",IF(LEN(IF(O8="MISMATCH","lines do not sum to stated total (LABOUR_ALL); ","")&IF(R8="MISMATCH","lines do not sum to stated total (INSTALL); ","")&IF(U8="MISMATCH","lines do not sum to stated total (PRODUCT); ","")&IF(X8="MISMATCH","lines do not sum to stated total (ALLOWANCE); ","")&IF(AA8="MISMATCH","lines do not sum to grand total; ","")&IF(OR(I8="1-"&H8,AND(H8=1,I8="1")),"","pages not read; ")&IF(K8="N","extracted without mapping table; ","")&IF(AB8>1,"document extracted twice; ",""))>2,LEFT(IF(O8="MISMATCH","lines do not sum to stated total (LABOUR_ALL); ","")&IF(R8="MISMATCH","lines do not sum to stated total (INSTALL); ","")&IF(U8="MISMATCH","lines do not sum to stated total (PRODUCT); ","")&IF(X8="MISMATCH","lines do not sum to stated total (ALLOWANCE); ","")&IF(AA8="MISMATCH","lines do not sum to grand total; ","")&IF(OR(I8="1-"&H8,AND(H8=1,I8="1")),"","pages not read; ")&IF(K8="N","extracted without mapping table; ","")&IF(AB8>1,"document extracted twice; ",""),LEN(IF(O8="MISMATCH","lines do not sum to stated total (LABOUR_ALL); ","")&IF(R8="MISMATCH","lines do not sum to stated total (INSTALL); ","")&IF(U8="MISMATCH","lines do not sum to stated total (PRODUCT); ","")&IF(X8="MISMATCH","lines do not sum to stated total (ALLOWANCE); ","")&IF(AA8="MISMATCH","lines do not sum to grand total; ","")&IF(OR(I8="1-"&H8,AND(H8=1,I8="1")),"","pages not read; ")&IF(K8="N","extracted without mapping table; ","")&IF(AB8>1,"document extracted twice; ",""))-2),"")) | AD8: =IF(AC8<>"",MAX($AD$1:AD7)+1,"")
A9: 8 | B9: =IFERROR(MATCH(A9,Lines!$AF$2:$AF$500,0),"") | C9: =IF(B9="","",INDEX(Lines!$E$2:$E$500,B9)&"") | D9: =IF(B9="","",INDEX(Lines!$B$2:$B$500,B9)&"") | E9: =IF(B9="","",INDEX(Lines!$C$2:$C$500,B9)&"") | F9: =IF(B9="","",INDEX(Lines!$D$2:$D$500,B9)&"") | G9: =IF(B9="","",INDEX(Lines!$F$2:$F$500,B9)&"") | H9: =IF(B9="","",INDEX(Lines!$R$2:$R$500,B9)) | I9: =IF(B9="","",INDEX(Lines!$S$2:$S$500,B9)&"") | J9: =IF(B9="","",INDEX(Lines!$T$2:$T$500,B9)&"") | K9: =IF(B9="","",INDEX(Lines!$U$2:$U$500,B9)&"") | L9: =IF(B9="","",INDEX(Lines!$V$2:$V$500,B9)&"") | M9: =IF(C9="","",SUMIFS(Lines!$N$2:$N$500,Lines!$E$2:$E$500,C9,Lines!$A$2:$A$500,"total",Lines!$X$2:$X$500,"LABOUR_ALL")) | N9: =IF(C9="","",SUMIFS(Lines!$N$2:$N$500,Lines!$E$2:$E$500,C9,Lines!$A$2:$A$500,"line",Lines!$X$2:$X$500,"LABOUR_ALL")) | O9: =IF(C9="","",IF(M9=0,"no stated total",IF(ABS(M9-N9)>Settings!$B$2,"MISMATCH","ok"))) | P9: =IF(C9="","",SUMIFS(Lines!$N$2:$N$500,Lines!$E$2:$E$500,C9,Lines!$A$2:$A$500,"total",Lines!$O$2:$O$500,"INSTALL")) | Q9: =IF(C9="","",SUMIFS(Lines!$N$2:$N$500,Lines!$E$2:$E$500,C9,Lines!$A$2:$A$500,"line",Lines!$O$2:$O$500,"INSTALL")) | R9: =IF(C9="","",IF(P9=0,"no stated total",IF(ABS(P9-Q9)>Settings!$B$2,"MISMATCH","ok"))) | S9: =IF(C9="","",SUMIFS(Lines!$N$2:$N$500,Lines!$E$2:$E$500,C9,Lines!$A$2:$A$500,"total",Lines!$O$2:$O$500,"PRODUCT")) | T9: =IF(C9="","",SUMIFS(Lines!$N$2:$N$500,Lines!$E$2:$E$500,C9,Lines!$A$2:$A$500,"line",Lines!$O$2:$O$500,"PRODUCT")) | U9: =IF(C9="","",IF(S9=0,"no stated total",IF(ABS(S9-T9)>Settings!$B$2,"MISMATCH","ok"))) | V9: =IF(C9="","",SUMIFS(Lines!$N$2:$N$500,Lines!$E$2:$E$500,C9,Lines!$A$2:$A$500,"total",Lines!$O$2:$O$500,"ALLOWANCE")) | W9: =IF(C9="","",SUMIFS(Lines!$N$2:$N$500,Lines!$E$2:$E$500,C9,Lines!$A$2:$A$500,"line",Lines!$O$2:$O$500,"ALLOWANCE")) | X9: =IF(C9="","",IF(V9=0,"no stated total",IF(ABS(V9-W9)>Settings!$B$2,"MISMATCH","ok"))) | Y9: =IF(C9="","",SUMIFS(Lines!$N$2:$N$500,Lines!$E$2:$E$500,C9,Lines!$A$2:$A$500,"total",Lines!$O$2:$O$500,"GRAND")) | Z9: =IF(C9="","",SUMIFS(Lines!$N$2:$N$500,Lines!$E$2:$E$500,C9,Lines!$A$2:$A$500,"line")) | AA9: =IF(C9="","",IF(Y9=0,"no stated total",IF(ABS(Y9-Z9)>Settings!$B$2,"MISMATCH","ok"))) | AB9: =IF(C9="","",COUNTIFS(Lines!$E$2:$E$500,C9,Lines!$A$2:$A$500,"coverage")) | AC9: =IF(C9="","",IF(LEN(IF(O9="MISMATCH","lines do not sum to stated total (LABOUR_ALL); ","")&IF(R9="MISMATCH","lines do not sum to stated total (INSTALL); ","")&IF(U9="MISMATCH","lines do not sum to stated total (PRODUCT); ","")&IF(X9="MISMATCH","lines do not sum to stated total (ALLOWANCE); ","")&IF(AA9="MISMATCH","lines do not sum to grand total; ","")&IF(OR(I9="1-"&H9,AND(H9=1,I9="1")),"","pages not read; ")&IF(K9="N","extracted without mapping table; ","")&IF(AB9>1,"document extracted twice; ",""))>2,LEFT(IF(O9="MISMATCH","lines do not sum to stated total (LABOUR_ALL); ","")&IF(R9="MISMATCH","lines do not sum to stated total (INSTALL); ","")&IF(U9="MISMATCH","lines do not sum to stated total (PRODUCT); ","")&IF(X9="MISMATCH","lines do not sum to stated total (ALLOWANCE); ","")&IF(AA9="MISMATCH","lines do not sum to grand total; ","")&IF(OR(I9="1-"&H9,AND(H9=1,I9="1")),"","pages not read; ")&IF(K9="N","extracted without mapping table; ","")&IF(AB9>1,"document extracted twice; ",""),LEN(IF(O9="MISMATCH","lines do not sum to stated total (LABOUR_ALL); ","")&IF(R9="MISMATCH","lines do not sum to stated total (INSTALL); ","")&IF(U9="MISMATCH","lines do not sum to stated total (PRODUCT); ","")&IF(X9="MISMATCH","lines do not sum to stated total (ALLOWANCE); ","")&IF(AA9="MISMATCH","lines do not sum to grand total; ","")&IF(OR(I9="1-"&H9,AND(H9=1,I9="1")),"","pages not read; ")&IF(K9="N","extracted without mapping table; ","")&IF(AB9>1,"document extracted twice; ",""))-2),"")) | AD9: =IF(AC9<>"",MAX($AD$1:AD8)+1,"")
A10: 9 | B10: =IFERROR(MATCH(A10,Lines!$AF$2:$AF$500,0),"") | C10: =IF(B10="","",INDEX(Lines!$E$2:$E$500,B10)&"") | D10: =IF(B10="","",INDEX(Lines!$B$2:$B$500,B10)&"") | E10: =IF(B10="","",INDEX(Lines!$C$2:$C$500,B10)&"") | F10: =IF(B10="","",INDEX(Lines!$D$2:$D$500,B10)&"") | G10: =IF(B10="","",INDEX(Lines!$F$2:$F$500,B10)&"") | H10: =IF(B10="","",INDEX(Lines!$R$2:$R$500,B10)) | I10: =IF(B10="","",INDEX(Lines!$S$2:$S$500,B10)&"") | J10: =IF(B10="","",INDEX(Lines!$T$2:$T$500,B10)&"") | K10: =IF(B10="","",INDEX(Lines!$U$2:$U$500,B10)&"") | L10: =IF(B10="","",INDEX(Lines!$V$2:$V$500,B10)&"") | M10: =IF(C10="","",SUMIFS(Lines!$N$2:$N$500,Lines!$E$2:$E$500,C10,Lines!$A$2:$A$500,"total",Lines!$X$2:$X$500,"LABOUR_ALL")) | N10: =IF(C10="","",SUMIFS(Lines!$N$2:$N$500,Lines!$E$2:$E$500,C10,Lines!$A$2:$A$500,"line",Lines!$X$2:$X$500,"LABOUR_ALL")) | O10: =IF(C10="","",IF(M10=0,"no stated total",IF(ABS(M10-N10)>Settings!$B$2,"MISMATCH","ok"))) | P10: =IF(C10="","",SUMIFS(Lines!$N$2:$N$500,Lines!$E$2:$E$500,C10,Lines!$A$2:$A$500,"total",Lines!$O$2:$O$500,"INSTALL")) | Q10: =IF(C10="","",SUMIFS(Lines!$N$2:$N$500,Lines!$E$2:$E$500,C10,Lines!$A$2:$A$500,"line",Lines!$O$2:$O$500,"INSTALL")) | R10: =IF(C10="","",IF(P10=0,"no stated total",IF(ABS(P10-Q10)>Settings!$B$2,"MISMATCH","ok"))) | S10: =IF(C10="","",SUMIFS(Lines!$N$2:$N$500,Lines!$E$2:$E$500,C10,Lines!$A$2:$A$500,"total",Lines!$O$2:$O$500,"PRODUCT")) | T10: =IF(C10="","",SUMIFS(Lines!$N$2:$N$500,Lines!$E$2:$E$500,C10,Lines!$A$2:$A$500,"line",Lines!$O$2:$O$500,"PRODUCT")) | U10: =IF(C10="","",IF(S10=0,"no stated total",IF(ABS(S10-T10)>Settings!$B$2,"MISMATCH","ok"))) | V10: =IF(C10="","",SUMIFS(Lines!$N$2:$N$500,Lines!$E$2:$E$500,C10,Lines!$A$2:$A$500,"total",Lines!$O$2:$O$500,"ALLOWANCE")) | W10: =IF(C10="","",SUMIFS(Lines!$N$2:$N$500,Lines!$E$2:$E$500,C10,Lines!$A$2:$A$500,"line",Lines!$O$2:$O$500,"ALLOWANCE")) | X10: =IF(C10="","",IF(V10=0,"no stated total",IF(ABS(V10-W10)>Settings!$B$2,"MISMATCH","ok"))) | Y10: =IF(C10="","",SUMIFS(Lines!$N$2:$N$500,Lines!$E$2:$E$500,C10,Lines!$A$2:$A$500,"total",Lines!$O$2:$O$500,"GRAND")) | Z10: =IF(C10="","",SUMIFS(Lines!$N$2:$N$500,Lines!$E$2:$E$500,C10,Lines!$A$2:$A$500,"line")) | AA10: =IF(C10="","",IF(Y10=0,"no stated total",IF(ABS(Y10-Z10)>Settings!$B$2,"MISMATCH","ok"))) | AB10: =IF(C10="","",COUNTIFS(Lines!$E$2:$E$500,C10,Lines!$A$2:$A$500,"coverage")) | AC10: =IF(C10="","",IF(LEN(IF(O10="MISMATCH","lines do not sum to stated total (LABOUR_ALL); ","")&IF(R10="MISMATCH","lines do not sum to stated total (INSTALL); ","")&IF(U10="MISMATCH","lines do not sum to stated total (PRODUCT); ","")&IF(X10="MISMATCH","lines do not sum to stated total (ALLOWANCE); ","")&IF(AA10="MISMATCH","lines do not sum to grand total; ","")&IF(OR(I10="1-"&H10,AND(H10=1,I10="1")),"","pages not read; ")&IF(K10="N","extracted without mapping table; ","")&IF(AB10>1,"document extracted twice; ",""))>2,LEFT(IF(O10="MISMATCH","lines do not sum to stated total (LABOUR_ALL); ","")&IF(R10="MISMATCH","lines do not sum to stated total (INSTALL); ","")&IF(U10="MISMATCH","lines do not sum to stated total (PRODUCT); ","")&IF(X10="MISMATCH","lines do not sum to stated total (ALLOWANCE); ","")&IF(AA10="MISMATCH","lines do not sum to grand total; ","")&IF(OR(I10="1-"&H10,AND(H10=1,I10="1")),"","pages not read; ")&IF(K10="N","extracted without mapping table; ","")&IF(AB10>1,"document extracted twice; ",""),LEN(IF(O10="MISMATCH","lines do not sum to stated total (LABOUR_ALL); ","")&IF(R10="MISMATCH","lines do not sum to stated total (INSTALL); ","")&IF(U10="MISMATCH","lines do not sum to stated total (PRODUCT); ","")&IF(X10="MISMATCH","lines do not sum to stated total (ALLOWANCE); ","")&IF(AA10="MISMATCH","lines do not sum to grand total; ","")&IF(OR(I10="1-"&H10,AND(H10=1,I10="1")),"","pages not read; ")&IF(K10="N","extracted without mapping table; ","")&IF(AB10>1,"document extracted twice; ",""))-2),"")) | AD10: =IF(AC10<>"",MAX($AD$1:AD9)+1,"")
A11: 10 | B11: =IFERROR(MATCH(A11,Lines!$AF$2:$AF$500,0),"") | C11: =IF(B11="","",INDEX(Lines!$E$2:$E$500,B11)&"") | D11: =IF(B11="","",INDEX(Lines!$B$2:$B$500,B11)&"") | E11: =IF(B11="","",INDEX(Lines!$C$2:$C$500,B11)&"") | F11: =IF(B11="","",INDEX(Lines!$D$2:$D$500,B11)&"") | G11: =IF(B11="","",INDEX(Lines!$F$2:$F$500,B11)&"") | H11: =IF(B11="","",INDEX(Lines!$R$2:$R$500,B11)) | I11: =IF(B11="","",INDEX(Lines!$S$2:$S$500,B11)&"") | J11: =IF(B11="","",INDEX(Lines!$T$2:$T$500,B11)&"") | K11: =IF(B11="","",INDEX(Lines!$U$2:$U$500,B11)&"") | L11: =IF(B11="","",INDEX(Lines!$V$2:$V$500,B11)&"") | M11: =IF(C11="","",SUMIFS(Lines!$N$2:$N$500,Lines!$E$2:$E$500,C11,Lines!$A$2:$A$500,"total",Lines!$X$2:$X$500,"LABOUR_ALL")) | N11: =IF(C11="","",SUMIFS(Lines!$N$2:$N$500,Lines!$E$2:$E$500,C11,Lines!$A$2:$A$500,"line",Lines!$X$2:$X$500,"LABOUR_ALL")) | O11: =IF(C11="","",IF(M11=0,"no stated total",IF(ABS(M11-N11)>Settings!$B$2,"MISMATCH","ok"))) | P11: =IF(C11="","",SUMIFS(Lines!$N$2:$N$500,Lines!$E$2:$E$500,C11,Lines!$A$2:$A$500,"total",Lines!$O$2:$O$500,"INSTALL")) | Q11: =IF(C11="","",SUMIFS(Lines!$N$2:$N$500,Lines!$E$2:$E$500,C11,Lines!$A$2:$A$500,"line",Lines!$O$2:$O$500,"INSTALL")) | R11: =IF(C11="","",IF(P11=0,"no stated total",IF(ABS(P11-Q11)>Settings!$B$2,"MISMATCH","ok"))) | S11: =IF(C11="","",SUMIFS(Lines!$N$2:$N$500,Lines!$E$2:$E$500,C11,Lines!$A$2:$A$500,"total",Lines!$O$2:$O$500,"PRODUCT")) | T11: =IF(C11="","",SUMIFS(Lines!$N$2:$N$500,Lines!$E$2:$E$500,C11,Lines!$A$2:$A$500,"line",Lines!$O$2:$O$500,"PRODUCT")) | U11: =IF(C11="","",IF(S11=0,"no stated total",IF(ABS(S11-T11)>Settings!$B$2,"MISMATCH","ok"))) | V11: =IF(C11="","",SUMIFS(Lines!$N$2:$N$500,Lines!$E$2:$E$500,C11,Lines!$A$2:$A$500,"total",Lines!$O$2:$O$500,"ALLOWANCE")) | W11: =IF(C11="","",SUMIFS(Lines!$N$2:$N$500,Lines!$E$2:$E$500,C11,Lines!$A$2:$A$500,"line",Lines!$O$2:$O$500,"ALLOWANCE")) | X11: =IF(C11="","",IF(V11=0,"no stated total",IF(ABS(V11-W11)>Settings!$B$2,"MISMATCH","ok"))) | Y11: =IF(C11="","",SUMIFS(Lines!$N$2:$N$500,Lines!$E$2:$E$500,C11,Lines!$A$2:$A$500,"total",Lines!$O$2:$O$500,"GRAND")) | Z11: =IF(C11="","",SUMIFS(Lines!$N$2:$N$500,Lines!$E$2:$E$500,C11,Lines!$A$2:$A$500,"line")) | AA11: =IF(C11="","",IF(Y11=0,"no stated total",IF(ABS(Y11-Z11)>Settings!$B$2,"MISMATCH","ok"))) | AB11: =IF(C11="","",COUNTIFS(Lines!$E$2:$E$500,C11,Lines!$A$2:$A$500,"coverage")) | AC11: =IF(C11="","",IF(LEN(IF(O11="MISMATCH","lines do not sum to stated total (LABOUR_ALL); ","")&IF(R11="MISMATCH","lines do not sum to stated total (INSTALL); ","")&IF(U11="MISMATCH","lines do not sum to stated total (PRODUCT); ","")&IF(X11="MISMATCH","lines do not sum to stated total (ALLOWANCE); ","")&IF(AA11="MISMATCH","lines do not sum to grand total; ","")&IF(OR(I11="1-"&H11,AND(H11=1,I11="1")),"","pages not read; ")&IF(K11="N","extracted without mapping table; ","")&IF(AB11>1,"document extracted twice; ",""))>2,LEFT(IF(O11="MISMATCH","lines do not sum to stated total (LABOUR_ALL); ","")&IF(R11="MISMATCH","lines do not sum to stated total (INSTALL); ","")&IF(U11="MISMATCH","lines do not sum to stated total (PRODUCT); ","")&IF(X11="MISMATCH","lines do not sum to stated total (ALLOWANCE); ","")&IF(AA11="MISMATCH","lines do not sum to grand total; ","")&IF(OR(I11="1-"&H11,AND(H11=1,I11="1")),"","pages not read; ")&IF(K11="N","extracted without mapping table; ","")&IF(AB11>1,"document extracted twice; ",""),LEN(IF(O11="MISMATCH","lines do not sum to stated total (LABOUR_ALL); ","")&IF(R11="MISMATCH","lines do not sum to stated total (INSTALL); ","")&IF(U11="MISMATCH","lines do not sum to stated total (PRODUCT); ","")&IF(X11="MISMATCH","lines do not sum to stated total (ALLOWANCE); ","")&IF(AA11="MISMATCH","lines do not sum to grand total; ","")&IF(OR(I11="1-"&H11,AND(H11=1,I11="1")),"","pages not read; ")&IF(K11="N","extracted without mapping table; ","")&IF(AB11>1,"document extracted twice; ",""))-2),"")) | AD11: =IF(AC11<>"",MAX($AD$1:AD10)+1,"")
A12: 11 | B12: =IFERROR(MATCH(A12,Lines!$AF$2:$AF$500,0),"") | C12: =IF(B12="","",INDEX(Lines!$E$2:$E$500,B12)&"") | D12: =IF(B12="","",INDEX(Lines!$B$2:$B$500,B12)&"") | E12: =IF(B12="","",INDEX(Lines!$C$2:$C$500,B12)&"") | F12: =IF(B12="","",INDEX(Lines!$D$2:$D$500,B12)&"") | G12: =IF(B12="","",INDEX(Lines!$F$2:$F$500,B12)&"") | H12: =IF(B12="","",INDEX(Lines!$R$2:$R$500,B12)) | I12: =IF(B12="","",INDEX(Lines!$S$2:$S$500,B12)&"") | J12: =IF(B12="","",INDEX(Lines!$T$2:$T$500,B12)&"") | K12: =IF(B12="","",INDEX(Lines!$U$2:$U$500,B12)&"") | L12: =IF(B12="","",INDEX(Lines!$V$2:$V$500,B12)&"") | M12: =IF(C12="","",SUMIFS(Lines!$N$2:$N$500,Lines!$E$2:$E$500,C12,Lines!$A$2:$A$500,"total",Lines!$X$2:$X$500,"LABOUR_ALL")) | N12: =IF(C12="","",SUMIFS(Lines!$N$2:$N$500,Lines!$E$2:$E$500,C12,Lines!$A$2:$A$500,"line",Lines!$X$2:$X$500,"LABOUR_ALL")) | O12: =IF(C12="","",IF(M12=0,"no stated total",IF(ABS(M12-N12)>Settings!$B$2,"MISMATCH","ok"))) | P12: =IF(C12="","",SUMIFS(Lines!$N$2:$N$500,Lines!$E$2:$E$500,C12,Lines!$A$2:$A$500,"total",Lines!$O$2:$O$500,"INSTALL")) | Q12: =IF(C12="","",SUMIFS(Lines!$N$2:$N$500,Lines!$E$2:$E$500,C12,Lines!$A$2:$A$500,"line",Lines!$O$2:$O$500,"INSTALL")) | R12: =IF(C12="","",IF(P12=0,"no stated total",IF(ABS(P12-Q12)>Settings!$B$2,"MISMATCH","ok"))) | S12: =IF(C12="","",SUMIFS(Lines!$N$2:$N$500,Lines!$E$2:$E$500,C12,Lines!$A$2:$A$500,"total",Lines!$O$2:$O$500,"PRODUCT")) | T12: =IF(C12="","",SUMIFS(Lines!$N$2:$N$500,Lines!$E$2:$E$500,C12,Lines!$A$2:$A$500,"line",Lines!$O$2:$O$500,"PRODUCT")) | U12: =IF(C12="","",IF(S12=0,"no stated total",IF(ABS(S12-T12)>Settings!$B$2,"MISMATCH","ok"))) | V12: =IF(C12="","",SUMIFS(Lines!$N$2:$N$500,Lines!$E$2:$E$500,C12,Lines!$A$2:$A$500,"total",Lines!$O$2:$O$500,"ALLOWANCE")) | W12: =IF(C12="","",SUMIFS(Lines!$N$2:$N$500,Lines!$E$2:$E$500,C12,Lines!$A$2:$A$500,"line",Lines!$O$2:$O$500,"ALLOWANCE")) | X12: =IF(C12="","",IF(V12=0,"no stated total",IF(ABS(V12-W12)>Settings!$B$2,"MISMATCH","ok"))) | Y12: =IF(C12="","",SUMIFS(Lines!$N$2:$N$500,Lines!$E$2:$E$500,C12,Lines!$A$2:$A$500,"total",Lines!$O$2:$O$500,"GRAND")) | Z12: =IF(C12="","",SUMIFS(Lines!$N$2:$N$500,Lines!$E$2:$E$500,C12,Lines!$A$2:$A$500,"line")) | AA12: =IF(C12="","",IF(Y12=0,"no stated total",IF(ABS(Y12-Z12)>Settings!$B$2,"MISMATCH","ok"))) | AB12: =IF(C12="","",COUNTIFS(Lines!$E$2:$E$500,C12,Lines!$A$2:$A$500,"coverage")) | AC12: =IF(C12="","",IF(LEN(IF(O12="MISMATCH","lines do not sum to stated total (LABOUR_ALL); ","")&IF(R12="MISMATCH","lines do not sum to stated total (INSTALL); ","")&IF(U12="MISMATCH","lines do not sum to stated total (PRODUCT); ","")&IF(X12="MISMATCH","lines do not sum to stated total (ALLOWANCE); ","")&IF(AA12="MISMATCH","lines do not sum to grand total; ","")&IF(OR(I12="1-"&H12,AND(H12=1,I12="1")),"","pages not read; ")&IF(K12="N","extracted without mapping table; ","")&IF(AB12>1,"document extracted twice; ",""))>2,LEFT(IF(O12="MISMATCH","lines do not sum to stated total (LABOUR_ALL); ","")&IF(R12="MISMATCH","lines do not sum to stated total (INSTALL); ","")&IF(U12="MISMATCH","lines do not sum to stated total (PRODUCT); ","")&IF(X12="MISMATCH","lines do not sum to stated total (ALLOWANCE); ","")&IF(AA12="MISMATCH","lines do not sum to grand total; ","")&IF(OR(I12="1-"&H12,AND(H12=1,I12="1")),"","pages not read; ")&IF(K12="N","extracted without mapping table; ","")&IF(AB12>1,"document extracted twice; ",""),LEN(IF(O12="MISMATCH","lines do not sum to stated total (LABOUR_ALL); ","")&IF(R12="MISMATCH","lines do not sum to stated total (INSTALL); ","")&IF(U12="MISMATCH","lines do not sum to stated total (PRODUCT); ","")&IF(X12="MISMATCH","lines do not sum to stated total (ALLOWANCE); ","")&IF(AA12="MISMATCH","lines do not sum to grand total; ","")&IF(OR(I12="1-"&H12,AND(H12=1,I12="1")),"","pages not read; ")&IF(K12="N","extracted without mapping table; ","")&IF(AB12>1,"document extracted twice; ",""))-2),"")) | AD12: =IF(AC12<>"",MAX($AD$1:AD11)+1,"")
A13: 12 | B13: =IFERROR(MATCH(A13,Lines!$AF$2:$AF$500,0),"") | C13: =IF(B13="","",INDEX(Lines!$E$2:$E$500,B13)&"") | D13: =IF(B13="","",INDEX(Lines!$B$2:$B$500,B13)&"") | E13: =IF(B13="","",INDEX(Lines!$C$2:$C$500,B13)&"") | F13: =IF(B13="","",INDEX(Lines!$D$2:$D$500,B13)&"") | G13: =IF(B13="","",INDEX(Lines!$F$2:$F$500,B13)&"") | H13: =IF(B13="","",INDEX(Lines!$R$2:$R$500,B13)) | I13: =IF(B13="","",INDEX(Lines!$S$2:$S$500,B13)&"") | J13: =IF(B13="","",INDEX(Lines!$T$2:$T$500,B13)&"") | K13: =IF(B13="","",INDEX(Lines!$U$2:$U$500,B13)&"") | L13: =IF(B13="","",INDEX(Lines!$V$2:$V$500,B13)&"") | M13: =IF(C13="","",SUMIFS(Lines!$N$2:$N$500,Lines!$E$2:$E$500,C13,Lines!$A$2:$A$500,"total",Lines!$X$2:$X$500,"LABOUR_ALL")) | N13: =IF(C13="","",SUMIFS(Lines!$N$2:$N$500,Lines!$E$2:$E$500,C13,Lines!$A$2:$A$500,"line",Lines!$X$2:$X$500,"LABOUR_ALL")) | O13: =IF(C13="","",IF(M13=0,"no stated total",IF(ABS(M13-N13)>Settings!$B$2,"MISMATCH","ok"))) | P13: =IF(C13="","",SUMIFS(Lines!$N$2:$N$500,Lines!$E$2:$E$500,C13,Lines!$A$2:$A$500,"total",Lines!$O$2:$O$500,"INSTALL")) | Q13: =IF(C13="","",SUMIFS(Lines!$N$2:$N$500,Lines!$E$2:$E$500,C13,Lines!$A$2:$A$500,"line",Lines!$O$2:$O$500,"INSTALL")) | R13: =IF(C13="","",IF(P13=0,"no stated total",IF(ABS(P13-Q13)>Settings!$B$2,"MISMATCH","ok"))) | S13: =IF(C13="","",SUMIFS(Lines!$N$2:$N$500,Lines!$E$2:$E$500,C13,Lines!$A$2:$A$500,"total",Lines!$O$2:$O$500,"PRODUCT")) | T13: =IF(C13="","",SUMIFS(Lines!$N$2:$N$500,Lines!$E$2:$E$500,C13,Lines!$A$2:$A$500,"line",Lines!$O$2:$O$500,"PRODUCT")) | U13: =IF(C13="","",IF(S13=0,"no stated total",IF(ABS(S13-T13)>Settings!$B$2,"MISMATCH","ok"))) | V13: =IF(C13="","",SUMIFS(Lines!$N$2:$N$500,Lines!$E$2:$E$500,C13,Lines!$A$2:$A$500,"total",Lines!$O$2:$O$500,"ALLOWANCE")) | W13: =IF(C13="","",SUMIFS(Lines!$N$2:$N$500,Lines!$E$2:$E$500,C13,Lines!$A$2:$A$500,"line",Lines!$O$2:$O$500,"ALLOWANCE")) | X13: =IF(C13="","",IF(V13=0,"no stated total",IF(ABS(V13-W13)>Settings!$B$2,"MISMATCH","ok"))) | Y13: =IF(C13="","",SUMIFS(Lines!$N$2:$N$500,Lines!$E$2:$E$500,C13,Lines!$A$2:$A$500,"total",Lines!$O$2:$O$500,"GRAND")) | Z13: =IF(C13="","",SUMIFS(Lines!$N$2:$N$500,Lines!$E$2:$E$500,C13,Lines!$A$2:$A$500,"line")) | AA13: =IF(C13="","",IF(Y13=0,"no stated total",IF(ABS(Y13-Z13)>Settings!$B$2,"MISMATCH","ok"))) | AB13: =IF(C13="","",COUNTIFS(Lines!$E$2:$E$500,C13,Lines!$A$2:$A$500,"coverage")) | AC13: =IF(C13="","",IF(LEN(IF(O13="MISMATCH","lines do not sum to stated total (LABOUR_ALL); ","")&IF(R13="MISMATCH","lines do not sum to stated total (INSTALL); ","")&IF(U13="MISMATCH","lines do not sum to stated total (PRODUCT); ","")&IF(X13="MISMATCH","lines do not sum to stated total (ALLOWANCE); ","")&IF(AA13="MISMATCH","lines do not sum to grand total; ","")&IF(OR(I13="1-"&H13,AND(H13=1,I13="1")),"","pages not read; ")&IF(K13="N","extracted without mapping table; ","")&IF(AB13>1,"document extracted twice; ",""))>2,LEFT(IF(O13="MISMATCH","lines do not sum to stated total (LABOUR_ALL); ","")&IF(R13="MISMATCH","lines do not sum to stated total (INSTALL); ","")&IF(U13="MISMATCH","lines do not sum to stated total (PRODUCT); ","")&IF(X13="MISMATCH","lines do not sum to stated total (ALLOWANCE); ","")&IF(AA13="MISMATCH","lines do not sum to grand total; ","")&IF(OR(I13="1-"&H13,AND(H13=1,I13="1")),"","pages not read; ")&IF(K13="N","extracted without mapping table; ","")&IF(AB13>1,"document extracted twice; ",""),LEN(IF(O13="MISMATCH","lines do not sum to stated total (LABOUR_ALL); ","")&IF(R13="MISMATCH","lines do not sum to stated total (INSTALL); ","")&IF(U13="MISMATCH","lines do not sum to stated total (PRODUCT); ","")&IF(X13="MISMATCH","lines do not sum to stated total (ALLOWANCE); ","")&IF(AA13="MISMATCH","lines do not sum to grand total; ","")&IF(OR(I13="1-"&H13,AND(H13=1,I13="1")),"","pages not read; ")&IF(K13="N","extracted without mapping table; ","")&IF(AB13>1,"document extracted twice; ",""))-2),"")) | AD13: =IF(AC13<>"",MAX($AD$1:AD12)+1,"")
... A51: 50 | B51: =IFERROR(MATCH(A51,Lines!$AF$2:$AF$500,0),"") | C51: =IF(B51="","",INDEX(Lines!$E$2:$E$500,B51)&"") | D51: =IF(B51="","",INDEX(Lines!$B$2:$B$500,B51)&"") | E51: =IF(B51="","",INDEX(Lines!$C$2:$C$500,B51)&"") | F51: =IF(B51="","",INDEX(Lines!$D$2:$D$500,B51)&"") | G51: =IF(B51="","",INDEX(Lines!$F$2:$F$500,B51)&"") | H51: =IF(B51="","",INDEX(Lines!$R$2:$R$500,B51)) | I51: =IF(B51="","",INDEX(Lines!$S$2:$S$500,B51)&"") | J51: =IF(B51="","",INDEX(Lines!$T$2:$T$500,B51)&"") | K51: =IF(B51="","",INDEX(Lines!$U$2:$U$500,B51)&"") | L51: =IF(B51="","",INDEX(Lines!$V$2:$V$500,B51)&"") | M51: =IF(C51="","",SUMIFS(Lines!$N$2:$N$500,Lines!$E$2:$E$500,C51,Lines!$A$2:$A$500,"total",Lines!$X$2:$X$500,"LABOUR_ALL")) | N51: =IF(C51="","",SUMIFS(Lines!$N$2:$N$500,Lines!$E$2:$E$500,C51,Lines!$A$2:$A$500,"line",Lines!$X$2:$X$500,"LABOUR_ALL")) | O51: =IF(C51="","",IF(M51=0,"no stated total",IF(ABS(M51-N51)>Settings!$B$2,"MISMATCH","ok"))) | P51: =IF(C51="","",SUMIFS(Lines!$N$2:$N$500,Lines!$E$2:$E$500,C51,Lines!$A$2:$A$500,"total",Lines!$O$2:$O$500,"INSTALL")) | Q51: =IF(C51="","",SUMIFS(Lines!$N$2:$N$500,Lines!$E$2:$E$500,C51,Lines!$A$2:$A$500,"line",Lines!$O$2:$O$500,"INSTALL")) | R51: =IF(C51="","",IF(P51=0,"no stated total",IF(ABS(P51-Q51)>Settings!$B$2,"MISMATCH","ok"))) | S51: =IF(C51="","",SUMIFS(Lines!$N$2:$N$500,Lines!$E$2:$E$500,C51,Lines!$A$2:$A$500,"total",Lines!$O$2:$O$500,"PRODUCT")) | T51: =IF(C51="","",SUMIFS(Lines!$N$2:$N$500,Lines!$E$2:$E$500,C51,Lines!$A$2:$A$500,"line",Lines!$O$2:$O$500,"PRODUCT")) | U51: =IF(C51="","",IF(S51=0,"no stated total",IF(ABS(S51-T51)>Settings!$B$2,"MISMATCH","ok"))) | V51: =IF(C51="","",SUMIFS(Lines!$N$2:$N$500,Lines!$E$2:$E$500,C51,Lines!$A$2:$A$500,"total",Lines!$O$2:$O$500,"ALLOWANCE")) | W51: =IF(C51="","",SUMIFS(Lines!$N$2:$N$500,Lines!$E$2:$E$500,C51,Lines!$A$2:$A$500,"line",Lines!$O$2:$O$500,"ALLOWANCE")) | X51: =IF(C51="","",IF(V51=0,"no stated total",IF(ABS(V51-W51)>Settings!$B$2,"MISMATCH","ok"))) | Y51: =IF(C51="","",SUMIFS(Lines!$N$2:$N$500,Lines!$E$2:$E$500,C51,Lines!$A$2:$A$500,"total",Lines!$O$2:$O$500,"GRAND")) | Z51: =IF(C51="","",SUMIFS(Lines!$N$2:$N$500,Lines!$E$2:$E$500,C51,Lines!$A$2:$A$500,"line")) | AA51: =IF(C51="","",IF(Y51=0,"no stated total",IF(ABS(Y51-Z51)>Settings!$B$2,"MISMATCH","ok"))) | AB51: =IF(C51="","",COUNTIFS(Lines!$E$2:$E$500,C51,Lines!$A$2:$A$500,"coverage")) | AC51: =IF(C51="","",IF(LEN(IF(O51="MISMATCH","lines do not sum to stated total (LABOUR_ALL); ","")&IF(R51="MISMATCH","lines do not sum to stated total (INSTALL); ","")&IF(U51="MISMATCH","lines do not sum to stated total (PRODUCT); ","")&IF(X51="MISMATCH","lines do not sum to stated total (ALLOWANCE); ","")&IF(AA51="MISMATCH","lines do not sum to grand total; ","")&IF(OR(I51="1-"&H51,AND(H51=1,I51="1")),"","pages not read; ")&IF(K51="N","extracted without mapping table; ","")&IF(AB51>1,"document extracted twice; ",""))>2,LEFT(IF(O51="MISMATCH","lines do not sum to stated total (LABOUR_ALL); ","")&IF(R51="MISMATCH","lines do not sum to stated total (INSTALL); ","")&IF(U51="MISMATCH","lines do not sum to stated total (PRODUCT); ","")&IF(X51="MISMATCH","lines do not sum to stated total (ALLOWANCE); ","")&IF(AA51="MISMATCH","lines do not sum to grand total; ","")&IF(OR(I51="1-"&H51,AND(H51=1,I51="1")),"","pages not read; ")&IF(K51="N","extracted without mapping table; ","")&IF(AB51>1,"document extracted twice; ",""),LEN(IF(O51="MISMATCH","lines do not sum to stated total (LABOUR_ALL); ","")&IF(R51="MISMATCH","lines do not sum to stated total (INSTALL); ","")&IF(U51="MISMATCH","lines do not sum to stated total (PRODUCT); ","")&IF(X51="MISMATCH","lines do not sum to stated total (ALLOWANCE); ","")&IF(AA51="MISMATCH","lines do not sum to grand total; ","")&IF(OR(I51="1-"&H51,AND(H51=1,I51="1")),"","pages not read; ")&IF(K51="N","extracted without mapping table; ","")&IF(AB51>1,"document extracted twice; ",""))-2),"")) | AD51: =IF(AC51<>"",MAX($AD$1:AD50)+1,"")

Sheet Tracker
A1: seq | B1: row | C1: project | D1: vendor | E1: quoted_LABOUR_ALL | F1: invoiced_LABOUR_ALL | G1: variance_LABOUR_ALL | H1: variance_pct_LABOUR_ALL | I1: quoted_INSTALL | J1: invoiced_INSTALL | K1: variance_INSTALL | L1: variance_pct_INSTALL | M1: quoted_PRODUCT | N1: invoiced_PRODUCT | O1: variance_PRODUCT | P1: variance_pct_PRODUCT | Q1: quoted_ALLOWANCE | R1: invoiced_ALLOWANCE | S1: variance_ALLOWANCE | T1: variance_pct_ALLOWANCE | U1: invoice_count | V1: discrepancy | W1: notes
A2: 1 | B2: =IFERROR(MATCH(A2,Lines!$AG$2:$AG$500,0),"") | C2: =IF(B2="","",INDEX(Lines!$B$2:$B$500,B2)) | D2: =IF(B2="","",INDEX(Lines!$C$2:$C$500,B2)) | E2: =IF(C2="","",SUMIFS(Lines!$N$2:$N$500,Lines!$B$2:$B$500,C2,Lines!$C$2:$C$500,D2,Lines!$A$2:$A$500,"line",Lines!$X$2:$X$500,"LABOUR_ALL",Lines!$D$2:$D$500,"quote")) | F2: =IF(C2="","",SUMIFS(Lines!$N$2:$N$500,Lines!$B$2:$B$500,C2,Lines!$C$2:$C$500,D2,Lines!$A$2:$A$500,"line",Lines!$X$2:$X$500,"LABOUR_ALL",Lines!$D$2:$D$500,"invoice")) | G2: =IF(C2="","",F2-E2) | H2: =IF(C2="","",IFERROR(G2/E2,"")) | I2: =IF(C2="","",SUMIFS(Lines!$N$2:$N$500,Lines!$B$2:$B$500,C2,Lines!$C$2:$C$500,D2,Lines!$A$2:$A$500,"line",Lines!$O$2:$O$500,"INSTALL",Lines!$D$2:$D$500,"quote")) | J2: =IF(C2="","",SUMIFS(Lines!$N$2:$N$500,Lines!$B$2:$B$500,C2,Lines!$C$2:$C$500,D2,Lines!$A$2:$A$500,"line",Lines!$O$2:$O$500,"INSTALL",Lines!$D$2:$D$500,"invoice")) | K2: =IF(C2="","",J2-I2) | L2: =IF(C2="","",IFERROR(K2/I2,"")) | M2: =IF(C2="","",SUMIFS(Lines!$N$2:$N$500,Lines!$B$2:$B$500,C2,Lines!$C$2:$C$500,D2,Lines!$A$2:$A$500,"line",Lines!$O$2:$O$500,"PRODUCT",Lines!$D$2:$D$500,"quote")) | N2: =IF(C2="","",SUMIFS(Lines!$N$2:$N$500,Lines!$B$2:$B$500,C2,Lines!$C$2:$C$500,D2,Lines!$A$2:$A$500,"line",Lines!$O$2:$O$500,"PRODUCT",Lines!$D$2:$D$500,"invoice")) | O2: =IF(C2="","",N2-M2) | P2: =IF(C2="","",IFERROR(O2/M2,"")) | Q2: =IF(C2="","",SUMIFS(Lines!$N$2:$N$500,Lines!$B$2:$B$500,C2,Lines!$C$2:$C$500,D2,Lines!$A$2:$A$500,"line",Lines!$O$2:$O$500,"ALLOWANCE",Lines!$D$2:$D$500,"quote")) | R2: =IF(C2="","",SUMIFS(Lines!$N$2:$N$500,Lines!$B$2:$B$500,C2,Lines!$C$2:$C$500,D2,Lines!$A$2:$A$500,"line",Lines!$O$2:$O$500,"ALLOWANCE",Lines!$D$2:$D$500,"invoice")) | S2: =IF(C2="","",R2-Q2) | T2: =IF(C2="","",IFERROR(S2/Q2,"")) | U2: =IF(C2="","",COUNTIFS(Docs!$D$2:$D$51,C2,Docs!$E$2:$E$51,D2,Docs!$F$2:$F$51,"invoice")) | V2: =IF(C2="","",IF(U2=0,"N/A - pending",IF(MAX(ABS(G2),ABS(K2),ABS(O2),ABS(S2))>Settings!$B$2,"Y","N"))) | W2: =IF(C2="","",TRIM(IFERROR("LABOUR_ALL: "&INDEX(Notes!$D$3:$D$52,MATCH(C2&"|"&D2&"|LABOUR_ALL",Notes!$E$3:$E$52,0))&" ","")&IFERROR("INSTALL: "&INDEX(Notes!$D$3:$D$52,MATCH(C2&"|"&D2&"|INSTALL",Notes!$E$3:$E$52,0))&" ","")&IFERROR("PRODUCT: "&INDEX(Notes!$D$3:$D$52,MATCH(C2&"|"&D2&"|PRODUCT",Notes!$E$3:$E$52,0))&" ","")&IFERROR("ALLOWANCE: "&INDEX(Notes!$D$3:$D$52,MATCH(C2&"|"&D2&"|ALLOWANCE",Notes!$E$3:$E$52,0))&" ","")))
A3: 2 | B3: =IFERROR(MATCH(A3,Lines!$AG$2:$AG$500,0),"") | C3: =IF(B3="","",INDEX(Lines!$B$2:$B$500,B3)) | D3: =IF(B3="","",INDEX(Lines!$C$2:$C$500,B3)) | E3: =IF(C3="","",SUMIFS(Lines!$N$2:$N$500,Lines!$B$2:$B$500,C3,Lines!$C$2:$C$500,D3,Lines!$A$2:$A$500,"line",Lines!$X$2:$X$500,"LABOUR_ALL",Lines!$D$2:$D$500,"quote")) | F3: =IF(C3="","",SUMIFS(Lines!$N$2:$N$500,Lines!$B$2:$B$500,C3,Lines!$C$2:$C$500,D3,Lines!$A$2:$A$500,"line",Lines!$X$2:$X$500,"LABOUR_ALL",Lines!$D$2:$D$500,"invoice")) | G3: =IF(C3="","",F3-E3) | H3: =IF(C3="","",IFERROR(G3/E3,"")) | I3: =IF(C3="","",SUMIFS(Lines!$N$2:$N$500,Lines!$B$2:$B$500,C3,Lines!$C$2:$C$500,D3,Lines!$A$2:$A$500,"line",Lines!$O$2:$O$500,"INSTALL",Lines!$D$2:$D$500,"quote")) | J3: =IF(C3="","",SUMIFS(Lines!$N$2:$N$500,Lines!$B$2:$B$500,C3,Lines!$C$2:$C$500,D3,Lines!$A$2:$A$500,"line",Lines!$O$2:$O$500,"INSTALL",Lines!$D$2:$D$500,"invoice")) | K3: =IF(C3="","",J3-I3) | L3: =IF(C3="","",IFERROR(K3/I3,"")) | M3: =IF(C3="","",SUMIFS(Lines!$N$2:$N$500,Lines!$B$2:$B$500,C3,Lines!$C$2:$C$500,D3,Lines!$A$2:$A$500,"line",Lines!$O$2:$O$500,"PRODUCT",Lines!$D$2:$D$500,"quote")) | N3: =IF(C3="","",SUMIFS(Lines!$N$2:$N$500,Lines!$B$2:$B$500,C3,Lines!$C$2:$C$500,D3,Lines!$A$2:$A$500,"line",Lines!$O$2:$O$500,"PRODUCT",Lines!$D$2:$D$500,"invoice")) | O3: =IF(C3="","",N3-M3) | P3: =IF(C3="","",IFERROR(O3/M3,"")) | Q3: =IF(C3="","",SUMIFS(Lines!$N$2:$N$500,Lines!$B$2:$B$500,C3,Lines!$C$2:$C$500,D3,Lines!$A$2:$A$500,"line",Lines!$O$2:$O$500,"ALLOWANCE",Lines!$D$2:$D$500,"quote")) | R3: =IF(C3="","",SUMIFS(Lines!$N$2:$N$500,Lines!$B$2:$B$500,C3,Lines!$C$2:$C$500,D3,Lines!$A$2:$A$500,"line",Lines!$O$2:$O$500,"ALLOWANCE",Lines!$D$2:$D$500,"invoice")) | S3: =IF(C3="","",R3-Q3) | T3: =IF(C3="","",IFERROR(S3/Q3,"")) | U3: =IF(C3="","",COUNTIFS(Docs!$D$2:$D$51,C3,Docs!$E$2:$E$51,D3,Docs!$F$2:$F$51,"invoice")) | V3: =IF(C3="","",IF(U3=0,"N/A - pending",IF(MAX(ABS(G3),ABS(K3),ABS(O3),ABS(S3))>Settings!$B$2,"Y","N"))) | W3: =IF(C3="","",TRIM(IFERROR("LABOUR_ALL: "&INDEX(Notes!$D$3:$D$52,MATCH(C3&"|"&D3&"|LABOUR_ALL",Notes!$E$3:$E$52,0))&" ","")&IFERROR("INSTALL: "&INDEX(Notes!$D$3:$D$52,MATCH(C3&"|"&D3&"|INSTALL",Notes!$E$3:$E$52,0))&" ","")&IFERROR("PRODUCT: "&INDEX(Notes!$D$3:$D$52,MATCH(C3&"|"&D3&"|PRODUCT",Notes!$E$3:$E$52,0))&" ","")&IFERROR("ALLOWANCE: "&INDEX(Notes!$D$3:$D$52,MATCH(C3&"|"&D3&"|ALLOWANCE",Notes!$E$3:$E$52,0))&" ","")))
A4: 3 | B4: =IFERROR(MATCH(A4,Lines!$AG$2:$AG$500,0),"") | C4: =IF(B4="","",INDEX(Lines!$B$2:$B$500,B4)) | D4: =IF(B4="","",INDEX(Lines!$C$2:$C$500,B4)) | E4: =IF(C4="","",SUMIFS(Lines!$N$2:$N$500,Lines!$B$2:$B$500,C4,Lines!$C$2:$C$500,D4,Lines!$A$2:$A$500,"line",Lines!$X$2:$X$500,"LABOUR_ALL",Lines!$D$2:$D$500,"quote")) | F4: =IF(C4="","",SUMIFS(Lines!$N$2:$N$500,Lines!$B$2:$B$500,C4,Lines!$C$2:$C$500,D4,Lines!$A$2:$A$500,"line",Lines!$X$2:$X$500,"LABOUR_ALL",Lines!$D$2:$D$500,"invoice")) | G4: =IF(C4="","",F4-E4) | H4: =IF(C4="","",IFERROR(G4/E4,"")) | I4: =IF(C4="","",SUMIFS(Lines!$N$2:$N$500,Lines!$B$2:$B$500,C4,Lines!$C$2:$C$500,D4,Lines!$A$2:$A$500,"line",Lines!$O$2:$O$500,"INSTALL",Lines!$D$2:$D$500,"quote")) | J4: =IF(C4="","",SUMIFS(Lines!$N$2:$N$500,Lines!$B$2:$B$500,C4,Lines!$C$2:$C$500,D4,Lines!$A$2:$A$500,"line",Lines!$O$2:$O$500,"INSTALL",Lines!$D$2:$D$500,"invoice")) | K4: =IF(C4="","",J4-I4) | L4: =IF(C4="","",IFERROR(K4/I4,"")) | M4: =IF(C4="","",SUMIFS(Lines!$N$2:$N$500,Lines!$B$2:$B$500,C4,Lines!$C$2:$C$500,D4,Lines!$A$2:$A$500,"line",Lines!$O$2:$O$500,"PRODUCT",Lines!$D$2:$D$500,"quote")) | N4: =IF(C4="","",SUMIFS(Lines!$N$2:$N$500,Lines!$B$2:$B$500,C4,Lines!$C$2:$C$500,D4,Lines!$A$2:$A$500,"line",Lines!$O$2:$O$500,"PRODUCT",Lines!$D$2:$D$500,"invoice")) | O4: =IF(C4="","",N4-M4) | P4: =IF(C4="","",IFERROR(O4/M4,"")) | Q4: =IF(C4="","",SUMIFS(Lines!$N$2:$N$500,Lines!$B$2:$B$500,C4,Lines!$C$2:$C$500,D4,Lines!$A$2:$A$500,"line",Lines!$O$2:$O$500,"ALLOWANCE",Lines!$D$2:$D$500,"quote")) | R4: =IF(C4="","",SUMIFS(Lines!$N$2:$N$500,Lines!$B$2:$B$500,C4,Lines!$C$2:$C$500,D4,Lines!$A$2:$A$500,"line",Lines!$O$2:$O$500,"ALLOWANCE",Lines!$D$2:$D$500,"invoice")) | S4: =IF(C4="","",R4-Q4) | T4: =IF(C4="","",IFERROR(S4/Q4,"")) | U4: =IF(C4="","",COUNTIFS(Docs!$D$2:$D$51,C4,Docs!$E$2:$E$51,D4,Docs!$F$2:$F$51,"invoice")) | V4: =IF(C4="","",IF(U4=0,"N/A - pending",IF(MAX(ABS(G4),ABS(K4),ABS(O4),ABS(S4))>Settings!$B$2,"Y","N"))) | W4: =IF(C4="","",TRIM(IFERROR("LABOUR_ALL: "&INDEX(Notes!$D$3:$D$52,MATCH(C4&"|"&D4&"|LABOUR_ALL",Notes!$E$3:$E$52,0))&" ","")&IFERROR("INSTALL: "&INDEX(Notes!$D$3:$D$52,MATCH(C4&"|"&D4&"|INSTALL",Notes!$E$3:$E$52,0))&" ","")&IFERROR("PRODUCT: "&INDEX(Notes!$D$3:$D$52,MATCH(C4&"|"&D4&"|PRODUCT",Notes!$E$3:$E$52,0))&" ","")&IFERROR("ALLOWANCE: "&INDEX(Notes!$D$3:$D$52,MATCH(C4&"|"&D4&"|ALLOWANCE",Notes!$E$3:$E$52,0))&" ","")))
A5: 4 | B5: =IFERROR(MATCH(A5,Lines!$AG$2:$AG$500,0),"") | C5: =IF(B5="","",INDEX(Lines!$B$2:$B$500,B5)) | D5: =IF(B5="","",INDEX(Lines!$C$2:$C$500,B5)) | E5: =IF(C5="","",SUMIFS(Lines!$N$2:$N$500,Lines!$B$2:$B$500,C5,Lines!$C$2:$C$500,D5,Lines!$A$2:$A$500,"line",Lines!$X$2:$X$500,"LABOUR_ALL",Lines!$D$2:$D$500,"quote")) | F5: =IF(C5="","",SUMIFS(Lines!$N$2:$N$500,Lines!$B$2:$B$500,C5,Lines!$C$2:$C$500,D5,Lines!$A$2:$A$500,"line",Lines!$X$2:$X$500,"LABOUR_ALL",Lines!$D$2:$D$500,"invoice")) | G5: =IF(C5="","",F5-E5) | H5: =IF(C5="","",IFERROR(G5/E5,"")) | I5: =IF(C5="","",SUMIFS(Lines!$N$2:$N$500,Lines!$B$2:$B$500,C5,Lines!$C$2:$C$500,D5,Lines!$A$2:$A$500,"line",Lines!$O$2:$O$500,"INSTALL",Lines!$D$2:$D$500,"quote")) | J5: =IF(C5="","",SUMIFS(Lines!$N$2:$N$500,Lines!$B$2:$B$500,C5,Lines!$C$2:$C$500,D5,Lines!$A$2:$A$500,"line",Lines!$O$2:$O$500,"INSTALL",Lines!$D$2:$D$500,"invoice")) | K5: =IF(C5="","",J5-I5) | L5: =IF(C5="","",IFERROR(K5/I5,"")) | M5: =IF(C5="","",SUMIFS(Lines!$N$2:$N$500,Lines!$B$2:$B$500,C5,Lines!$C$2:$C$500,D5,Lines!$A$2:$A$500,"line",Lines!$O$2:$O$500,"PRODUCT",Lines!$D$2:$D$500,"quote")) | N5: =IF(C5="","",SUMIFS(Lines!$N$2:$N$500,Lines!$B$2:$B$500,C5,Lines!$C$2:$C$500,D5,Lines!$A$2:$A$500,"line",Lines!$O$2:$O$500,"PRODUCT",Lines!$D$2:$D$500,"invoice")) | O5: =IF(C5="","",N5-M5) | P5: =IF(C5="","",IFERROR(O5/M5,"")) | Q5: =IF(C5="","",SUMIFS(Lines!$N$2:$N$500,Lines!$B$2:$B$500,C5,Lines!$C$2:$C$500,D5,Lines!$A$2:$A$500,"line",Lines!$O$2:$O$500,"ALLOWANCE",Lines!$D$2:$D$500,"quote")) | R5: =IF(C5="","",SUMIFS(Lines!$N$2:$N$500,Lines!$B$2:$B$500,C5,Lines!$C$2:$C$500,D5,Lines!$A$2:$A$500,"line",Lines!$O$2:$O$500,"ALLOWANCE",Lines!$D$2:$D$500,"invoice")) | S5: =IF(C5="","",R5-Q5) | T5: =IF(C5="","",IFERROR(S5/Q5,"")) | U5: =IF(C5="","",COUNTIFS(Docs!$D$2:$D$51,C5,Docs!$E$2:$E$51,D5,Docs!$F$2:$F$51,"invoice")) | V5: =IF(C5="","",IF(U5=0,"N/A - pending",IF(MAX(ABS(G5),ABS(K5),ABS(O5),ABS(S5))>Settings!$B$2,"Y","N"))) | W5: =IF(C5="","",TRIM(IFERROR("LABOUR_ALL: "&INDEX(Notes!$D$3:$D$52,MATCH(C5&"|"&D5&"|LABOUR_ALL",Notes!$E$3:$E$52,0))&" ","")&IFERROR("INSTALL: "&INDEX(Notes!$D$3:$D$52,MATCH(C5&"|"&D5&"|INSTALL",Notes!$E$3:$E$52,0))&" ","")&IFERROR("PRODUCT: "&INDEX(Notes!$D$3:$D$52,MATCH(C5&"|"&D5&"|PRODUCT",Notes!$E$3:$E$52,0))&" ","")&IFERROR("ALLOWANCE: "&INDEX(Notes!$D$3:$D$52,MATCH(C5&"|"&D5&"|ALLOWANCE",Notes!$E$3:$E$52,0))&" ","")))
A6: 5 | B6: =IFERROR(MATCH(A6,Lines!$AG$2:$AG$500,0),"") | C6: =IF(B6="","",INDEX(Lines!$B$2:$B$500,B6)) | D6: =IF(B6="","",INDEX(Lines!$C$2:$C$500,B6)) | E6: =IF(C6="","",SUMIFS(Lines!$N$2:$N$500,Lines!$B$2:$B$500,C6,Lines!$C$2:$C$500,D6,Lines!$A$2:$A$500,"line",Lines!$X$2:$X$500,"LABOUR_ALL",Lines!$D$2:$D$500,"quote")) | F6: =IF(C6="","",SUMIFS(Lines!$N$2:$N$500,Lines!$B$2:$B$500,C6,Lines!$C$2:$C$500,D6,Lines!$A$2:$A$500,"line",Lines!$X$2:$X$500,"LABOUR_ALL",Lines!$D$2:$D$500,"invoice")) | G6: =IF(C6="","",F6-E6) | H6: =IF(C6="","",IFERROR(G6/E6,"")) | I6: =IF(C6="","",SUMIFS(Lines!$N$2:$N$500,Lines!$B$2:$B$500,C6,Lines!$C$2:$C$500,D6,Lines!$A$2:$A$500,"line",Lines!$O$2:$O$500,"INSTALL",Lines!$D$2:$D$500,"quote")) | J6: =IF(C6="","",SUMIFS(Lines!$N$2:$N$500,Lines!$B$2:$B$500,C6,Lines!$C$2:$C$500,D6,Lines!$A$2:$A$500,"line",Lines!$O$2:$O$500,"INSTALL",Lines!$D$2:$D$500,"invoice")) | K6: =IF(C6="","",J6-I6) | L6: =IF(C6="","",IFERROR(K6/I6,"")) | M6: =IF(C6="","",SUMIFS(Lines!$N$2:$N$500,Lines!$B$2:$B$500,C6,Lines!$C$2:$C$500,D6,Lines!$A$2:$A$500,"line",Lines!$O$2:$O$500,"PRODUCT",Lines!$D$2:$D$500,"quote")) | N6: =IF(C6="","",SUMIFS(Lines!$N$2:$N$500,Lines!$B$2:$B$500,C6,Lines!$C$2:$C$500,D6,Lines!$A$2:$A$500,"line",Lines!$O$2:$O$500,"PRODUCT",Lines!$D$2:$D$500,"invoice")) | O6: =IF(C6="","",N6-M6) | P6: =IF(C6="","",IFERROR(O6/M6,"")) | Q6: =IF(C6="","",SUMIFS(Lines!$N$2:$N$500,Lines!$B$2:$B$500,C6,Lines!$C$2:$C$500,D6,Lines!$A$2:$A$500,"line",Lines!$O$2:$O$500,"ALLOWANCE",Lines!$D$2:$D$500,"quote")) | R6: =IF(C6="","",SUMIFS(Lines!$N$2:$N$500,Lines!$B$2:$B$500,C6,Lines!$C$2:$C$500,D6,Lines!$A$2:$A$500,"line",Lines!$O$2:$O$500,"ALLOWANCE",Lines!$D$2:$D$500,"invoice")) | S6: =IF(C6="","",R6-Q6) | T6: =IF(C6="","",IFERROR(S6/Q6,"")) | U6: =IF(C6="","",COUNTIFS(Docs!$D$2:$D$51,C6,Docs!$E$2:$E$51,D6,Docs!$F$2:$F$51,"invoice")) | V6: =IF(C6="","",IF(U6=0,"N/A - pending",IF(MAX(ABS(G6),ABS(K6),ABS(O6),ABS(S6))>Settings!$B$2,"Y","N"))) | W6: =IF(C6="","",TRIM(IFERROR("LABOUR_ALL: "&INDEX(Notes!$D$3:$D$52,MATCH(C6&"|"&D6&"|LABOUR_ALL",Notes!$E$3:$E$52,0))&" ","")&IFERROR("INSTALL: "&INDEX(Notes!$D$3:$D$52,MATCH(C6&"|"&D6&"|INSTALL",Notes!$E$3:$E$52,0))&" ","")&IFERROR("PRODUCT: "&INDEX(Notes!$D$3:$D$52,MATCH(C6&"|"&D6&"|PRODUCT",Notes!$E$3:$E$52,0))&" ","")&IFERROR("ALLOWANCE: "&INDEX(Notes!$D$3:$D$52,MATCH(C6&"|"&D6&"|ALLOWANCE",Notes!$E$3:$E$52,0))&" ","")))
A7: 6 | B7: =IFERROR(MATCH(A7,Lines!$AG$2:$AG$500,0),"") | C7: =IF(B7="","",INDEX(Lines!$B$2:$B$500,B7)) | D7: =IF(B7="","",INDEX(Lines!$C$2:$C$500,B7)) | E7: =IF(C7="","",SUMIFS(Lines!$N$2:$N$500,Lines!$B$2:$B$500,C7,Lines!$C$2:$C$500,D7,Lines!$A$2:$A$500,"line",Lines!$X$2:$X$500,"LABOUR_ALL",Lines!$D$2:$D$500,"quote")) | F7: =IF(C7="","",SUMIFS(Lines!$N$2:$N$500,Lines!$B$2:$B$500,C7,Lines!$C$2:$C$500,D7,Lines!$A$2:$A$500,"line",Lines!$X$2:$X$500,"LABOUR_ALL",Lines!$D$2:$D$500,"invoice")) | G7: =IF(C7="","",F7-E7) | H7: =IF(C7="","",IFERROR(G7/E7,"")) | I7: =IF(C7="","",SUMIFS(Lines!$N$2:$N$500,Lines!$B$2:$B$500,C7,Lines!$C$2:$C$500,D7,Lines!$A$2:$A$500,"line",Lines!$O$2:$O$500,"INSTALL",Lines!$D$2:$D$500,"quote")) | J7: =IF(C7="","",SUMIFS(Lines!$N$2:$N$500,Lines!$B$2:$B$500,C7,Lines!$C$2:$C$500,D7,Lines!$A$2:$A$500,"line",Lines!$O$2:$O$500,"INSTALL",Lines!$D$2:$D$500,"invoice")) | K7: =IF(C7="","",J7-I7) | L7: =IF(C7="","",IFERROR(K7/I7,"")) | M7: =IF(C7="","",SUMIFS(Lines!$N$2:$N$500,Lines!$B$2:$B$500,C7,Lines!$C$2:$C$500,D7,Lines!$A$2:$A$500,"line",Lines!$O$2:$O$500,"PRODUCT",Lines!$D$2:$D$500,"quote")) | N7: =IF(C7="","",SUMIFS(Lines!$N$2:$N$500,Lines!$B$2:$B$500,C7,Lines!$C$2:$C$500,D7,Lines!$A$2:$A$500,"line",Lines!$O$2:$O$500,"PRODUCT",Lines!$D$2:$D$500,"invoice")) | O7: =IF(C7="","",N7-M7) | P7: =IF(C7="","",IFERROR(O7/M7,"")) | Q7: =IF(C7="","",SUMIFS(Lines!$N$2:$N$500,Lines!$B$2:$B$500,C7,Lines!$C$2:$C$500,D7,Lines!$A$2:$A$500,"line",Lines!$O$2:$O$500,"ALLOWANCE",Lines!$D$2:$D$500,"quote")) | R7: =IF(C7="","",SUMIFS(Lines!$N$2:$N$500,Lines!$B$2:$B$500,C7,Lines!$C$2:$C$500,D7,Lines!$A$2:$A$500,"line",Lines!$O$2:$O$500,"ALLOWANCE",Lines!$D$2:$D$500,"invoice")) | S7: =IF(C7="","",R7-Q7) | T7: =IF(C7="","",IFERROR(S7/Q7,"")) | U7: =IF(C7="","",COUNTIFS(Docs!$D$2:$D$51,C7,Docs!$E$2:$E$51,D7,Docs!$F$2:$F$51,"invoice")) | V7: =IF(C7="","",IF(U7=0,"N/A - pending",IF(MAX(ABS(G7),ABS(K7),ABS(O7),ABS(S7))>Settings!$B$2,"Y","N"))) | W7: =IF(C7="","",TRIM(IFERROR("LABOUR_ALL: "&INDEX(Notes!$D$3:$D$52,MATCH(C7&"|"&D7&"|LABOUR_ALL",Notes!$E$3:$E$52,0))&" ","")&IFERROR("INSTALL: "&INDEX(Notes!$D$3:$D$52,MATCH(C7&"|"&D7&"|INSTALL",Notes!$E$3:$E$52,0))&" ","")&IFERROR("PRODUCT: "&INDEX(Notes!$D$3:$D$52,MATCH(C7&"|"&D7&"|PRODUCT",Notes!$E$3:$E$52,0))&" ","")&IFERROR("ALLOWANCE: "&INDEX(Notes!$D$3:$D$52,MATCH(C7&"|"&D7&"|ALLOWANCE",Notes!$E$3:$E$52,0))&" ","")))
A8: 7 | B8: =IFERROR(MATCH(A8,Lines!$AG$2:$AG$500,0),"") | C8: =IF(B8="","",INDEX(Lines!$B$2:$B$500,B8)) | D8: =IF(B8="","",INDEX(Lines!$C$2:$C$500,B8)) | E8: =IF(C8="","",SUMIFS(Lines!$N$2:$N$500,Lines!$B$2:$B$500,C8,Lines!$C$2:$C$500,D8,Lines!$A$2:$A$500,"line",Lines!$X$2:$X$500,"LABOUR_ALL",Lines!$D$2:$D$500,"quote")) | F8: =IF(C8="","",SUMIFS(Lines!$N$2:$N$500,Lines!$B$2:$B$500,C8,Lines!$C$2:$C$500,D8,Lines!$A$2:$A$500,"line",Lines!$X$2:$X$500,"LABOUR_ALL",Lines!$D$2:$D$500,"invoice")) | G8: =IF(C8="","",F8-E8) | H8: =IF(C8="","",IFERROR(G8/E8,"")) | I8: =IF(C8="","",SUMIFS(Lines!$N$2:$N$500,Lines!$B$2:$B$500,C8,Lines!$C$2:$C$500,D8,Lines!$A$2:$A$500,"line",Lines!$O$2:$O$500,"INSTALL",Lines!$D$2:$D$500,"quote")) | J8: =IF(C8="","",SUMIFS(Lines!$N$2:$N$500,Lines!$B$2:$B$500,C8,Lines!$C$2:$C$500,D8,Lines!$A$2:$A$500,"line",Lines!$O$2:$O$500,"INSTALL",Lines!$D$2:$D$500,"invoice")) | K8: =IF(C8="","",J8-I8) | L8: =IF(C8="","",IFERROR(K8/I8,"")) | M8: =IF(C8="","",SUMIFS(Lines!$N$2:$N$500,Lines!$B$2:$B$500,C8,Lines!$C$2:$C$500,D8,Lines!$A$2:$A$500,"line",Lines!$O$2:$O$500,"PRODUCT",Lines!$D$2:$D$500,"quote")) | N8: =IF(C8="","",SUMIFS(Lines!$N$2:$N$500,Lines!$B$2:$B$500,C8,Lines!$C$2:$C$500,D8,Lines!$A$2:$A$500,"line",Lines!$O$2:$O$500,"PRODUCT",Lines!$D$2:$D$500,"invoice")) | O8: =IF(C8="","",N8-M8) | P8: =IF(C8="","",IFERROR(O8/M8,"")) | Q8: =IF(C8="","",SUMIFS(Lines!$N$2:$N$500,Lines!$B$2:$B$500,C8,Lines!$C$2:$C$500,D8,Lines!$A$2:$A$500,"line",Lines!$O$2:$O$500,"ALLOWANCE",Lines!$D$2:$D$500,"quote")) | R8: =IF(C8="","",SUMIFS(Lines!$N$2:$N$500,Lines!$B$2:$B$500,C8,Lines!$C$2:$C$500,D8,Lines!$A$2:$A$500,"line",Lines!$O$2:$O$500,"ALLOWANCE",Lines!$D$2:$D$500,"invoice")) | S8: =IF(C8="","",R8-Q8) | T8: =IF(C8="","",IFERROR(S8/Q8,"")) | U8: =IF(C8="","",COUNTIFS(Docs!$D$2:$D$51,C8,Docs!$E$2:$E$51,D8,Docs!$F$2:$F$51,"invoice")) | V8: =IF(C8="","",IF(U8=0,"N/A - pending",IF(MAX(ABS(G8),ABS(K8),ABS(O8),ABS(S8))>Settings!$B$2,"Y","N"))) | W8: =IF(C8="","",TRIM(IFERROR("LABOUR_ALL: "&INDEX(Notes!$D$3:$D$52,MATCH(C8&"|"&D8&"|LABOUR_ALL",Notes!$E$3:$E$52,0))&" ","")&IFERROR("INSTALL: "&INDEX(Notes!$D$3:$D$52,MATCH(C8&"|"&D8&"|INSTALL",Notes!$E$3:$E$52,0))&" ","")&IFERROR("PRODUCT: "&INDEX(Notes!$D$3:$D$52,MATCH(C8&"|"&D8&"|PRODUCT",Notes!$E$3:$E$52,0))&" ","")&IFERROR("ALLOWANCE: "&INDEX(Notes!$D$3:$D$52,MATCH(C8&"|"&D8&"|ALLOWANCE",Notes!$E$3:$E$52,0))&" ","")))
A9: 8 | B9: =IFERROR(MATCH(A9,Lines!$AG$2:$AG$500,0),"") | C9: =IF(B9="","",INDEX(Lines!$B$2:$B$500,B9)) | D9: =IF(B9="","",INDEX(Lines!$C$2:$C$500,B9)) | E9: =IF(C9="","",SUMIFS(Lines!$N$2:$N$500,Lines!$B$2:$B$500,C9,Lines!$C$2:$C$500,D9,Lines!$A$2:$A$500,"line",Lines!$X$2:$X$500,"LABOUR_ALL",Lines!$D$2:$D$500,"quote")) | F9: =IF(C9="","",SUMIFS(Lines!$N$2:$N$500,Lines!$B$2:$B$500,C9,Lines!$C$2:$C$500,D9,Lines!$A$2:$A$500,"line",Lines!$X$2:$X$500,"LABOUR_ALL",Lines!$D$2:$D$500,"invoice")) | G9: =IF(C9="","",F9-E9) | H9: =IF(C9="","",IFERROR(G9/E9,"")) | I9: =IF(C9="","",SUMIFS(Lines!$N$2:$N$500,Lines!$B$2:$B$500,C9,Lines!$C$2:$C$500,D9,Lines!$A$2:$A$500,"line",Lines!$O$2:$O$500,"INSTALL",Lines!$D$2:$D$500,"quote")) | J9: =IF(C9="","",SUMIFS(Lines!$N$2:$N$500,Lines!$B$2:$B$500,C9,Lines!$C$2:$C$500,D9,Lines!$A$2:$A$500,"line",Lines!$O$2:$O$500,"INSTALL",Lines!$D$2:$D$500,"invoice")) | K9: =IF(C9="","",J9-I9) | L9: =IF(C9="","",IFERROR(K9/I9,"")) | M9: =IF(C9="","",SUMIFS(Lines!$N$2:$N$500,Lines!$B$2:$B$500,C9,Lines!$C$2:$C$500,D9,Lines!$A$2:$A$500,"line",Lines!$O$2:$O$500,"PRODUCT",Lines!$D$2:$D$500,"quote")) | N9: =IF(C9="","",SUMIFS(Lines!$N$2:$N$500,Lines!$B$2:$B$500,C9,Lines!$C$2:$C$500,D9,Lines!$A$2:$A$500,"line",Lines!$O$2:$O$500,"PRODUCT",Lines!$D$2:$D$500,"invoice")) | O9: =IF(C9="","",N9-M9) | P9: =IF(C9="","",IFERROR(O9/M9,"")) | Q9: =IF(C9="","",SUMIFS(Lines!$N$2:$N$500,Lines!$B$2:$B$500,C9,Lines!$C$2:$C$500,D9,Lines!$A$2:$A$500,"line",Lines!$O$2:$O$500,"ALLOWANCE",Lines!$D$2:$D$500,"quote")) | R9: =IF(C9="","",SUMIFS(Lines!$N$2:$N$500,Lines!$B$2:$B$500,C9,Lines!$C$2:$C$500,D9,Lines!$A$2:$A$500,"line",Lines!$O$2:$O$500,"ALLOWANCE",Lines!$D$2:$D$500,"invoice")) | S9: =IF(C9="","",R9-Q9) | T9: =IF(C9="","",IFERROR(S9/Q9,"")) | U9: =IF(C9="","",COUNTIFS(Docs!$D$2:$D$51,C9,Docs!$E$2:$E$51,D9,Docs!$F$2:$F$51,"invoice")) | V9: =IF(C9="","",IF(U9=0,"N/A - pending",IF(MAX(ABS(G9),ABS(K9),ABS(O9),ABS(S9))>Settings!$B$2,"Y","N"))) | W9: =IF(C9="","",TRIM(IFERROR("LABOUR_ALL: "&INDEX(Notes!$D$3:$D$52,MATCH(C9&"|"&D9&"|LABOUR_ALL",Notes!$E$3:$E$52,0))&" ","")&IFERROR("INSTALL: "&INDEX(Notes!$D$3:$D$52,MATCH(C9&"|"&D9&"|INSTALL",Notes!$E$3:$E$52,0))&" ","")&IFERROR("PRODUCT: "&INDEX(Notes!$D$3:$D$52,MATCH(C9&"|"&D9&"|PRODUCT",Notes!$E$3:$E$52,0))&" ","")&IFERROR("ALLOWANCE: "&INDEX(Notes!$D$3:$D$52,MATCH(C9&"|"&D9&"|ALLOWANCE",Notes!$E$3:$E$52,0))&" ","")))
A10: 9 | B10: =IFERROR(MATCH(A10,Lines!$AG$2:$AG$500,0),"") | C10: =IF(B10="","",INDEX(Lines!$B$2:$B$500,B10)) | D10: =IF(B10="","",INDEX(Lines!$C$2:$C$500,B10)) | E10: =IF(C10="","",SUMIFS(Lines!$N$2:$N$500,Lines!$B$2:$B$500,C10,Lines!$C$2:$C$500,D10,Lines!$A$2:$A$500,"line",Lines!$X$2:$X$500,"LABOUR_ALL",Lines!$D$2:$D$500,"quote")) | F10: =IF(C10="","",SUMIFS(Lines!$N$2:$N$500,Lines!$B$2:$B$500,C10,Lines!$C$2:$C$500,D10,Lines!$A$2:$A$500,"line",Lines!$X$2:$X$500,"LABOUR_ALL",Lines!$D$2:$D$500,"invoice")) | G10: =IF(C10="","",F10-E10) | H10: =IF(C10="","",IFERROR(G10/E10,"")) | I10: =IF(C10="","",SUMIFS(Lines!$N$2:$N$500,Lines!$B$2:$B$500,C10,Lines!$C$2:$C$500,D10,Lines!$A$2:$A$500,"line",Lines!$O$2:$O$500,"INSTALL",Lines!$D$2:$D$500,"quote")) | J10: =IF(C10="","",SUMIFS(Lines!$N$2:$N$500,Lines!$B$2:$B$500,C10,Lines!$C$2:$C$500,D10,Lines!$A$2:$A$500,"line",Lines!$O$2:$O$500,"INSTALL",Lines!$D$2:$D$500,"invoice")) | K10: =IF(C10="","",J10-I10) | L10: =IF(C10="","",IFERROR(K10/I10,"")) | M10: =IF(C10="","",SUMIFS(Lines!$N$2:$N$500,Lines!$B$2:$B$500,C10,Lines!$C$2:$C$500,D10,Lines!$A$2:$A$500,"line",Lines!$O$2:$O$500,"PRODUCT",Lines!$D$2:$D$500,"quote")) | N10: =IF(C10="","",SUMIFS(Lines!$N$2:$N$500,Lines!$B$2:$B$500,C10,Lines!$C$2:$C$500,D10,Lines!$A$2:$A$500,"line",Lines!$O$2:$O$500,"PRODUCT",Lines!$D$2:$D$500,"invoice")) | O10: =IF(C10="","",N10-M10) | P10: =IF(C10="","",IFERROR(O10/M10,"")) | Q10: =IF(C10="","",SUMIFS(Lines!$N$2:$N$500,Lines!$B$2:$B$500,C10,Lines!$C$2:$C$500,D10,Lines!$A$2:$A$500,"line",Lines!$O$2:$O$500,"ALLOWANCE",Lines!$D$2:$D$500,"quote")) | R10: =IF(C10="","",SUMIFS(Lines!$N$2:$N$500,Lines!$B$2:$B$500,C10,Lines!$C$2:$C$500,D10,Lines!$A$2:$A$500,"line",Lines!$O$2:$O$500,"ALLOWANCE",Lines!$D$2:$D$500,"invoice")) | S10: =IF(C10="","",R10-Q10) | T10: =IF(C10="","",IFERROR(S10/Q10,"")) | U10: =IF(C10="","",COUNTIFS(Docs!$D$2:$D$51,C10,Docs!$E$2:$E$51,D10,Docs!$F$2:$F$51,"invoice")) | V10: =IF(C10="","",IF(U10=0,"N/A - pending",IF(MAX(ABS(G10),ABS(K10),ABS(O10),ABS(S10))>Settings!$B$2,"Y","N"))) | W10: =IF(C10="","",TRIM(IFERROR("LABOUR_ALL: "&INDEX(Notes!$D$3:$D$52,MATCH(C10&"|"&D10&"|LABOUR_ALL",Notes!$E$3:$E$52,0))&" ","")&IFERROR("INSTALL: "&INDEX(Notes!$D$3:$D$52,MATCH(C10&"|"&D10&"|INSTALL",Notes!$E$3:$E$52,0))&" ","")&IFERROR("PRODUCT: "&INDEX(Notes!$D$3:$D$52,MATCH(C10&"|"&D10&"|PRODUCT",Notes!$E$3:$E$52,0))&" ","")&IFERROR("ALLOWANCE: "&INDEX(Notes!$D$3:$D$52,MATCH(C10&"|"&D10&"|ALLOWANCE",Notes!$E$3:$E$52,0))&" ","")))
A11: 10 | B11: =IFERROR(MATCH(A11,Lines!$AG$2:$AG$500,0),"") | C11: =IF(B11="","",INDEX(Lines!$B$2:$B$500,B11)) | D11: =IF(B11="","",INDEX(Lines!$C$2:$C$500,B11)) | E11: =IF(C11="","",SUMIFS(Lines!$N$2:$N$500,Lines!$B$2:$B$500,C11,Lines!$C$2:$C$500,D11,Lines!$A$2:$A$500,"line",Lines!$X$2:$X$500,"LABOUR_ALL",Lines!$D$2:$D$500,"quote")) | F11: =IF(C11="","",SUMIFS(Lines!$N$2:$N$500,Lines!$B$2:$B$500,C11,Lines!$C$2:$C$500,D11,Lines!$A$2:$A$500,"line",Lines!$X$2:$X$500,"LABOUR_ALL",Lines!$D$2:$D$500,"invoice")) | G11: =IF(C11="","",F11-E11) | H11: =IF(C11="","",IFERROR(G11/E11,"")) | I11: =IF(C11="","",SUMIFS(Lines!$N$2:$N$500,Lines!$B$2:$B$500,C11,Lines!$C$2:$C$500,D11,Lines!$A$2:$A$500,"line",Lines!$O$2:$O$500,"INSTALL",Lines!$D$2:$D$500,"quote")) | J11: =IF(C11="","",SUMIFS(Lines!$N$2:$N$500,Lines!$B$2:$B$500,C11,Lines!$C$2:$C$500,D11,Lines!$A$2:$A$500,"line",Lines!$O$2:$O$500,"INSTALL",Lines!$D$2:$D$500,"invoice")) | K11: =IF(C11="","",J11-I11) | L11: =IF(C11="","",IFERROR(K11/I11,"")) | M11: =IF(C11="","",SUMIFS(Lines!$N$2:$N$500,Lines!$B$2:$B$500,C11,Lines!$C$2:$C$500,D11,Lines!$A$2:$A$500,"line",Lines!$O$2:$O$500,"PRODUCT",Lines!$D$2:$D$500,"quote")) | N11: =IF(C11="","",SUMIFS(Lines!$N$2:$N$500,Lines!$B$2:$B$500,C11,Lines!$C$2:$C$500,D11,Lines!$A$2:$A$500,"line",Lines!$O$2:$O$500,"PRODUCT",Lines!$D$2:$D$500,"invoice")) | O11: =IF(C11="","",N11-M11) | P11: =IF(C11="","",IFERROR(O11/M11,"")) | Q11: =IF(C11="","",SUMIFS(Lines!$N$2:$N$500,Lines!$B$2:$B$500,C11,Lines!$C$2:$C$500,D11,Lines!$A$2:$A$500,"line",Lines!$O$2:$O$500,"ALLOWANCE",Lines!$D$2:$D$500,"quote")) | R11: =IF(C11="","",SUMIFS(Lines!$N$2:$N$500,Lines!$B$2:$B$500,C11,Lines!$C$2:$C$500,D11,Lines!$A$2:$A$500,"line",Lines!$O$2:$O$500,"ALLOWANCE",Lines!$D$2:$D$500,"invoice")) | S11: =IF(C11="","",R11-Q11) | T11: =IF(C11="","",IFERROR(S11/Q11,"")) | U11: =IF(C11="","",COUNTIFS(Docs!$D$2:$D$51,C11,Docs!$E$2:$E$51,D11,Docs!$F$2:$F$51,"invoice")) | V11: =IF(C11="","",IF(U11=0,"N/A - pending",IF(MAX(ABS(G11),ABS(K11),ABS(O11),ABS(S11))>Settings!$B$2,"Y","N"))) | W11: =IF(C11="","",TRIM(IFERROR("LABOUR_ALL: "&INDEX(Notes!$D$3:$D$52,MATCH(C11&"|"&D11&"|LABOUR_ALL",Notes!$E$3:$E$52,0))&" ","")&IFERROR("INSTALL: "&INDEX(Notes!$D$3:$D$52,MATCH(C11&"|"&D11&"|INSTALL",Notes!$E$3:$E$52,0))&" ","")&IFERROR("PRODUCT: "&INDEX(Notes!$D$3:$D$52,MATCH(C11&"|"&D11&"|PRODUCT",Notes!$E$3:$E$52,0))&" ","")&IFERROR("ALLOWANCE: "&INDEX(Notes!$D$3:$D$52,MATCH(C11&"|"&D11&"|ALLOWANCE",Notes!$E$3:$E$52,0))&" ","")))
A12: 11 | B12: =IFERROR(MATCH(A12,Lines!$AG$2:$AG$500,0),"") | C12: =IF(B12="","",INDEX(Lines!$B$2:$B$500,B12)) | D12: =IF(B12="","",INDEX(Lines!$C$2:$C$500,B12)) | E12: =IF(C12="","",SUMIFS(Lines!$N$2:$N$500,Lines!$B$2:$B$500,C12,Lines!$C$2:$C$500,D12,Lines!$A$2:$A$500,"line",Lines!$X$2:$X$500,"LABOUR_ALL",Lines!$D$2:$D$500,"quote")) | F12: =IF(C12="","",SUMIFS(Lines!$N$2:$N$500,Lines!$B$2:$B$500,C12,Lines!$C$2:$C$500,D12,Lines!$A$2:$A$500,"line",Lines!$X$2:$X$500,"LABOUR_ALL",Lines!$D$2:$D$500,"invoice")) | G12: =IF(C12="","",F12-E12) | H12: =IF(C12="","",IFERROR(G12/E12,"")) | I12: =IF(C12="","",SUMIFS(Lines!$N$2:$N$500,Lines!$B$2:$B$500,C12,Lines!$C$2:$C$500,D12,Lines!$A$2:$A$500,"line",Lines!$O$2:$O$500,"INSTALL",Lines!$D$2:$D$500,"quote")) | J12: =IF(C12="","",SUMIFS(Lines!$N$2:$N$500,Lines!$B$2:$B$500,C12,Lines!$C$2:$C$500,D12,Lines!$A$2:$A$500,"line",Lines!$O$2:$O$500,"INSTALL",Lines!$D$2:$D$500,"invoice")) | K12: =IF(C12="","",J12-I12) | L12: =IF(C12="","",IFERROR(K12/I12,"")) | M12: =IF(C12="","",SUMIFS(Lines!$N$2:$N$500,Lines!$B$2:$B$500,C12,Lines!$C$2:$C$500,D12,Lines!$A$2:$A$500,"line",Lines!$O$2:$O$500,"PRODUCT",Lines!$D$2:$D$500,"quote")) | N12: =IF(C12="","",SUMIFS(Lines!$N$2:$N$500,Lines!$B$2:$B$500,C12,Lines!$C$2:$C$500,D12,Lines!$A$2:$A$500,"line",Lines!$O$2:$O$500,"PRODUCT",Lines!$D$2:$D$500,"invoice")) | O12: =IF(C12="","",N12-M12) | P12: =IF(C12="","",IFERROR(O12/M12,"")) | Q12: =IF(C12="","",SUMIFS(Lines!$N$2:$N$500,Lines!$B$2:$B$500,C12,Lines!$C$2:$C$500,D12,Lines!$A$2:$A$500,"line",Lines!$O$2:$O$500,"ALLOWANCE",Lines!$D$2:$D$500,"quote")) | R12: =IF(C12="","",SUMIFS(Lines!$N$2:$N$500,Lines!$B$2:$B$500,C12,Lines!$C$2:$C$500,D12,Lines!$A$2:$A$500,"line",Lines!$O$2:$O$500,"ALLOWANCE",Lines!$D$2:$D$500,"invoice")) | S12: =IF(C12="","",R12-Q12) | T12: =IF(C12="","",IFERROR(S12/Q12,"")) | U12: =IF(C12="","",COUNTIFS(Docs!$D$2:$D$51,C12,Docs!$E$2:$E$51,D12,Docs!$F$2:$F$51,"invoice")) | V12: =IF(C12="","",IF(U12=0,"N/A - pending",IF(MAX(ABS(G12),ABS(K12),ABS(O12),ABS(S12))>Settings!$B$2,"Y","N"))) | W12: =IF(C12="","",TRIM(IFERROR("LABOUR_ALL: "&INDEX(Notes!$D$3:$D$52,MATCH(C12&"|"&D12&"|LABOUR_ALL",Notes!$E$3:$E$52,0))&" ","")&IFERROR("INSTALL: "&INDEX(Notes!$D$3:$D$52,MATCH(C12&"|"&D12&"|INSTALL",Notes!$E$3:$E$52,0))&" ","")&IFERROR("PRODUCT: "&INDEX(Notes!$D$3:$D$52,MATCH(C12&"|"&D12&"|PRODUCT",Notes!$E$3:$E$52,0))&" ","")&IFERROR("ALLOWANCE: "&INDEX(Notes!$D$3:$D$52,MATCH(C12&"|"&D12&"|ALLOWANCE",Notes!$E$3:$E$52,0))&" ","")))
A13: 12 | B13: =IFERROR(MATCH(A13,Lines!$AG$2:$AG$500,0),"") | C13: =IF(B13="","",INDEX(Lines!$B$2:$B$500,B13)) | D13: =IF(B13="","",INDEX(Lines!$C$2:$C$500,B13)) | E13: =IF(C13="","",SUMIFS(Lines!$N$2:$N$500,Lines!$B$2:$B$500,C13,Lines!$C$2:$C$500,D13,Lines!$A$2:$A$500,"line",Lines!$X$2:$X$500,"LABOUR_ALL",Lines!$D$2:$D$500,"quote")) | F13: =IF(C13="","",SUMIFS(Lines!$N$2:$N$500,Lines!$B$2:$B$500,C13,Lines!$C$2:$C$500,D13,Lines!$A$2:$A$500,"line",Lines!$X$2:$X$500,"LABOUR_ALL",Lines!$D$2:$D$500,"invoice")) | G13: =IF(C13="","",F13-E13) | H13: =IF(C13="","",IFERROR(G13/E13,"")) | I13: =IF(C13="","",SUMIFS(Lines!$N$2:$N$500,Lines!$B$2:$B$500,C13,Lines!$C$2:$C$500,D13,Lines!$A$2:$A$500,"line",Lines!$O$2:$O$500,"INSTALL",Lines!$D$2:$D$500,"quote")) | J13: =IF(C13="","",SUMIFS(Lines!$N$2:$N$500,Lines!$B$2:$B$500,C13,Lines!$C$2:$C$500,D13,Lines!$A$2:$A$500,"line",Lines!$O$2:$O$500,"INSTALL",Lines!$D$2:$D$500,"invoice")) | K13: =IF(C13="","",J13-I13) | L13: =IF(C13="","",IFERROR(K13/I13,"")) | M13: =IF(C13="","",SUMIFS(Lines!$N$2:$N$500,Lines!$B$2:$B$500,C13,Lines!$C$2:$C$500,D13,Lines!$A$2:$A$500,"line",Lines!$O$2:$O$500,"PRODUCT",Lines!$D$2:$D$500,"quote")) | N13: =IF(C13="","",SUMIFS(Lines!$N$2:$N$500,Lines!$B$2:$B$500,C13,Lines!$C$2:$C$500,D13,Lines!$A$2:$A$500,"line",Lines!$O$2:$O$500,"PRODUCT",Lines!$D$2:$D$500,"invoice")) | O13: =IF(C13="","",N13-M13) | P13: =IF(C13="","",IFERROR(O13/M13,"")) | Q13: =IF(C13="","",SUMIFS(Lines!$N$2:$N$500,Lines!$B$2:$B$500,C13,Lines!$C$2:$C$500,D13,Lines!$A$2:$A$500,"line",Lines!$O$2:$O$500,"ALLOWANCE",Lines!$D$2:$D$500,"quote")) | R13: =IF(C13="","",SUMIFS(Lines!$N$2:$N$500,Lines!$B$2:$B$500,C13,Lines!$C$2:$C$500,D13,Lines!$A$2:$A$500,"line",Lines!$O$2:$O$500,"ALLOWANCE",Lines!$D$2:$D$500,"invoice")) | S13: =IF(C13="","",R13-Q13) | T13: =IF(C13="","",IFERROR(S13/Q13,"")) | U13: =IF(C13="","",COUNTIFS(Docs!$D$2:$D$51,C13,Docs!$E$2:$E$51,D13,Docs!$F$2:$F$51,"invoice")) | V13: =IF(C13="","",IF(U13=0,"N/A - pending",IF(MAX(ABS(G13),ABS(K13),ABS(O13),ABS(S13))>Settings!$B$2,"Y","N"))) | W13: =IF(C13="","",TRIM(IFERROR("LABOUR_ALL: "&INDEX(Notes!$D$3:$D$52,MATCH(C13&"|"&D13&"|LABOUR_ALL",Notes!$E$3:$E$52,0))&" ","")&IFERROR("INSTALL: "&INDEX(Notes!$D$3:$D$52,MATCH(C13&"|"&D13&"|INSTALL",Notes!$E$3:$E$52,0))&" ","")&IFERROR("PRODUCT: "&INDEX(Notes!$D$3:$D$52,MATCH(C13&"|"&D13&"|PRODUCT",Notes!$E$3:$E$52,0))&" ","")&IFERROR("ALLOWANCE: "&INDEX(Notes!$D$3:$D$52,MATCH(C13&"|"&D13&"|ALLOWANCE",Notes!$E$3:$E$52,0))&" ","")))
... A51: 50 | B51: =IFERROR(MATCH(A51,Lines!$AG$2:$AG$500,0),"") | C51: =IF(B51="","",INDEX(Lines!$B$2:$B$500,B51)) | D51: =IF(B51="","",INDEX(Lines!$C$2:$C$500,B51)) | E51: =IF(C51="","",SUMIFS(Lines!$N$2:$N$500,Lines!$B$2:$B$500,C51,Lines!$C$2:$C$500,D51,Lines!$A$2:$A$500,"line",Lines!$X$2:$X$500,"LABOUR_ALL",Lines!$D$2:$D$500,"quote")) | F51: =IF(C51="","",SUMIFS(Lines!$N$2:$N$500,Lines!$B$2:$B$500,C51,Lines!$C$2:$C$500,D51,Lines!$A$2:$A$500,"line",Lines!$X$2:$X$500,"LABOUR_ALL",Lines!$D$2:$D$500,"invoice")) | G51: =IF(C51="","",F51-E51) | H51: =IF(C51="","",IFERROR(G51/E51,"")) | I51: =IF(C51="","",SUMIFS(Lines!$N$2:$N$500,Lines!$B$2:$B$500,C51,Lines!$C$2:$C$500,D51,Lines!$A$2:$A$500,"line",Lines!$O$2:$O$500,"INSTALL",Lines!$D$2:$D$500,"quote")) | J51: =IF(C51="","",SUMIFS(Lines!$N$2:$N$500,Lines!$B$2:$B$500,C51,Lines!$C$2:$C$500,D51,Lines!$A$2:$A$500,"line",Lines!$O$2:$O$500,"INSTALL",Lines!$D$2:$D$500,"invoice")) | K51: =IF(C51="","",J51-I51) | L51: =IF(C51="","",IFERROR(K51/I51,"")) | M51: =IF(C51="","",SUMIFS(Lines!$N$2:$N$500,Lines!$B$2:$B$500,C51,Lines!$C$2:$C$500,D51,Lines!$A$2:$A$500,"line",Lines!$O$2:$O$500,"PRODUCT",Lines!$D$2:$D$500,"quote")) | N51: =IF(C51="","",SUMIFS(Lines!$N$2:$N$500,Lines!$B$2:$B$500,C51,Lines!$C$2:$C$500,D51,Lines!$A$2:$A$500,"line",Lines!$O$2:$O$500,"PRODUCT",Lines!$D$2:$D$500,"invoice")) | O51: =IF(C51="","",N51-M51) | P51: =IF(C51="","",IFERROR(O51/M51,"")) | Q51: =IF(C51="","",SUMIFS(Lines!$N$2:$N$500,Lines!$B$2:$B$500,C51,Lines!$C$2:$C$500,D51,Lines!$A$2:$A$500,"line",Lines!$O$2:$O$500,"ALLOWANCE",Lines!$D$2:$D$500,"quote")) | R51: =IF(C51="","",SUMIFS(Lines!$N$2:$N$500,Lines!$B$2:$B$500,C51,Lines!$C$2:$C$500,D51,Lines!$A$2:$A$500,"line",Lines!$O$2:$O$500,"ALLOWANCE",Lines!$D$2:$D$500,"invoice")) | S51: =IF(C51="","",R51-Q51) | T51: =IF(C51="","",IFERROR(S51/Q51,"")) | U51: =IF(C51="","",COUNTIFS(Docs!$D$2:$D$51,C51,Docs!$E$2:$E$51,D51,Docs!$F$2:$F$51,"invoice")) | V51: =IF(C51="","",IF(U51=0,"N/A - pending",IF(MAX(ABS(G51),ABS(K51),ABS(O51),ABS(S51))>Settings!$B$2,"Y","N"))) | W51: =IF(C51="","",TRIM(IFERROR("LABOUR_ALL: "&INDEX(Notes!$D$3:$D$52,MATCH(C51&"|"&D51&"|LABOUR_ALL",Notes!$E$3:$E$52,0))&" ","")&IFERROR("INSTALL: "&INDEX(Notes!$D$3:$D$52,MATCH(C51&"|"&D51&"|INSTALL",Notes!$E$3:$E$52,0))&" ","")&IFERROR("PRODUCT: "&INDEX(Notes!$D$3:$D$52,MATCH(C51&"|"&D51&"|PRODUCT",Notes!$E$3:$E$52,0))&" ","")&IFERROR("ALLOWANCE: "&INDEX(Notes!$D$3:$D$52,MATCH(C51&"|"&D51&"|ALLOWANCE",Notes!$E$3:$E$52,0))&" ","")))

Sheet Detail
A1: seq | B1: row | C1: project | D1: vendor | E1: doc_type | F1: doc_id | G1: ref_quote_id | H1: page | I1: line_no | J1: label_as_printed | K1: description | L1: category | M1: quote_amount | N1: invoice_amount | O1: variance | P1: status | Q1: note
A2: 1 | B2: =IFERROR(MATCH(A2,Lines!$AC$2:$AC$500,0),"") | C2: =IF(B2="","",INDEX(Lines!$B$2:$B$500,B2)&"") | D2: =IF(B2="","",INDEX(Lines!$C$2:$C$500,B2)&"") | E2: =IF(B2="","",INDEX(Lines!$D$2:$D$500,B2)&"") | F2: =IF(B2="","",INDEX(Lines!$E$2:$E$500,B2)&"") | G2: =IF(B2="","",INDEX(Lines!$G$2:$G$500,B2)&"") | H2: =IF(B2="","",INDEX(Lines!$H$2:$H$500,B2)) | I2: =IF(B2="","",INDEX(Lines!$I$2:$I$500,B2)) | J2: =IF(B2="","",INDEX(Lines!$J$2:$J$500,B2)&"") | K2: =IF(B2="","",INDEX(Lines!$K$2:$K$500,B2)&"") | L2: =IF(B2="","",INDEX(Lines!$O$2:$O$500,B2)&"") | M2: =IF(B2="","",IF(E2="quote",INDEX(Lines!$N$2:$N$500,B2),"")) | N2: =IF(B2="","",IF(E2="quote",IF(INDEX(Lines!$Z$2:$Z$500,B2)=0,"",INDEX(Lines!$Y$2:$Y$500,B2)),INDEX(Lines!$N$2:$N$500,B2))) | O2: =IF(B2="","",N(N2)-N(M2)) | P2: =IF(B2="","",INDEX(Lines!$AB$2:$AB$500,B2)&"") | Q2: =IF(B2="","",IFERROR(INDEX(Notes!$F$62:$F$111,MATCH(F2&"|"&I2,Notes!$G$62:$G$111,0)),""))
A3: 2 | B3: =IFERROR(MATCH(A3,Lines!$AC$2:$AC$500,0),"") | C3: =IF(B3="","",INDEX(Lines!$B$2:$B$500,B3)&"") | D3: =IF(B3="","",INDEX(Lines!$C$2:$C$500,B3)&"") | E3: =IF(B3="","",INDEX(Lines!$D$2:$D$500,B3)&"") | F3: =IF(B3="","",INDEX(Lines!$E$2:$E$500,B3)&"") | G3: =IF(B3="","",INDEX(Lines!$G$2:$G$500,B3)&"") | H3: =IF(B3="","",INDEX(Lines!$H$2:$H$500,B3)) | I3: =IF(B3="","",INDEX(Lines!$I$2:$I$500,B3)) | J3: =IF(B3="","",INDEX(Lines!$J$2:$J$500,B3)&"") | K3: =IF(B3="","",INDEX(Lines!$K$2:$K$500,B3)&"") | L3: =IF(B3="","",INDEX(Lines!$O$2:$O$500,B3)&"") | M3: =IF(B3="","",IF(E3="quote",INDEX(Lines!$N$2:$N$500,B3),"")) | N3: =IF(B3="","",IF(E3="quote",IF(INDEX(Lines!$Z$2:$Z$500,B3)=0,"",INDEX(Lines!$Y$2:$Y$500,B3)),INDEX(Lines!$N$2:$N$500,B3))) | O3: =IF(B3="","",N(N3)-N(M3)) | P3: =IF(B3="","",INDEX(Lines!$AB$2:$AB$500,B3)&"") | Q3: =IF(B3="","",IFERROR(INDEX(Notes!$F$62:$F$111,MATCH(F3&"|"&I3,Notes!$G$62:$G$111,0)),""))
A4: 3 | B4: =IFERROR(MATCH(A4,Lines!$AC$2:$AC$500,0),"") | C4: =IF(B4="","",INDEX(Lines!$B$2:$B$500,B4)&"") | D4: =IF(B4="","",INDEX(Lines!$C$2:$C$500,B4)&"") | E4: =IF(B4="","",INDEX(Lines!$D$2:$D$500,B4)&"") | F4: =IF(B4="","",INDEX(Lines!$E$2:$E$500,B4)&"") | G4: =IF(B4="","",INDEX(Lines!$G$2:$G$500,B4)&"") | H4: =IF(B4="","",INDEX(Lines!$H$2:$H$500,B4)) | I4: =IF(B4="","",INDEX(Lines!$I$2:$I$500,B4)) | J4: =IF(B4="","",INDEX(Lines!$J$2:$J$500,B4)&"") | K4: =IF(B4="","",INDEX(Lines!$K$2:$K$500,B4)&"") | L4: =IF(B4="","",INDEX(Lines!$O$2:$O$500,B4)&"") | M4: =IF(B4="","",IF(E4="quote",INDEX(Lines!$N$2:$N$500,B4),"")) | N4: =IF(B4="","",IF(E4="quote",IF(INDEX(Lines!$Z$2:$Z$500,B4)=0,"",INDEX(Lines!$Y$2:$Y$500,B4)),INDEX(Lines!$N$2:$N$500,B4))) | O4: =IF(B4="","",N(N4)-N(M4)) | P4: =IF(B4="","",INDEX(Lines!$AB$2:$AB$500,B4)&"") | Q4: =IF(B4="","",IFERROR(INDEX(Notes!$F$62:$F$111,MATCH(F4&"|"&I4,Notes!$G$62:$G$111,0)),""))
A5: 4 | B5: =IFERROR(MATCH(A5,Lines!$AC$2:$AC$500,0),"") | C5: =IF(B5="","",INDEX(Lines!$B$2:$B$500,B5)&"") | D5: =IF(B5="","",INDEX(Lines!$C$2:$C$500,B5)&"") | E5: =IF(B5="","",INDEX(Lines!$D$2:$D$500,B5)&"") | F5: =IF(B5="","",INDEX(Lines!$E$2:$E$500,B5)&"") | G5: =IF(B5="","",INDEX(Lines!$G$2:$G$500,B5)&"") | H5: =IF(B5="","",INDEX(Lines!$H$2:$H$500,B5)) | I5: =IF(B5="","",INDEX(Lines!$I$2:$I$500,B5)) | J5: =IF(B5="","",INDEX(Lines!$J$2:$J$500,B5)&"") | K5: =IF(B5="","",INDEX(Lines!$K$2:$K$500,B5)&"") | L5: =IF(B5="","",INDEX(Lines!$O$2:$O$500,B5)&"") | M5: =IF(B5="","",IF(E5="quote",INDEX(Lines!$N$2:$N$500,B5),"")) | N5: =IF(B5="","",IF(E5="quote",IF(INDEX(Lines!$Z$2:$Z$500,B5)=0,"",INDEX(Lines!$Y$2:$Y$500,B5)),INDEX(Lines!$N$2:$N$500,B5))) | O5: =IF(B5="","",N(N5)-N(M5)) | P5: =IF(B5="","",INDEX(Lines!$AB$2:$AB$500,B5)&"") | Q5: =IF(B5="","",IFERROR(INDEX(Notes!$F$62:$F$111,MATCH(F5&"|"&I5,Notes!$G$62:$G$111,0)),""))
A6: 5 | B6: =IFERROR(MATCH(A6,Lines!$AC$2:$AC$500,0),"") | C6: =IF(B6="","",INDEX(Lines!$B$2:$B$500,B6)&"") | D6: =IF(B6="","",INDEX(Lines!$C$2:$C$500,B6)&"") | E6: =IF(B6="","",INDEX(Lines!$D$2:$D$500,B6)&"") | F6: =IF(B6="","",INDEX(Lines!$E$2:$E$500,B6)&"") | G6: =IF(B6="","",INDEX(Lines!$G$2:$G$500,B6)&"") | H6: =IF(B6="","",INDEX(Lines!$H$2:$H$500,B6)) | I6: =IF(B6="","",INDEX(Lines!$I$2:$I$500,B6)) | J6: =IF(B6="","",INDEX(Lines!$J$2:$J$500,B6)&"") | K6: =IF(B6="","",INDEX(Lines!$K$2:$K$500,B6)&"") | L6: =IF(B6="","",INDEX(Lines!$O$2:$O$500,B6)&"") | M6: =IF(B6="","",IF(E6="quote",INDEX(Lines!$N$2:$N$500,B6),"")) | N6: =IF(B6="","",IF(E6="quote",IF(INDEX(Lines!$Z$2:$Z$500,B6)=0,"",INDEX(Lines!$Y$2:$Y$500,B6)),INDEX(Lines!$N$2:$N$500,B6))) | O6: =IF(B6="","",N(N6)-N(M6)) | P6: =IF(B6="","",INDEX(Lines!$AB$2:$AB$500,B6)&"") | Q6: =IF(B6="","",IFERROR(INDEX(Notes!$F$62:$F$111,MATCH(F6&"|"&I6,Notes!$G$62:$G$111,0)),""))
A7: 6 | B7: =IFERROR(MATCH(A7,Lines!$AC$2:$AC$500,0),"") | C7: =IF(B7="","",INDEX(Lines!$B$2:$B$500,B7)&"") | D7: =IF(B7="","",INDEX(Lines!$C$2:$C$500,B7)&"") | E7: =IF(B7="","",INDEX(Lines!$D$2:$D$500,B7)&"") | F7: =IF(B7="","",INDEX(Lines!$E$2:$E$500,B7)&"") | G7: =IF(B7="","",INDEX(Lines!$G$2:$G$500,B7)&"") | H7: =IF(B7="","",INDEX(Lines!$H$2:$H$500,B7)) | I7: =IF(B7="","",INDEX(Lines!$I$2:$I$500,B7)) | J7: =IF(B7="","",INDEX(Lines!$J$2:$J$500,B7)&"") | K7: =IF(B7="","",INDEX(Lines!$K$2:$K$500,B7)&"") | L7: =IF(B7="","",INDEX(Lines!$O$2:$O$500,B7)&"") | M7: =IF(B7="","",IF(E7="quote",INDEX(Lines!$N$2:$N$500,B7),"")) | N7: =IF(B7="","",IF(E7="quote",IF(INDEX(Lines!$Z$2:$Z$500,B7)=0,"",INDEX(Lines!$Y$2:$Y$500,B7)),INDEX(Lines!$N$2:$N$500,B7))) | O7: =IF(B7="","",N(N7)-N(M7)) | P7: =IF(B7="","",INDEX(Lines!$AB$2:$AB$500,B7)&"") | Q7: =IF(B7="","",IFERROR(INDEX(Notes!$F$62:$F$111,MATCH(F7&"|"&I7,Notes!$G$62:$G$111,0)),""))
A8: 7 | B8: =IFERROR(MATCH(A8,Lines!$AC$2:$AC$500,0),"") | C8: =IF(B8="","",INDEX(Lines!$B$2:$B$500,B8)&"") | D8: =IF(B8="","",INDEX(Lines!$C$2:$C$500,B8)&"") | E8: =IF(B8="","",INDEX(Lines!$D$2:$D$500,B8)&"") | F8: =IF(B8="","",INDEX(Lines!$E$2:$E$500,B8)&"") | G8: =IF(B8="","",INDEX(Lines!$G$2:$G$500,B8)&"") | H8: =IF(B8="","",INDEX(Lines!$H$2:$H$500,B8)) | I8: =IF(B8="","",INDEX(Lines!$I$2:$I$500,B8)) | J8: =IF(B8="","",INDEX(Lines!$J$2:$J$500,B8)&"") | K8: =IF(B8="","",INDEX(Lines!$K$2:$K$500,B8)&"") | L8: =IF(B8="","",INDEX(Lines!$O$2:$O$500,B8)&"") | M8: =IF(B8="","",IF(E8="quote",INDEX(Lines!$N$2:$N$500,B8),"")) | N8: =IF(B8="","",IF(E8="quote",IF(INDEX(Lines!$Z$2:$Z$500,B8)=0,"",INDEX(Lines!$Y$2:$Y$500,B8)),INDEX(Lines!$N$2:$N$500,B8))) | O8: =IF(B8="","",N(N8)-N(M8)) | P8: =IF(B8="","",INDEX(Lines!$AB$2:$AB$500,B8)&"") | Q8: =IF(B8="","",IFERROR(INDEX(Notes!$F$62:$F$111,MATCH(F8&"|"&I8,Notes!$G$62:$G$111,0)),""))
A9: 8 | B9: =IFERROR(MATCH(A9,Lines!$AC$2:$AC$500,0),"") | C9: =IF(B9="","",INDEX(Lines!$B$2:$B$500,B9)&"") | D9: =IF(B9="","",INDEX(Lines!$C$2:$C$500,B9)&"") | E9: =IF(B9="","",INDEX(Lines!$D$2:$D$500,B9)&"") | F9: =IF(B9="","",INDEX(Lines!$E$2:$E$500,B9)&"") | G9: =IF(B9="","",INDEX(Lines!$G$2:$G$500,B9)&"") | H9: =IF(B9="","",INDEX(Lines!$H$2:$H$500,B9)) | I9: =IF(B9="","",INDEX(Lines!$I$2:$I$500,B9)) | J9: =IF(B9="","",INDEX(Lines!$J$2:$J$500,B9)&"") | K9: =IF(B9="","",INDEX(Lines!$K$2:$K$500,B9)&"") | L9: =IF(B9="","",INDEX(Lines!$O$2:$O$500,B9)&"") | M9: =IF(B9="","",IF(E9="quote",INDEX(Lines!$N$2:$N$500,B9),"")) | N9: =IF(B9="","",IF(E9="quote",IF(INDEX(Lines!$Z$2:$Z$500,B9)=0,"",INDEX(Lines!$Y$2:$Y$500,B9)),INDEX(Lines!$N$2:$N$500,B9))) | O9: =IF(B9="","",N(N9)-N(M9)) | P9: =IF(B9="","",INDEX(Lines!$AB$2:$AB$500,B9)&"") | Q9: =IF(B9="","",IFERROR(INDEX(Notes!$F$62:$F$111,MATCH(F9&"|"&I9,Notes!$G$62:$G$111,0)),""))
A10: 9 | B10: =IFERROR(MATCH(A10,Lines!$AC$2:$AC$500,0),"") | C10: =IF(B10="","",INDEX(Lines!$B$2:$B$500,B10)&"") | D10: =IF(B10="","",INDEX(Lines!$C$2:$C$500,B10)&"") | E10: =IF(B10="","",INDEX(Lines!$D$2:$D$500,B10)&"") | F10: =IF(B10="","",INDEX(Lines!$E$2:$E$500,B10)&"") | G10: =IF(B10="","",INDEX(Lines!$G$2:$G$500,B10)&"") | H10: =IF(B10="","",INDEX(Lines!$H$2:$H$500,B10)) | I10: =IF(B10="","",INDEX(Lines!$I$2:$I$500,B10)) | J10: =IF(B10="","",INDEX(Lines!$J$2:$J$500,B10)&"") | K10: =IF(B10="","",INDEX(Lines!$K$2:$K$500,B10)&"") | L10: =IF(B10="","",INDEX(Lines!$O$2:$O$500,B10)&"") | M10: =IF(B10="","",IF(E10="quote",INDEX(Lines!$N$2:$N$500,B10),"")) | N10: =IF(B10="","",IF(E10="quote",IF(INDEX(Lines!$Z$2:$Z$500,B10)=0,"",INDEX(Lines!$Y$2:$Y$500,B10)),INDEX(Lines!$N$2:$N$500,B10))) | O10: =IF(B10="","",N(N10)-N(M10)) | P10: =IF(B10="","",INDEX(Lines!$AB$2:$AB$500,B10)&"") | Q10: =IF(B10="","",IFERROR(INDEX(Notes!$F$62:$F$111,MATCH(F10&"|"&I10,Notes!$G$62:$G$111,0)),""))
A11: 10 | B11: =IFERROR(MATCH(A11,Lines!$AC$2:$AC$500,0),"") | C11: =IF(B11="","",INDEX(Lines!$B$2:$B$500,B11)&"") | D11: =IF(B11="","",INDEX(Lines!$C$2:$C$500,B11)&"") | E11: =IF(B11="","",INDEX(Lines!$D$2:$D$500,B11)&"") | F11: =IF(B11="","",INDEX(Lines!$E$2:$E$500,B11)&"") | G11: =IF(B11="","",INDEX(Lines!$G$2:$G$500,B11)&"") | H11: =IF(B11="","",INDEX(Lines!$H$2:$H$500,B11)) | I11: =IF(B11="","",INDEX(Lines!$I$2:$I$500,B11)) | J11: =IF(B11="","",INDEX(Lines!$J$2:$J$500,B11)&"") | K11: =IF(B11="","",INDEX(Lines!$K$2:$K$500,B11)&"") | L11: =IF(B11="","",INDEX(Lines!$O$2:$O$500,B11)&"") | M11: =IF(B11="","",IF(E11="quote",INDEX(Lines!$N$2:$N$500,B11),"")) | N11: =IF(B11="","",IF(E11="quote",IF(INDEX(Lines!$Z$2:$Z$500,B11)=0,"",INDEX(Lines!$Y$2:$Y$500,B11)),INDEX(Lines!$N$2:$N$500,B11))) | O11: =IF(B11="","",N(N11)-N(M11)) | P11: =IF(B11="","",INDEX(Lines!$AB$2:$AB$500,B11)&"") | Q11: =IF(B11="","",IFERROR(INDEX(Notes!$F$62:$F$111,MATCH(F11&"|"&I11,Notes!$G$62:$G$111,0)),""))
A12: 11 | B12: =IFERROR(MATCH(A12,Lines!$AC$2:$AC$500,0),"") | C12: =IF(B12="","",INDEX(Lines!$B$2:$B$500,B12)&"") | D12: =IF(B12="","",INDEX(Lines!$C$2:$C$500,B12)&"") | E12: =IF(B12="","",INDEX(Lines!$D$2:$D$500,B12)&"") | F12: =IF(B12="","",INDEX(Lines!$E$2:$E$500,B12)&"") | G12: =IF(B12="","",INDEX(Lines!$G$2:$G$500,B12)&"") | H12: =IF(B12="","",INDEX(Lines!$H$2:$H$500,B12)) | I12: =IF(B12="","",INDEX(Lines!$I$2:$I$500,B12)) | J12: =IF(B12="","",INDEX(Lines!$J$2:$J$500,B12)&"") | K12: =IF(B12="","",INDEX(Lines!$K$2:$K$500,B12)&"") | L12: =IF(B12="","",INDEX(Lines!$O$2:$O$500,B12)&"") | M12: =IF(B12="","",IF(E12="quote",INDEX(Lines!$N$2:$N$500,B12),"")) | N12: =IF(B12="","",IF(E12="quote",IF(INDEX(Lines!$Z$2:$Z$500,B12)=0,"",INDEX(Lines!$Y$2:$Y$500,B12)),INDEX(Lines!$N$2:$N$500,B12))) | O12: =IF(B12="","",N(N12)-N(M12)) | P12: =IF(B12="","",INDEX(Lines!$AB$2:$AB$500,B12)&"") | Q12: =IF(B12="","",IFERROR(INDEX(Notes!$F$62:$F$111,MATCH(F12&"|"&I12,Notes!$G$62:$G$111,0)),""))
A13: 12 | B13: =IFERROR(MATCH(A13,Lines!$AC$2:$AC$500,0),"") | C13: =IF(B13="","",INDEX(Lines!$B$2:$B$500,B13)&"") | D13: =IF(B13="","",INDEX(Lines!$C$2:$C$500,B13)&"") | E13: =IF(B13="","",INDEX(Lines!$D$2:$D$500,B13)&"") | F13: =IF(B13="","",INDEX(Lines!$E$2:$E$500,B13)&"") | G13: =IF(B13="","",INDEX(Lines!$G$2:$G$500,B13)&"") | H13: =IF(B13="","",INDEX(Lines!$H$2:$H$500,B13)) | I13: =IF(B13="","",INDEX(Lines!$I$2:$I$500,B13)) | J13: =IF(B13="","",INDEX(Lines!$J$2:$J$500,B13)&"") | K13: =IF(B13="","",INDEX(Lines!$K$2:$K$500,B13)&"") | L13: =IF(B13="","",INDEX(Lines!$O$2:$O$500,B13)&"") | M13: =IF(B13="","",IF(E13="quote",INDEX(Lines!$N$2:$N$500,B13),"")) | N13: =IF(B13="","",IF(E13="quote",IF(INDEX(Lines!$Z$2:$Z$500,B13)=0,"",INDEX(Lines!$Y$2:$Y$500,B13)),INDEX(Lines!$N$2:$N$500,B13))) | O13: =IF(B13="","",N(N13)-N(M13)) | P13: =IF(B13="","",INDEX(Lines!$AB$2:$AB$500,B13)&"") | Q13: =IF(B13="","",IFERROR(INDEX(Notes!$F$62:$F$111,MATCH(F13&"|"&I13,Notes!$G$62:$G$111,0)),""))
... A101: 100 | B101: =IFERROR(MATCH(A101,Lines!$AC$2:$AC$500,0),"") | C101: =IF(B101="","",INDEX(Lines!$B$2:$B$500,B101)&"") | D101: =IF(B101="","",INDEX(Lines!$C$2:$C$500,B101)&"") | E101: =IF(B101="","",INDEX(Lines!$D$2:$D$500,B101)&"") | F101: =IF(B101="","",INDEX(Lines!$E$2:$E$500,B101)&"") | G101: =IF(B101="","",INDEX(Lines!$G$2:$G$500,B101)&"") | H101: =IF(B101="","",INDEX(Lines!$H$2:$H$500,B101)) | I101: =IF(B101="","",INDEX(Lines!$I$2:$I$500,B101)) | J101: =IF(B101="","",INDEX(Lines!$J$2:$J$500,B101)&"") | K101: =IF(B101="","",INDEX(Lines!$K$2:$K$500,B101)&"") | L101: =IF(B101="","",INDEX(Lines!$O$2:$O$500,B101)&"") | M101: =IF(B101="","",IF(E101="quote",INDEX(Lines!$N$2:$N$500,B101),"")) | N101: =IF(B101="","",IF(E101="quote",IF(INDEX(Lines!$Z$2:$Z$500,B101)=0,"",INDEX(Lines!$Y$2:$Y$500,B101)),INDEX(Lines!$N$2:$N$500,B101))) | O101: =IF(B101="","",N(N101)-N(M101)) | P101: =IF(B101="","",INDEX(Lines!$AB$2:$AB$500,B101)&"") | Q101: =IF(B101="","",IFERROR(INDEX(Notes!$F$62:$F$111,MATCH(F101&"|"&I101,Notes!$G$62:$G$111,0)),""))

Sheet Review
A1: seq | B1: doc_id | C1: page | D1: line_no | E1: label_as_printed | F1: reason
A2: 1 | B2: =IF(A2<=COUNT(Lines!$AE$2:$AE$500),IFERROR(INDEX(Lines!$E$2:$E$500,MATCH(A2,Lines!$AE$2:$AE$500,0))&"",""),IFERROR(INDEX(Docs!$C$2:$C$51,MATCH(A2-COUNT(Lines!$AE$2:$AE$500),Docs!$AD$2:$AD$51,0))&"","")) | C2: =IF(A2<=COUNT(Lines!$AE$2:$AE$500),IFERROR(INDEX(Lines!$H$2:$H$500,MATCH(A2,Lines!$AE$2:$AE$500,0)),""),IFERROR("","")) | D2: =IF(A2<=COUNT(Lines!$AE$2:$AE$500),IFERROR(INDEX(Lines!$I$2:$I$500,MATCH(A2,Lines!$AE$2:$AE$500,0)),""),IFERROR("","")) | E2: =IF(A2<=COUNT(Lines!$AE$2:$AE$500),IFERROR(INDEX(Lines!$J$2:$J$500,MATCH(A2,Lines!$AE$2:$AE$500,0))&"",""),IFERROR("","")) | F2: =IF(A2<=COUNT(Lines!$AE$2:$AE$500),IFERROR(INDEX(Lines!$AD$2:$AD$500,MATCH(A2,Lines!$AE$2:$AE$500,0))&"",""),IFERROR(INDEX(Docs!$AC$2:$AC$51,MATCH(A2-COUNT(Lines!$AE$2:$AE$500),Docs!$AD$2:$AD$51,0))&"",""))
A3: 2 | B3: =IF(A3<=COUNT(Lines!$AE$2:$AE$500),IFERROR(INDEX(Lines!$E$2:$E$500,MATCH(A3,Lines!$AE$2:$AE$500,0))&"",""),IFERROR(INDEX(Docs!$C$2:$C$51,MATCH(A3-COUNT(Lines!$AE$2:$AE$500),Docs!$AD$2:$AD$51,0))&"","")) | C3: =IF(A3<=COUNT(Lines!$AE$2:$AE$500),IFERROR(INDEX(Lines!$H$2:$H$500,MATCH(A3,Lines!$AE$2:$AE$500,0)),""),IFERROR("","")) | D3: =IF(A3<=COUNT(Lines!$AE$2:$AE$500),IFERROR(INDEX(Lines!$I$2:$I$500,MATCH(A3,Lines!$AE$2:$AE$500,0)),""),IFERROR("","")) | E3: =IF(A3<=COUNT(Lines!$AE$2:$AE$500),IFERROR(INDEX(Lines!$J$2:$J$500,MATCH(A3,Lines!$AE$2:$AE$500,0))&"",""),IFERROR("","")) | F3: =IF(A3<=COUNT(Lines!$AE$2:$AE$500),IFERROR(INDEX(Lines!$AD$2:$AD$500,MATCH(A3,Lines!$AE$2:$AE$500,0))&"",""),IFERROR(INDEX(Docs!$AC$2:$AC$51,MATCH(A3-COUNT(Lines!$AE$2:$AE$500),Docs!$AD$2:$AD$51,0))&"",""))
A4: 3 | B4: =IF(A4<=COUNT(Lines!$AE$2:$AE$500),IFERROR(INDEX(Lines!$E$2:$E$500,MATCH(A4,Lines!$AE$2:$AE$500,0))&"",""),IFERROR(INDEX(Docs!$C$2:$C$51,MATCH(A4-COUNT(Lines!$AE$2:$AE$500),Docs!$AD$2:$AD$51,0))&"","")) | C4: =IF(A4<=COUNT(Lines!$AE$2:$AE$500),IFERROR(INDEX(Lines!$H$2:$H$500,MATCH(A4,Lines!$AE$2:$AE$500,0)),""),IFERROR("","")) | D4: =IF(A4<=COUNT(Lines!$AE$2:$AE$500),IFERROR(INDEX(Lines!$I$2:$I$500,MATCH(A4,Lines!$AE$2:$AE$500,0)),""),IFERROR("","")) | E4: =IF(A4<=COUNT(Lines!$AE$2:$AE$500),IFERROR(INDEX(Lines!$J$2:$J$500,MATCH(A4,Lines!$AE$2:$AE$500,0))&"",""),IFERROR("","")) | F4: =IF(A4<=COUNT(Lines!$AE$2:$AE$500),IFERROR(INDEX(Lines!$AD$2:$AD$500,MATCH(A4,Lines!$AE$2:$AE$500,0))&"",""),IFERROR(INDEX(Docs!$AC$2:$AC$51,MATCH(A4-COUNT(Lines!$AE$2:$AE$500),Docs!$AD$2:$AD$51,0))&"",""))
A5: 4 | B5: =IF(A5<=COUNT(Lines!$AE$2:$AE$500),IFERROR(INDEX(Lines!$E$2:$E$500,MATCH(A5,Lines!$AE$2:$AE$500,0))&"",""),IFERROR(INDEX(Docs!$C$2:$C$51,MATCH(A5-COUNT(Lines!$AE$2:$AE$500),Docs!$AD$2:$AD$51,0))&"","")) | C5: =IF(A5<=COUNT(Lines!$AE$2:$AE$500),IFERROR(INDEX(Lines!$H$2:$H$500,MATCH(A5,Lines!$AE$2:$AE$500,0)),""),IFERROR("","")) | D5: =IF(A5<=COUNT(Lines!$AE$2:$AE$500),IFERROR(INDEX(Lines!$I$2:$I$500,MATCH(A5,Lines!$AE$2:$AE$500,0)),""),IFERROR("","")) | E5: =IF(A5<=COUNT(Lines!$AE$2:$AE$500),IFERROR(INDEX(Lines!$J$2:$J$500,MATCH(A5,Lines!$AE$2:$AE$500,0))&"",""),IFERROR("","")) | F5: =IF(A5<=COUNT(Lines!$AE$2:$AE$500),IFERROR(INDEX(Lines!$AD$2:$AD$500,MATCH(A5,Lines!$AE$2:$AE$500,0))&"",""),IFERROR(INDEX(Docs!$AC$2:$AC$51,MATCH(A5-COUNT(Lines!$AE$2:$AE$500),Docs!$AD$2:$AD$51,0))&"",""))
A6: 5 | B6: =IF(A6<=COUNT(Lines!$AE$2:$AE$500),IFERROR(INDEX(Lines!$E$2:$E$500,MATCH(A6,Lines!$AE$2:$AE$500,0))&"",""),IFERROR(INDEX(Docs!$C$2:$C$51,MATCH(A6-COUNT(Lines!$AE$2:$AE$500),Docs!$AD$2:$AD$51,0))&"","")) | C6: =IF(A6<=COUNT(Lines!$AE$2:$AE$500),IFERROR(INDEX(Lines!$H$2:$H$500,MATCH(A6,Lines!$AE$2:$AE$500,0)),""),IFERROR("","")) | D6: =IF(A6<=COUNT(Lines!$AE$2:$AE$500),IFERROR(INDEX(Lines!$I$2:$I$500,MATCH(A6,Lines!$AE$2:$AE$500,0)),""),IFERROR("","")) | E6: =IF(A6<=COUNT(Lines!$AE$2:$AE$500),IFERROR(INDEX(Lines!$J$2:$J$500,MATCH(A6,Lines!$AE$2:$AE$500,0))&"",""),IFERROR("","")) | F6: =IF(A6<=COUNT(Lines!$AE$2:$AE$500),IFERROR(INDEX(Lines!$AD$2:$AD$500,MATCH(A6,Lines!$AE$2:$AE$500,0))&"",""),IFERROR(INDEX(Docs!$AC$2:$AC$51,MATCH(A6-COUNT(Lines!$AE$2:$AE$500),Docs!$AD$2:$AD$51,0))&"",""))
A7: 6 | B7: =IF(A7<=COUNT(Lines!$AE$2:$AE$500),IFERROR(INDEX(Lines!$E$2:$E$500,MATCH(A7,Lines!$AE$2:$AE$500,0))&"",""),IFERROR(INDEX(Docs!$C$2:$C$51,MATCH(A7-COUNT(Lines!$AE$2:$AE$500),Docs!$AD$2:$AD$51,0))&"","")) | C7: =IF(A7<=COUNT(Lines!$AE$2:$AE$500),IFERROR(INDEX(Lines!$H$2:$H$500,MATCH(A7,Lines!$AE$2:$AE$500,0)),""),IFERROR("","")) | D7: =IF(A7<=COUNT(Lines!$AE$2:$AE$500),IFERROR(INDEX(Lines!$I$2:$I$500,MATCH(A7,Lines!$AE$2:$AE$500,0)),""),IFERROR("","")) | E7: =IF(A7<=COUNT(Lines!$AE$2:$AE$500),IFERROR(INDEX(Lines!$J$2:$J$500,MATCH(A7,Lines!$AE$2:$AE$500,0))&"",""),IFERROR("","")) | F7: =IF(A7<=COUNT(Lines!$AE$2:$AE$500),IFERROR(INDEX(Lines!$AD$2:$AD$500,MATCH(A7,Lines!$AE$2:$AE$500,0))&"",""),IFERROR(INDEX(Docs!$AC$2:$AC$51,MATCH(A7-COUNT(Lines!$AE$2:$AE$500),Docs!$AD$2:$AD$51,0))&"",""))
A8: 7 | B8: =IF(A8<=COUNT(Lines!$AE$2:$AE$500),IFERROR(INDEX(Lines!$E$2:$E$500,MATCH(A8,Lines!$AE$2:$AE$500,0))&"",""),IFERROR(INDEX(Docs!$C$2:$C$51,MATCH(A8-COUNT(Lines!$AE$2:$AE$500),Docs!$AD$2:$AD$51,0))&"","")) | C8: =IF(A8<=COUNT(Lines!$AE$2:$AE$500),IFERROR(INDEX(Lines!$H$2:$H$500,MATCH(A8,Lines!$AE$2:$AE$500,0)),""),IFERROR("","")) | D8: =IF(A8<=COUNT(Lines!$AE$2:$AE$500),IFERROR(INDEX(Lines!$I$2:$I$500,MATCH(A8,Lines!$AE$2:$AE$500,0)),""),IFERROR("","")) | E8: =IF(A8<=COUNT(Lines!$AE$2:$AE$500),IFERROR(INDEX(Lines!$J$2:$J$500,MATCH(A8,Lines!$AE$2:$AE$500,0))&"",""),IFERROR("","")) | F8: =IF(A8<=COUNT(Lines!$AE$2:$AE$500),IFERROR(INDEX(Lines!$AD$2:$AD$500,MATCH(A8,Lines!$AE$2:$AE$500,0))&"",""),IFERROR(INDEX(Docs!$AC$2:$AC$51,MATCH(A8-COUNT(Lines!$AE$2:$AE$500),Docs!$AD$2:$AD$51,0))&"",""))
A9: 8 | B9: =IF(A9<=COUNT(Lines!$AE$2:$AE$500),IFERROR(INDEX(Lines!$E$2:$E$500,MATCH(A9,Lines!$AE$2:$AE$500,0))&"",""),IFERROR(INDEX(Docs!$C$2:$C$51,MATCH(A9-COUNT(Lines!$AE$2:$AE$500),Docs!$AD$2:$AD$51,0))&"","")) | C9: =IF(A9<=COUNT(Lines!$AE$2:$AE$500),IFERROR(INDEX(Lines!$H$2:$H$500,MATCH(A9,Lines!$AE$2:$AE$500,0)),""),IFERROR("","")) | D9: =IF(A9<=COUNT(Lines!$AE$2:$AE$500),IFERROR(INDEX(Lines!$I$2:$I$500,MATCH(A9,Lines!$AE$2:$AE$500,0)),""),IFERROR("","")) | E9: =IF(A9<=COUNT(Lines!$AE$2:$AE$500),IFERROR(INDEX(Lines!$J$2:$J$500,MATCH(A9,Lines!$AE$2:$AE$500,0))&"",""),IFERROR("","")) | F9: =IF(A9<=COUNT(Lines!$AE$2:$AE$500),IFERROR(INDEX(Lines!$AD$2:$AD$500,MATCH(A9,Lines!$AE$2:$AE$500,0))&"",""),IFERROR(INDEX(Docs!$AC$2:$AC$51,MATCH(A9-COUNT(Lines!$AE$2:$AE$500),Docs!$AD$2:$AD$51,0))&"",""))
A10: 9 | B10: =IF(A10<=COUNT(Lines!$AE$2:$AE$500),IFERROR(INDEX(Lines!$E$2:$E$500,MATCH(A10,Lines!$AE$2:$AE$500,0))&"",""),IFERROR(INDEX(Docs!$C$2:$C$51,MATCH(A10-COUNT(Lines!$AE$2:$AE$500),Docs!$AD$2:$AD$51,0))&"","")) | C10: =IF(A10<=COUNT(Lines!$AE$2:$AE$500),IFERROR(INDEX(Lines!$H$2:$H$500,MATCH(A10,Lines!$AE$2:$AE$500,0)),""),IFERROR("","")) | D10: =IF(A10<=COUNT(Lines!$AE$2:$AE$500),IFERROR(INDEX(Lines!$I$2:$I$500,MATCH(A10,Lines!$AE$2:$AE$500,0)),""),IFERROR("","")) | E10: =IF(A10<=COUNT(Lines!$AE$2:$AE$500),IFERROR(INDEX(Lines!$J$2:$J$500,MATCH(A10,Lines!$AE$2:$AE$500,0))&"",""),IFERROR("","")) | F10: =IF(A10<=COUNT(Lines!$AE$2:$AE$500),IFERROR(INDEX(Lines!$AD$2:$AD$500,MATCH(A10,Lines!$AE$2:$AE$500,0))&"",""),IFERROR(INDEX(Docs!$AC$2:$AC$51,MATCH(A10-COUNT(Lines!$AE$2:$AE$500),Docs!$AD$2:$AD$51,0))&"",""))
A11: 10 | B11: =IF(A11<=COUNT(Lines!$AE$2:$AE$500),IFERROR(INDEX(Lines!$E$2:$E$500,MATCH(A11,Lines!$AE$2:$AE$500,0))&"",""),IFERROR(INDEX(Docs!$C$2:$C$51,MATCH(A11-COUNT(Lines!$AE$2:$AE$500),Docs!$AD$2:$AD$51,0))&"","")) | C11: =IF(A11<=COUNT(Lines!$AE$2:$AE$500),IFERROR(INDEX(Lines!$H$2:$H$500,MATCH(A11,Lines!$AE$2:$AE$500,0)),""),IFERROR("","")) | D11: =IF(A11<=COUNT(Lines!$AE$2:$AE$500),IFERROR(INDEX(Lines!$I$2:$I$500,MATCH(A11,Lines!$AE$2:$AE$500,0)),""),IFERROR("","")) | E11: =IF(A11<=COUNT(Lines!$AE$2:$AE$500),IFERROR(INDEX(Lines!$J$2:$J$500,MATCH(A11,Lines!$AE$2:$AE$500,0))&"",""),IFERROR("","")) | F11: =IF(A11<=COUNT(Lines!$AE$2:$AE$500),IFERROR(INDEX(Lines!$AD$2:$AD$500,MATCH(A11,Lines!$AE$2:$AE$500,0))&"",""),IFERROR(INDEX(Docs!$AC$2:$AC$51,MATCH(A11-COUNT(Lines!$AE$2:$AE$500),Docs!$AD$2:$AD$51,0))&"",""))
A12: 11 | B12: =IF(A12<=COUNT(Lines!$AE$2:$AE$500),IFERROR(INDEX(Lines!$E$2:$E$500,MATCH(A12,Lines!$AE$2:$AE$500,0))&"",""),IFERROR(INDEX(Docs!$C$2:$C$51,MATCH(A12-COUNT(Lines!$AE$2:$AE$500),Docs!$AD$2:$AD$51,0))&"","")) | C12: =IF(A12<=COUNT(Lines!$AE$2:$AE$500),IFERROR(INDEX(Lines!$H$2:$H$500,MATCH(A12,Lines!$AE$2:$AE$500,0)),""),IFERROR("","")) | D12: =IF(A12<=COUNT(Lines!$AE$2:$AE$500),IFERROR(INDEX(Lines!$I$2:$I$500,MATCH(A12,Lines!$AE$2:$AE$500,0)),""),IFERROR("","")) | E12: =IF(A12<=COUNT(Lines!$AE$2:$AE$500),IFERROR(INDEX(Lines!$J$2:$J$500,MATCH(A12,Lines!$AE$2:$AE$500,0))&"",""),IFERROR("","")) | F12: =IF(A12<=COUNT(Lines!$AE$2:$AE$500),IFERROR(INDEX(Lines!$AD$2:$AD$500,MATCH(A12,Lines!$AE$2:$AE$500,0))&"",""),IFERROR(INDEX(Docs!$AC$2:$AC$51,MATCH(A12-COUNT(Lines!$AE$2:$AE$500),Docs!$AD$2:$AD$51,0))&"",""))
A13: 12 | B13: =IF(A13<=COUNT(Lines!$AE$2:$AE$500),IFERROR(INDEX(Lines!$E$2:$E$500,MATCH(A13,Lines!$AE$2:$AE$500,0))&"",""),IFERROR(INDEX(Docs!$C$2:$C$51,MATCH(A13-COUNT(Lines!$AE$2:$AE$500),Docs!$AD$2:$AD$51,0))&"","")) | C13: =IF(A13<=COUNT(Lines!$AE$2:$AE$500),IFERROR(INDEX(Lines!$H$2:$H$500,MATCH(A13,Lines!$AE$2:$AE$500,0)),""),IFERROR("","")) | D13: =IF(A13<=COUNT(Lines!$AE$2:$AE$500),IFERROR(INDEX(Lines!$I$2:$I$500,MATCH(A13,Lines!$AE$2:$AE$500,0)),""),IFERROR("","")) | E13: =IF(A13<=COUNT(Lines!$AE$2:$AE$500),IFERROR(INDEX(Lines!$J$2:$J$500,MATCH(A13,Lines!$AE$2:$AE$500,0))&"",""),IFERROR("","")) | F13: =IF(A13<=COUNT(Lines!$AE$2:$AE$500),IFERROR(INDEX(Lines!$AD$2:$AD$500,MATCH(A13,Lines!$AE$2:$AE$500,0))&"",""),IFERROR(INDEX(Docs!$AC$2:$AC$51,MATCH(A13-COUNT(Lines!$AE$2:$AE$500),Docs!$AD$2:$AD$51,0))&"",""))
... A101: 100 | B101: =IF(A101<=COUNT(Lines!$AE$2:$AE$500),IFERROR(INDEX(Lines!$E$2:$E$500,MATCH(A101,Lines!$AE$2:$AE$500,0))&"",""),IFERROR(INDEX(Docs!$C$2:$C$51,MATCH(A101-COUNT(Lines!$AE$2:$AE$500),Docs!$AD$2:$AD$51,0))&"","")) | C101: =IF(A101<=COUNT(Lines!$AE$2:$AE$500),IFERROR(INDEX(Lines!$H$2:$H$500,MATCH(A101,Lines!$AE$2:$AE$500,0)),""),IFERROR("","")) | D101: =IF(A101<=COUNT(Lines!$AE$2:$AE$500),IFERROR(INDEX(Lines!$I$2:$I$500,MATCH(A101,Lines!$AE$2:$AE$500,0)),""),IFERROR("","")) | E101: =IF(A101<=COUNT(Lines!$AE$2:$AE$500),IFERROR(INDEX(Lines!$J$2:$J$500,MATCH(A101,Lines!$AE$2:$AE$500,0))&"",""),IFERROR("","")) | F101: =IF(A101<=COUNT(Lines!$AE$2:$AE$500),IFERROR(INDEX(Lines!$AD$2:$AD$500,MATCH(A101,Lines!$AE$2:$AE$500,0))&"",""),IFERROR(INDEX(Docs!$AC$2:$AC$51,MATCH(A101-COUNT(Lines!$AE$2:$AE$500),Docs!$AD$2:$AD$51,0))&"",""))
